Workbook

Sheet JANUARI
A1: BARANG MASUK ARAW FILM | K1: BON JATUH TEMPO MEI 2021 ( JT)
A2: TGL MASUK | B2: NAMA BARANG | C2: SUPLIER | D2: QTY | E2: SAT | F2: HARGA/PCS/SET | G2: JUMLAH | H2: TOTAL FAKTUR | I2: KET | K2: NO | L2: TGL BARANG MASUK | M2: NAMA SALES/ SUPLIER | N2: JUMLAH BON | O2: KET
A3: 44198 | B3: SARUNG JOK INNOVA LUXURY MB 8808 | C3: B'IDA | D3: 1 | E3: SET | K3: 1 | L3: 44158 | M3: PB.IRWAN | N3: 4000000 | O3: GIRO 25/5/21
B4: SARUNG JOK INNOVA LUXURY MB 9001 +9010 | C4: B'IDA | D4: 1 | E4: SET | K4: 2 | L4: 44161 | M4: PB.IRWAN | N4: 1800000 | O4: GIRO 25/5/21
A5: 44200 | B5: FRONT GUARD (PLANG DEPAN) PAJERO '19 RHINO | C5: TJM | D5: 1 | E5: SET | F5: 2150000 | G5: =F5*D5 -> 2150000 | H5: =SUM(G5) -> 2150000 | I5: JUNI | J5: LUNAS TF 30/1 | K5: 3 | L5: 44163 | M5: PB.LEO | N5: 11700000 | O5: GIRO 15/5/21
A6: 44200 | B6: TALANG AIR H-TECH HITAM ALL NEW PAJERO'16 D/T | C6: MR.BOSS | D6: 5 | E6: SET | F6: 123000 | G6: =F6*D6 -> 615000 | H6: =SUM(G6) -> 615000 | I6: MEI | J6: LUNAS TF.6/4/21 | K6: 4 | L6: 44166 | M6: MR.BOSS | N6: 1040000 | O6: GIRO 20/5/21
A7: 44200 | B7: OUTER COVER ELEGANT BLACKTIVO JAZZ | C7: JSL | D7: 5 | E7: SET | F7: 135000 | G7: =F7*D7 -> 675000 | H7: =SUM(G7:G9) -> 2675000 | I7: RENCANA CASH BLN MARET | K7: 5 | L7: 44166 | M7: MR.BOSS | N7: 1235000 | O7: GIRO 20/5/21
B8: HANDLE COVER BLACKTIVO JAZZ | C8: JSL | D8: 5 | E8: SET | F8: 100000 | G8: =F8*D8 -> 500000 | K8: 6 | L8: 44166 | M8: MR.BOSS | N8: 1570000 | O8: GIRO 20/5/21
B9: SIDE SCUFF PLATE ACTIVO SPORTY W/LAMP AN RUSH | C9: JSL | D9: 5 | E9: SET | F9: 300000 | G9: =F9*D9 -> 1500000 | K9: 7 | L9: 44167 | M9: HENDRIK | N9: 1800000 | O9: GIRO 10/5/21
A10: 44204 | B10: STRETCHER AMBULANCE YDC 3B | C10: GM | D10: 1 | E10: SET | G10: =F10*D10 -> 0 | I10: LUNAS | K10: 8 | L10: 44172 | M10: MR.BOSS | N10: 750000 | O10: GIRO 20/5/21
A11: 44204 | B11: SARUNG JOK RUSH'20 MB 9001 + 9005 | C11: B'IDA | D11: 1 | E11: SET | G11: =F11*D11 -> 0 | K11: 9 | L11: 44172 | M11: MR.BOSS | N11: 2250000 | O11: GIRO 20/5/21
B12: SARUNG JOK XPANDER MB 9001 + 9008 | C12: B'IDA | D12: 1 | E12: SET | G12: =F12*D12 -> 0 | K12: 10 | L12: 44172 | M12: HENDRIK | N12: 3050000 | O12: GIRO 10/5/21
A13: 44205 | B13: BALANCE ARM FORTUNER MERAH | C13: IRWAN | D13: 2 | E13: SET | F13: 1800000 | G13: =F13*D13 -> 3600000 | H13: =SUM(G13:G19) -> 22900000 | I13: JUNI | J13: 44292 | K13: 11 | L13: 44173 | M13: PB.IRWAN | N13: 12515000 | O13: GIRO 25/5/21
B14: LIS GRILL HITAM BRIO'20 ORI | C14: IRWAN | D14: 15 | E14: SET | F14: 200000 | G14: =F14*D14 -> 3000000 | K14: 13 | L14: 44176 | M14: PB.IRWAN | N14: 15000000 | O14: GIRO 25/5/21
B15: SPOILER BRIO MERAH | C15: IRWAN | D15: 10 | E15: SET | F15: 400000 | G15: =F15*D15 -> 4000000 | K15: 14 | L15: 44177 | M15: SALIM (MOBILINDO) | N15: 4760000 | O15: GIRO 30/5/21
B16: SPOILER BRIO PUTIH | C16: IRWAN | D16: 6 | E16: SET | F16: 400000 | G16: =F16*D16 -> 2400000 | K16: 15 | L16: 44181 | M16: SALIM (MOBILINDO) | N16: 2375000 | O16: GIRO 30/5/21
B17: SPOILER BRIO SILVER | C17: IRWAN | D17: 5 | E17: SET | F17: 400000 | G17: =F17*D17 -> 2000000 | K17: 16 | L17: 44181 | M17: SALIM (MOBILINDO) | N17: 6300000 | O17: GIRO 30/5/21
B18: SPOILER BRIO HITAM | C18: IRWAN | D18: 4 | E18: SET | F18: 400000 | G18: =F18*D18 -> 1600000 | K18: 17 | L18: 44182 | M18: JKI | N18: 4400000 | O18: GIRO 30/5/21
B19: FOGLAMP BRIO DLAA | C19: IRWAN | D19: 12 | E19: SET | F19: 525000 | G19: =F19*D19 -> 6300000 | K19: 18 | L19: 44186 | M19: MR.BOSS | N19: 8920000 | O19: GIRO 15/5/21
A20: 44205 | B20: KARPET MI 3 RAY BLACK GREY | C20: MR.BOSS | D20: 2 | E20: SET | F20: 425000 | G20: =F20*D20 -> 850000 | H20: =SUM(G20:G22) -> 4400000 | I20: JUNI | J20: 44292 | K20: 19 | L20: 44191 | M20: HENDRIK | N20: 9630000 | O20: GIRO 30/5/21
B21: KARPET MI 3 RAY COFFE BEIGE | C21: MR.BOSS | D21: 5 | E21: SET | F21: 425000 | G21: =F21*D21 -> 2125000 | K21: 20 | L21: 44195 | M21: SALIM (MOBILINDO) | N21: 4000000 | O21: GIRO 30/5/21
B22: KARPET MI 2 RAY BLACK GREY | C22: MR.BOSS | D22: 5 | E22: SET | F22: 285000 | G22: =F22*D22 -> 1425000 | K22: 21 | L22: 44200 | M22: MR.BOSS | N22: 615000 | O22: LUNAS 06/04/2021
A23: 44205 | B23: GARNIS LAMPU DEPAN HILUX'20 HITAM WITH LOGO | C23: HENDRIK | D23: 3 | E23: SET | F23: 175000 | G23: =F23*D23 -> 525000 | H23: =SUM(G23:G28) -> 4025000 | I23: JUNI TGL 10 | J23: 44249 | K23: 22 | L23: 44214 | M23: NVM | N23: 1110000 | O23: LUNAS TF 15/2
B24: GARNIS LAMPU BELAKANG HILUX'20 HITAM WITH LOGO | C24: HENDRIK | D24: 3 | E24: SET | F24: 175000 | G24: =F24*D24 -> 525000 | K24: 23 | L24: 44216 | M24: NVM(HANDOYO) | N24: 3660000 | O24: GIRO 30/5/21
B25: GARNIS LAMPU DEPAN RUSH'18 HITAM | C25: HENDRIK | D25: 5 | E25: SET | F25: 135000 | G25: =F25*D25 -> 675000 | K25: 24 | L25: 44231 | M25: HENDRIK | N25: 10800000 | O25: GIRO 30/5/21
B26: GARNIS LAMPU BELAKANG RUSH'18 HITAM | C26: HENDRIK | D26: 5 | E26: SET | F26: 150000 | G26: =F26*D26 -> 750000 | K26: 25 | L26: 44249 | M26: KO AKHON | N26: 7350000 | O26: LUNAS TF. 18/5/21
B27: GARNIS LAMPU DEPAN PAJERO'18 HITAM | C27: HENDRIK | D27: 5 | E27: SET | F27: 135000 | G27: =F27*D27 -> 675000 | K27: 26 | L27: 44250 | M27: TJM | N27: 2150000 | O27: LUNAS TF. 18/5/21
B28: GARNIS LAMPU BELAKANG PAJERO'18 HITAM | C28: HENDRIK | D28: 5 | E28: SET | F28: 175000 | G28: =F28*D28 -> 875000 | K28: 27 | L28: 44263 | M28: OTO PROJECT | N28: 4374000 | O28: LUNAS TF. 29/4/21
A29: 44205 | B29: KACA FILM WB 70i+ (1809200207K2A1) | C29: WINCOS | D29: 1 | E29: ROL | G29: =F29*D29 -> 0 | K29: 28 | L29: 44322 | M29: HENDRIK | N29: 3750000 | O29: LUNAS TF.18/5/21
A30: 44207 | B30: TOWING BELAKANG MCC (PLANG BELAKANG) PAJERO | C30: NVM | D30: 4 | E30: SET | F30: 1250000 | G30: =F30*D30 -> 5000000 | H30: =G30 -> 5000000 | I30: APRIL | J30: 44242 | K30: 29 | L30: 44343 | M30: HENDRIK | N30: 3750000 | O30: LUNAS TF. 01/6/21
A31: 44209 | B31: TV ANDROID 10' ENIGMA | C31: SALIM(MOBILINDO) | D31: 3 | E31: SET | F31: 2000000 | G31: =F31*D31 -> 6000000 | H31: =G31 -> 6000000 | I31: JUNI | J31: 44256
A32: 44211 | B32: SARUNG JOK G.AVANZA '20 HITAM | C32: B'IDA | D32: 2 | E32: SET | G32: =F32*D32 -> 0
B33: SARUNG JOK G.AVANZA '20 HITAM/GREY | C33: B'IDA | D33: 1 | E33: SET | G33: =F33*D33 -> 0 | N33: =SUM(N3:N32) -> 134654000
B34: SARUNG JOK G.AVANZA '20 HITAM/MERAH | C34: B'IDA | D34: 1 | E34: SET | G34: =F34*D34 -> 0
B35: SARUNG JOK G.AVANZA '20 HITAM/COKLAT | C35: B'IDA | D35: 1 | E35: SET | G35: =F35*D35 -> 0
B36: SARUNG JOK RUSH'20 HITAM | C36: B'IDA | D36: 2 | E36: SET | G36: =F36*D36 -> 0
B37: SARUNG JOK CALYA '20 HITAM | C37: B'IDA | D37: 2 | E37: SET | G37: =F37*D37 -> 0
B38: SARUNG JOK BRIO '20 HITAM | C38: B'IDA | D38: 2 | E38: SET | G38: =F38*D38 -> 0
B39: SARUNG JOK BRIO '20 HITAM/GREY | C39: B'IDA | D39: 1 | E39: SET | G39: =F39*D39 -> 0
B40: SARUNG JOK BRIO '20 HITAM/MERAH | C40: B'IDA | D40: 1 | E40: SET | G40: =F40*D40 -> 0
A41: 44212 | B41: VALEO WIPER CB 16' 400MM | C41: JSL | D41: 50 | E41: SET | F41: 21000 | G41: =F41*D41 -> 1050000 | H41: =SUM(G41:G46) -> 4410000 | I41: =SUM(H41:H52) -> 10323000
B42: VALEO WIPER CB 17' 425MM | C42: JSL | D42: 40 | E42: SET | F42: 21000 | G42: =F42*D42 -> 840000 | I42: JUNI
B43: VALEO WIPER CB 18' 450MM | C43: JSL | D43: 50 | E43: SET | F43: 21000 | G43: =F43*D43 -> 1050000 | J43: 44275
B44: VALEO WIPER CB 20' 500MM | C44: JSL | D44: 30 | E44: SET | F44: 23000 | G44: =F44*D44 -> 690000
B45: VALEO WIPER CB 22' 550MM | C45: JSL | D45: 30 | E45: SET | F45: 26000 | G45: =F45*D45 -> 780000
B46: VALEO WIPER CB 14' 350MM | C46: JSL | D46: 50 | E46: SET | F46: BONUS
B47: BRIO/AN BRIO'18 SIDE SCUFF PLATE BLACK | C47: JSL | D47: 10 | E47: SET | F47: 50000 | G47: =F47*D47 -> 500000 | H47: =SUM(G47:G50) -> 2450000 | J47: GRATIS 1
B48: AN PAJERO'16 SIDE SCUFF PLATE BLACK | C48: JSL | D48: 10 | E48: SET | F48: 85000 | G48: =F48*D48 -> 850000 | J48: GRATIS 1
B49: AVANZA/AGYA/AYLA HANDLE COVER EXCLUSIVE CHROME | C49: JSL | D49: 10 | E49: SET | F49: 25000 | G49: =F49*D49 -> 250000 | J49: GRATIS 1
B50: BRIO/AN BRIO'18 OUTER COVER ELEGANT CHROME | C50: JSL | D50: 10 | E50: SET | F50: 85000 | G50: =F50*D50 -> 850000 | J50: GRATIS 1
B51: BESTCO CAR COVER AN BRIO 18 | C51: JSL | D51: 15 | E51: SET | F51: 105000 | G51: =F51*D51 -> 1575000 | H51: =SUM(G51:G52) -> 3463000
B52: BESTCO CAR COVER AN RUSH/ TERIOS 18 | C52: JSL | D52: 16 | E52: SET | F52: 118000 | G52: =F52*D52 -> 1888000
A53: 44212 | B53: LAMPU POLISI LED MERAH | C53: IRWAN | D53: 1 | E53: SET | F53: 3200000 | G53: =F53*D53 -> 3200000 | H53: =SUM(G53) -> 3200000 | I53: JUNI | J53: 44292
A54: 44212 | B54: KACA FILM WINTERBLAST HCD 30G C 70 (2004230109EGAI) | C54: WINCOWS | D54: 1 | E54: SET | G54: =F54*D54 -> 0
A55: 44214 | B55: FOOT STEP(TANGGA SAMPING) REVO ORI ( HILUX) | C55: GREAT (KO OKHON) | D55: 1 | E55: SET | F55: 1650000 | G55: =F55*D55 -> 1650000 | H55: =SUM(G55:G56) -> 7350000 | I55: JUNI | J55: LUNAS TF. 18/5/21
B56: GARNISH LAMPU BELAKANG FORTUNER | C56: GREAT (KO OKHON) | D56: 6 | E56: SET | F56: 950000 | G56: =F56*D56 -> 5700000
A57: 44214 | B57: GARNISH LAMPU BELAKANG FORTUNER | C57: OTOPROJECT | D57: 1 | E57: SET | F57: 4450000 | G57: =F57*D57 -> 4450000 | H57: =SUM(G57) -> 4450000 | I57: MARET | J57: LUNAS TF 13/3
A58: 44214 | B58: OUTER PLASTIK CHROME MITSUBISHI MIRAGE | C58: MR.BOSS | D58: 2 | E58: SET | F58: 100000 | G58: =F58*D58 -> 200000 | H58: =SUM(G58:G60) -> 415000 | I58: JUNI | J58: 44292
B59: DOOR HANDLE PLASTIK CHROME MITSUBISHI MIRAGE | C59: MR.BOSS | D59: 2 | E59: SET | F59: 80000 | G59: =F59*D59 -> 160000
B60: TANK COVER M.TAWON MIRAGE(HITAM) | C60: MR.BOSS | D60: 2 | E60: SET | F60: 27500 | G60: =F60*D60 -> 55000
A61: 44214 | B61: KARPET DASAR PAJERO SPORT'16 - ON BLACK | C61: NVM | D61: 6 | E61: SET | F61: 185000 | G61: =F61*D61 -> 1110000 | H61: =SUM(G61) -> 1110000 | I61: MEI | J61: LUNAS TF 15/2
A62: 44214 | B62: HRV HANDLE COVER FRONT CHROME | C62: JSL | D62: 5 | E62: SET | F62: 62000 | G62: =F62*D62 -> 310000 | H62: =SUM(G62:G72) -> 5360000 | I62: =SUM(H62:H81) -> 16500000 | J62: 44275
B63: AN RUSH '18 TRD FOGLAMP COVER CHROME | C63: JSL | D63: 5 | E63: SET | F63: 125000 | G63: =F63*D63 -> 625000 | I63: JUNI
B64: AN INNOVA'16 TRUNKLID FULL CHROME | C64: JSL | D64: 3 | E64: SET | F64: 150000 | G64: =F64*D64 -> 450000
B65: AN BRIO'18 REAR WINDOW TRIM CHROME | C65: JSL | D65: 5 | E65: SET | F65: 90000 | G65: =F65*D65 -> 450000
B66: HRV HANDLE COVER REAR CHROME | C66: JSL | D66: 5 | E66: SET | F66: 60000 | G66: =F66*D66 -> 300000
B67: AN PAJERO'16 OUTER COVER ELEGANT CHROME | C67: JSL | D67: 5 | E67: SET | F67: 85000 | G67: =F67*D67 -> 425000
B68: AN PAJERO'16 HEAD LAMP GARNISH CHROME | C68: JSL | D68: 5 | E68: SET | F68: 110000 | G68: =F68*D68 -> 550000
B69: AN PAJERO'16 TAIL LAMP GARNISH CHROME | C69: JSL | D69: 5 | E69: SET | F69: 125000 | G69: =F69*D69 -> 625000
B70: AN INNOVA '16 HEAD LAMP GARNISH EXCLUSIVE CHROME | C70: JSL | D70: 5 | E70: SET | F70: 110000 | G70: =F70*D70 -> 550000
B71: AN INNOVA'16 TAIL LAMP GARNISH EXCLUSIVE CHROME | C71: JSL | D71: 5 | E71: SET | F71: 125000 | G71: =F71*D71 -> 625000
B72: HRV OUTER HANDLE COVER ELEGANT CHROME | C72: JSL | D72: 5 | E72: SET | F72: 90000 | G72: =F72*D72 -> 450000
B73: AN RUSH '18 /TERIOS HANDLE COVER KEYLESS BLACKTIVO | C73: JSL | D73: 10 | E73: SET | F73: 65000 | G73: =F73*D73 -> 650000 | H73: =SUM(G73:G79) -> 6100000
B74: AN BRIO '18 TAIL LAMP GARNISH BLACKTIVO | C74: JSL | D74: 10 | E74: SET | F74: 100000 | G74: =F74*D74 -> 1000000
B75: MOBILIO /BRIO HEAD LAMP GARNISH BLACKTIVO | C75: JSL | D75: 10 | E75: SET | F75: 110000 | G75: =F75*D75 -> 1100000
B76: INNOVA'16 SIDE SCUFF PLATE BLACK | C76: JSL | D76: 10 | E76: SET | F76: 55000 | G76: =F76*D76 -> 550000
B77: AN AVANZA/CALYA '16/ SIGRA'16 HANDLE COVER CHROME | C77: JSL | D77: 10 | E77: SET | F77: 55000 | G77: =F77*D77 -> 550000
B78: AVANZA OUTER COVER ELEGANT | C78: JSL | D78: 20 | E78: SET | F78: 85000 | G78: =F78*D78 -> 1700000
B79: AVANZA/CALYA/SIGRA'16 HANDLE COVER CHROME | C79: JSL | D79: 10 | E79: SET | F79: 55000 | G79: =F79*D79 -> 550000
B80: BESTCO CAR COVER PAJERO'16 | C80: JSL | D80: 20 | E80: SET | F80: 142000 | G80: =F80*D80 -> 2840000 | H80: =SUM(G80:G81) -> 5040000
B81: BESTCO CAR COVER AVANZA | C81: JSL | D81: 20 | E81: SET | F81: 110000 | G81: =F81*D81 -> 2200000
A82: 44216 | B82: KARPET DASAR AGYA HITAM | C82: NVM(HANDOYO) | D82: 10 | E82: SET | F82: 170000 | G82: =F82*D82 -> 1700000 | H82: =SUM(G82:G84) -> 3630000 | I82: MEI | J82: 44242
B83: KARPET DASAR BRIO HITAM | C83: NVM(HANDOYO) | D83: 5 | E83: SET | F83: 170000 | G83: =F83*D83 -> 850000
B84: KARPET DASAR RUSH HITAM | C84: NVM(HANDOYO) | D84: 6 | E84: SET | F84: 180000 | G84: =F84*D84 -> 1080000
A85: 44216 | B85: PARFUM DEO SCENTS COFFEE | C85: PARFUM | D85: 36 | E85: DUS | F85: 18500 | G85: =F85*D85 -> 666000 | H85: =SUM(G85:G90) -> 1290000 | I85: FEBRUARI
B86: PARFUM DORFREE KERTAS MORNING DEW | D86: 10 | E86: SET | F86: 13000 | G86: =F86*D86 -> 130000
B87: PARFUM DORFREE KERTAS FRUITY | D87: 10 | E87: SET | F87: 13000 | G87: =F87*D87 -> 130000
B88: PARFUM DORFREE KERTAS TROPICAL FRUITY | D88: 12 | E88: SET | F88: 13000 | G88: =F88*D88 -> 156000
B89: PARFUM DORFREE KERTAS HAWAIAN SWEET | D89: 10 | E89: PCS | F89: 13000 | G89: =F89*D89 -> 130000
B90: PARFUM DORFREE KERTAS STRAWBERRY | D90: 6 | E90: PCS | F90: 13000 | G90: =F90*D90 -> 78000
A91: 44217 | B91: F/S (TANGGA SAMPING)FORTUNER 12 (MDL ORI) | C91: TJM | D91: 1 | E91: SET | F91: 2100000 | G91: =F91*D91 -> 2100000 | H91: 2100000 | I91: FEBRUARI | J91: LUNAS TF 04/06/2021
A92: 44219 | B92: AVANZA/AGYA/AYLA HANDLE COVER EXCLUSIVE BLACKTIVO | C92: JSL | D92: 10 | E92: SET | F92: 25000 | G92: =F92*D92 -> 250000 | H92: =SUM(G92:G93) -> 2250000 | I92: =SUM(H92:H97) -> 9803000 | J92: 44275
B93: RUSH'18 SILTPLATE BELAKANG | C93: JSL | D93: 10 | E93: SET | F93: 200000 | G93: =F93*D93 -> 2000000 | I93: JUNI
B94: BESTCO BAR (BODY COVER) BRIO'18 | C94: JSL | D94: 15 | E94: SET | F94: 105000 | G94: =F94*D94 -> 1575000 | H94: =SUM(G94:G95) -> 3775000
B95: BESTCO BAR (BODY COVER) CALYA/SIGRA'16 | C95: JSL | D95: 20 | E95: SET | F95: 110000 | G95: =F95*D95 -> 2200000
B96: BESTCO BAR (BODY COVER) INNOVA'16 | C96: JSL | D96: 20 | E96: SET | F96: 124000 | G96: =F96*D96 -> 2480000 | H96: =SUM(G96:G97) -> 3778000
B97: BESTCO BAR (BODY COVER) MOBILIO | C97: JSL | D97: 11 | E97: SET | F97: 118000 | G97: =F97*D97 -> 1298000
A98: 44219 | B98: KACA FILM ANTI GORES-BLACK 20% | C98: JKI | D98: 2 | E98: ROL | F98: 1100000 | G98: =F98*D98 -> 2200000 | I98: JUNI | J98: LUNAS TF. 01/7/21
A99: 44219 | B99: KACA FILM 3M 60% | C99: DHARMESTA | D99: 1 | E99: ROL
A100: 44222 | B100: KARPET DASAR BRIO HITAM TIPIS | C100: PB.HERMAN | D100: 30 | E100: SET | F100: 150000 | G100: =F100*D100 -> 4500000 | H100: =G100 -> 4500000 | I100: JUNI | J100: 44250
...

Sheet FEBRUARI
A1: BARANG MASUK ARAW FILM
A2: TGL MASUK | B2: NAMA BARANG | C2: SUPLIER | D2: QTY | E2: SAT | F2: HARGA/PCS/SET | G2: JUMLAH | H2: TOTAL FAKTUR | I2: KET | M2: BON JATUH TEMPO JUNI 2021 ( JT)
A3: 44228 | B3: KARPET KARET 3PC HITAM | C3: HERMAN | D3: 6 | E3: SET | F3: 145000 | G3: =F3*D3 -> 870000 | H3: =SUM(G3) -> 870000 | I3: JUNI | J3: 44250 | M3: NO | N3: TGL BARANG MASUK | O3: NAMA SALES/ SUPLIER | P3: JUMLAH BON | Q3: KET
A4: 44228 | B4: KARPET DASAR AGYA BLACK | C4: NVM | D4: 10 | E4: SET | F4: 170000 | G4: =F4*D4 -> 1700000 | H4: =SUM(G4:G5) -> 3400000 | I4: APRIL | J4: 44242 | M4: 1 | N4: 44196 | O4: IRWAN | P4: 6175000 | Q4: GIRO 15/06/2021 | R4: V | T4: =P11+P15+P16 -> 36626000 | U4: 3463
B5: KARPET DASAR BRIO BLACK | C5: NVM | D5: 10 | E5: SET | F5: 170000 | G5: =F5*D5 -> 1700000 | M5: 2 | N5: 44200 | O5: TJM | P5: 2150000 | Q5: LUNAS TF 4/6/2021 | U5: 4410
A6: 44228 | B6: AVANZA/AGYA/AYLA OUTER CHROME | C6: JSL | D6: 10 | E6: SET | F6: TITIPAN | M6: 3 | N6: 44205 | O6: IRWAN | P6: 22900000 | Q6: GIRO 30/06/2021 | S6: =P6+P9+P13+P21+P12 -> 41770000 | U6: 2450
B7: MOBILIO/BRIO/BRV'16 HANDLE HITAM | C7: JSL | D7: 10 | E7: SET | F7: 70000 | G7: =F7*D7 -> 700000 | H7: =SUM(G7:G8) -> 2700000 | I7: JULI | J7: 44275 | M7: 4 | N7: 44205 | O7: MR.BOSS | P7: 4400000 | Q7: GIRO 12/6/2021 | R7: V | T7: =P7+P14 -> 4815000 | U7: 5040
B8: BRIO'18 SCUFF PLATE ACTIVO W/REFLECTOR | C8: JSL | D8: 10 | E8: SET | F8: 200000 | G8: =F8*D8 -> 2000000 | M8: 5 | N8: 44205 | O8: HENDRIK | P8: 4025000 | Q8: GIRO 10/6/2021 | R8: V | U8: 6100
B9: RUSH/TERIOS/AVANZA/XENIA'19 MIROR COVER BLACK | C9: JSL | D9: 5 | E9: SET | F9: 100000 | G9: =F9*D9 -> 500000 | H9: =SUM(G9) -> 500000 | M9: 6 | N9: 44209 | O9: SALIM (MOBILINDO) | P9: 6000000 | Q9: GIRO 30/6/2021 | U9: 5360
A10: 44229 | B10: KARPET DASAR BRIO TIPIS | C10: IRWAN | D10: 100 | E10: SET | F10: 160000 | G10: =F10*D10 -> 16000000 | H10: =SUM(G10:G15) -> 19801200 | I10: JULI | J10: 44292 | M10: 7 | N10: 44531 | O10: HENDRIK | P10: 4050000 | Q10: LUNAS | U10: 3778
B11: KARPET KARET SMOKE TRANSPARAN | C11: IRWAN | D11: 4 | E11: SET | F11: 225000 | G11: =F11*D11 -> 900000 | M11: 8 | N11: 44212 | O11: JSL | P11: 10323000 | Q11: GIRO 15/6/21 | R11: V | T11: =P11+P15+P16 -> 36626000 | U11: 3775
B12: FIRE STOP (RACUN API) | C12: IRWAN | D12: 12 | E12: SET | F12: 20000 | G12: =F12*D12 -> 240000 | M12: 9 | N12: 44212 | O12: IRWAN | P12: 3200000 | Q12: GIRO 30/06/2021 | S12: =S6+R39 -> 100381000 | U12: 2250
B13: LAMPU SOROT ATAP 90CM | C13: IRWAN | D13: 1 | E13: SET | F13: 900000 | G13: =F13*D13 -> 900000 | M13: 10 | N13: 44249 | O13: NVM | P13: 6250000 | Q13: GIRO 30/6/21 | T13: =P13+P21 -> 9670000
B14: LAMPU SOROT ATAP 110CM | C14: IRWAN | D14: 1 | E14: SET | F14: 950000 | G14: =F14*D14 -> 950000 | M14: 11 | N14: 44214 | O14: MR.BOSS | P14: 415000 | Q14: GIRO 12/6/2021 | R14: V | U14: =SUM(U4:U13) -> 36626
B15: DAUBLE TIPE HIJAU | C15: IRWAN | D15: 208 | E15: SET | F15: 3900 | G15: =F15*D15 -> 811200 | M15: 12 | N15: 44214 | O15: JSL | P15: 16500000 | Q15: GIRO 15/6/21 | R15: V | T15: =SUM(P13+P21) -> 9670000
A16: 44231 | B16: HANDLE AVANZA VELOZ HITAM | C16: HENDRIK | D16: 5 | E16: SET | F16: 75000 | G16: =F16*D16 -> 375000 | H16: =SUM(G16:G29) -> 10800000 | I16: MEI | J16: 44249 | M16: 13 | N16: 44219 | O16: JSL | P16: 9803000 | Q16: GIRO 15/6/21 | R16: V
B17: HANDLE DEPAN HRV KEYLESS HITAM | C17: HENDRIK | D17: 5 | E17: SET | F17: 65000 | G17: =F17*D17 -> 325000 | M17: 14 | N17: 44219 | O17: JKI | P17: 2200000 | Q17: LUNAS TF. 01/7/21
B18: HANDLE PAJERO'16 HITAM | C18: HENDRIK | D18: 10 | E18: SET | F18: 110000 | G18: =F18*D18 -> 1100000 | M18: 15 | N18: 44222 | O18: PB.HERMAN | P18: 4500000 | Q18: GIRO 18/6/2021 | R18: V | S18: =SUM(P7+P14+P22) -> 6415000 | U18: 44252
B19: HANDLE BRIO HITAM | C19: HENDRIK | D19: 20 | E19: SET | F19: 80000 | G19: =F19*D19 -> 1600000 | M19: 16 | N19: 44249 | O19: NVM | P19: 1050000 | Q19: CASH 31/8/21
B20: TANKI HRV HITAM | C20: HENDRIK | D20: 5 | E20: SET | F20: 40000 | G20: =F20*D20 -> 200000 | M20: 17 | N20: 44228 | O20: HERMAN | P20: 870000 | Q20: GIRO 18/6/2021 | R20: V | S20: =P7+P14 -> 4815000 | U20: 44252
B21: TANKI BRIO HITAM | C21: HENDRIK | D21: 15 | E21: SET | F21: 35000 | G21: =F21*D21 -> 525000 | M21: 18 | N21: 44259 | O21: NVM | P21: 3420000 | Q21: GIRO 30/6/21
B22: TANKI RUSH HITAM | C22: HENDRIK | D22: 10 | E22: SET | F22: 40000 | G22: =F22*D22 -> 400000 | M22: 20 | N22: 44249 | O22: MR.BOSS | P22: 1600000 | Q22: GIRO 30/6/21 | R22: V
B23: . | C23: HENDRIK | D23: 15 | E23: SET | F23: 35000 | G23: =F23*D23 -> 525000 | M23: 21 | N23: 44316 | O23: WINCOS | P23: 30800000 | Q23: LUNAS 28/6/21
B24: HANDLE OUTER BELAKANG HRV HITAM (2PCS) | C24: HENDRIK | D24: 5 | E24: SET | F24: 75000 | G24: =F24*D24 -> 375000 | T24: 1-15 juni
B25: HANDLE OUTER BELAKANG HRV HITAM (6PCS) | C25: HENDRIK | D25: 5 | E25: SET | F25: 125000 | G25: =F25*D25 -> 625000 | P25: =SUM(P4:P24) -> 140631000 | Q25: total | T25: 6175000 | U25: herman
B26: OUTER BRIO HITAM | C26: HENDRIK | D26: 20 | E26: SET | F26: 100000 | G26: =F26*D26 -> 2000000 | T26: 4025000 | U26: hendrik
B27: OUTER INNOVA'16 CHROME | C27: HENDRIK | D27: 10 | E27: SET | F27: 125000 | G27: =F27*D27 -> 1250000 | P27: =P4+P6+P7+P8+P9+P11+P12+P13+P14+P15+P16+P18+P20+P21+P22 -> 100381000 | Q27: giro | T27: 36626000 | U27: jsl
B28: GARNIS LAMPU DEPAN HRV'20 HITAM | C28: HENDRIK | D28: 5 | E28: SET | F28: 140000 | G28: =F28*D28 -> 700000 | T28: 4815000 | U28: mr.boss
B29: GARNIS LAMPU BELAKANG HRV'20 HITAM | C29: HENDRIK | D29: 5 | E29: SET | F29: 160000 | G29: =F29*D29 -> 800000 | P29: =P5+P10+P23 -> 37000000 | Q29: lunas tf
A30: 44232 | B30: KACA FILM SRC 60-BLACK (ANTI GORES 60% SLR) | C30: JKI | D30: 2 | E30: ROL | F30: 1100000 | G30: =F30*D30 -> 2200000 | H30: =G30 -> 2200000 | I30: JULI | J30: LUNAS TF 14/8
A31: 44232 | B31: KACA FILM 4 MILI IR XT BLACK05 (KF CPF1 BLACK SECURITY 80%) | C31: JKI | D31: 1 | E31: ROL | F31: 9900000 | G31: =F31*D31 -> 9900000 | H31: =G31 -> 9900000 | P31: =P17+P19 -> 3250000 | Q31: blm bayar | T31: =SUM(T25:T30) -> 51641000 | V31: 60000000
A32: 44232 | B32: HOOD MOLDING INNOVA'16 | C32: JSL | D32: 3 | E32: PCS | F32: 110000 | G32: =F32*D32 -> 330000 | H32: =G32 -> 330000 | I32: JULI | J32: 44275 | V32: =V31-T31 -> 8359000
B33: OUTER BRIO HITAM | C33: JSL | D33: 10 | E33: SET | F33: 85000 | G33: =F33*D33 -> 850000 | H33: =G33 -> 850000 | I33: JULI | J33: 44275 | O33: GIRO YG DIBYR 60JT | P33: =P4+P7+P8+P11+P14+P15+P16+P18+P20+P22 -> 58611000 | Q33: V(ceklis) | R33: =T31+T35+T37 -> 58611000 | T33: 16-30 | V33: =V31-P33 -> 1389000
A34: 44233 | B34: SARUNG JOK RUSH 2021 (MB 9001 BLACK) | C34: B'IDA | D34: 1 | E34: SET | G34: =F34*D34 -> 0 | T34: 6000000 | U34: mobilindo
A35: 44235 | B35: HANDLE RUSH'18 SMARTKEY HITAM | C35: IRWAN | D35: 5 | E35: SET | F35: 85000 | G35: =F35*D35 -> 425000 | H35: =SUM(G35:G41) -> 2985000 | I35: JULI | J35: 44292 | T35: 5370000 | U35: herman
B36: SILICON KUNCI PAJERO'16 HITAM | C36: IRWAN | D36: 10 | E36: SET | F36: 18000 | G36: =F36*D36 -> 180000 | T36: 26100000 | U36: irwan
B37: SILICON KUNCI BRIO HITAM | C37: IRWAN | D37: 10 | E37: SET | F37: 18000 | G37: =F37*D37 -> 180000 | T37: 1600000 | U37: mr.boss
B38: COVER MITSUBISHI XPANDER HITAM D/B | C38: IRWAN | D38: 5 | E38: SET | F38: 130000 | G38: =F38*D38 -> 650000 | R38: =T31+T35 -> 57011000 | T38: 9670000 | U38: handoyo
B39: COVER MITSUBISHI XPANDER MERAH D/B | C39: IRWAN | D39: 5 | E39: SET | F39: 130000 | G39: =F39*D39 -> 650000 | R39: =R38+T37 -> 58611000
B40: DOOR GUARD BRAVO TOYOTA HITAM | C40: IRWAN | D40: 10 | E40: SET | F40: 45000 | G40: =F40*D40 -> 450000 | V40: =P6+P9+P12+P13+P21 -> 41770000
B41: DOOR GUARD BRAVO MITSUBISHI HITAM | C41: IRWAN | D41: 10 | E41: SET | F41: 45000 | G41: =F41*D41 -> 450000
A42: 44235 | B42: KACA FILM WINTERBLAST HCD 10G C 70 (2004230044EGAG) | C42: WINCOWS | D42: 1 | E42: ROL | G42: =F42*D42 -> 0 | I42: BRIO
B43: KACA FILM WINTERBLAST HCD 30G C 70 (2002030152K2A4) | C43: WINCOWS | D43: 1 | E43: ROL | G43: =F43*D43 -> 0 | I43: BRIO | V43: =V40+P33 -> 100381000
A44: 44239 | B44: RUSH/TERIOS'18 FOGLAMP COVER M/TRD BLACKTIVO | C44: JSL | D44: 2 | E44: SET | F44: 275000 | G44: =F44*D44 -> 550000 | H44: =SUM(G44) -> 550000 | I44: JULI | J44: 44275 | R44: =T31+#REF! -> #REF!
A45: 44239 | B45: LOGO HONDA CHROME BRIO BELAKANG | C45: HERMAN | D45: 100 | E45: SET | F45: 35000 | G45: =F45*D45 -> 3500000 | H45: =SUM(G45) -> 3500000 | I45: JULI | V45: 100000000
A46: 44240 | B46: FRONT GUARD PAJERO 19 RHINO (V-2) + LED + SWITCH | C46: TJM | D46: 1 | E46: SET | F46: 2800000 | G46: =F46*D46 -> 2800000 | H46: =SUM(G46) -> 2800000 | I46: APRIL | J46: LUNAS TF 10/4
A47: 44243 | B47: KACA FILM WINTERBLAST HCD 10G C 70 (2004230019EGAI) | C47: WINCOWS | D47: 1 | E47: ROL | I47: BRIO | V47: =V43-V45 -> 381000
B48: KACA FILM WINTERBLAST HCD 10G C 70 (2004230018EGAH) | C48: WINCOWS | D48: 1 | E48: ROL | I48: BRIO
B49: KACA FILM WINTERBLAST HCD 30G C 70 (2004240102EGAC) | C49: WINCOWS | D49: 1 | E49: ROL | I49: BRIO | R49: 6175000
A50: 44247 | B50: SARUNG JOK BRIO VARIASI HITAM+MERAH | C50: HERMAN | D50: 2 | E50: SET | F50: 625000 | G50: =F50*D50 -> 1250000 | H50: =G50+G51 -> 2500000 | I50: JULI | R50: 6000000
B51: SARUNG JOK BRIO VARIASI HITAM+CREAM | C51: HERMAN | D51: 2 | E51: SET | F51: 625000 | G51: =F51*D51 -> 1250000 | R51: 5370000
A52: 44247 | B52: KACA FILM WINCOS PREMIUM 50% | C52: WINCOWS | D52: 1 | E52: ROL | F52: 22000000 | G52: =F52*D52 -> 22000000 | H52: =G52 -> 22000000 | I52: LUNAS TF 16/2 | R52: 4025000
B53: KACA FILM WINCOS PREMIUM 80% | C53: WINCOWS | D53: 1 | E53: ROL | F53: 22000000 | G53: =F53*D53 -> 22000000 | H53: =G53 -> 22000000 | R53: 36626000
A54: 44249 | B54: SARUNG JOK INNOVA RIBON MB-TEACH(MB 9013+9012) | C54: B'IDA | D54: 1 | E54: SET | G54: =F54*D54 -> 0 | R54: 26100000
A55: 44249 | B55: BODY KIT/OVER FENDER PAJERO'16 MDL ROCKFOR | C55: MR.BOSS | D55: 1 | E55: SET | F55: 1600000 | G55: =F55*D55 -> 1600000 | H55: =G55 -> 1600000 | I55: GIRO 30/6/21 | R55: 4815000
A56: 44249 | B56: STIKER CARBON BLACK GLOSSY | C56: NVM | D56: 1 | E56: ROL | F56: 1600000 | G56: =F56*D56 -> 1600000 | H56: =SUM(G56:G67) -> 21550000 | I56: JULI | J56: GIRO 30/7/21 | R56: 1600000
B57: STIKER CARBON BLACK DOFF | C57: NVM | D57: 1 | E57: ROL | F57: 1600000 | G57: =F57*D57 -> 1600000 | R57: 9670000
B58: KABEL KLAKSON MX(RELAY BOSCH) | C58: NVM | D58: 10 | E58: SET | F58: 35000 | G58: =F58*D58 -> 350000
B59: TOWING BAR MCC RUSH/TERIOS'18 | C59: NVM | D59: 5 | E59: SET | F59: 1250000 | G59: =F59*D59 -> 6250000 | R59: =SUM(R49:R58) -> 100381000
B60: TOWING BAR MCC PAJERO SPORT FULL | C60: NVM | D60: 3 | E60: SET | F60: 1250000 | G60: =F60*D60 -> 3750000
B61: KLAKSON HELLA KEONG BIRU (TWIN TONE) 3 FH | C61: NVM | D61: 5 | E61: SET | F61: 110000 | G61: =F61*D61 -> 550000
B62: ANTENA SIRIP HIU HYBIRD BLACK | C62: NVM | D62: 10 | E62: SET | F62: 37500 | G62: =F62*D62 -> 375000
B63: ANTENA SIRIP HIU HYBIRD GREY (MS) | C63: NVM | D63: 10 | E63: SET | F63: 37500 | G63: =F63*D63 -> 375000
B64: TURBO TIMER TY INNOVA ALL NEW I-CONCEPT | C64: NVM | D64: 3 | E64: SET | F64: 675000 | G64: =F64*D64 -> 2025000
B65: SENSOR PARKING 2T LEOPARD | C65: NVM | D65: 5 | E65: SET | F65: 90000 | G65: =F65*D65 -> 450000
B66: CAMERA BLK ENIGMA (INFRA RED) JCS-606 | C66: NVM | D66: 15 | E66: SET | F66: 165000 | G66: =F66*D66 -> 2475000
B67: LAMPU ROOF LED (DOUBLE 90 CM) P1006K-2 BLUE-BLUE | C67: NVM | D67: 1 | E67: SET | F67: 1750000 | G67: =F67*D67 -> 1750000
A68: 44249 | B68: KLAKSON HELLA KEONG BLACK (TWIN TONE) 3 FH | C68: NVM | D68: 5 | E68: SET | F68: 210000 | G68: =F68*D68 -> 1050000 | H68: =SUM(G68) -> 1050000 | I68: JUNI
A69: 44249 | B69: TOWING BAR MCC XPANDER | C69: NVM | D69: 2 | E69: SET | F69: 1250000 | G69: =F69*D69 -> 2500000 | H69: =SUM(G69:G70) -> 6250000 | I69: GIRO 30/6/21
B70: TOWING BAR MCC FORTUNER/INNOVA | C70: NVM | D70: 3 | E70: SET | F70: 1250000 | G70: =F70*D70 -> 3750000
A71: 44249 | B71: KABEL LAMPU A VSS | C71: IRFAN | D71: 1 | E71: ROL | F71: 2200000 | G71: =F71*D71 -> 2200000 | H71: =SUM(G71) -> 2200000
A72: 44250 | B72: FRONT GUARD PAJERO 19 RHINO (V-2) | C72: TJM | D72: 1 | E72: SET | F72: 2150000 | G72: =F72*D72 -> 2150000 | H72: =SUM(G72) -> 2150000 | I72: LUNAS TF. 18/5/21
A73: 44251 | B73: KACA FILM WINTERBLAST HCD 10G C 70 (2004270009KA2D) | C73: WINCOWS | D73: 1 | E73: ROL | I73: BRIO
B74: KACA FILM WINTERBLAST HCD 10G C 70 (2004270012K2AJ) | C74: WINCOWS | D74: 1 | E74: ROL | I74: BRIO
B75: KACA FILM WINTERBLAST HCD 30G C 70 (2004240025EGAG) | C75: WINCOWS | D75: 1 | E75: ROL | I75: BRIO

Sheet MARET
A1: BARANG MASUK ARAW FILM | L1: BON JATUH TEMPO JULI 2021 ( JT)
A2: TGL MASUK | B2: NAMA BARANG | C2: SUPLIER | D2: QTY | E2: SAT | F2: HARGA/PCS/SET | G2: JUMLAH | H2: TOTAL FAKTUR | I2: KET | L2: NO | M2: TGL BARANG MASUK | N2: NAMA SALES/ SUPLIER | O2: JUMLAH BON | P2: KET
A3: 44256 | B3: SARUNG JOK BRIO HITAM MERAH | C3: NVM | D3: 2 | E3: SET | F3: 600000 | G3: =F3*D3 -> 1200000 | H3: =SUM(G3:G7) -> 3800000 | I3: GIRO 30/7/21 | L3: 1 | M3: 44226 | N3: MR. BOSS | O3: 780000 | P3: CHAS | U3: 44226 | V3: MR. BOSS | W3: 780000
B4: SARUNG JOK BRIO HITAM CREAM | C4: NVM | D4: 1 | E4: SET | F4: 600000 | G4: =F4*D4 -> 600000 | L4: 2 | M4: 44228 | N4: JSL | O4: 3200000 | P4: GIRO 15/7/21 | Q4: =O4+O8+O9+O11 -> 4930000 | R4: 2700
B5: SARUNG JOK BRIO HITAM PUTIH | C5: NVM | D5: 1 | E5: SET | F5: 600000 | G5: =F5*D5 -> 600000 | L5: 3 | M5: 44229 | N5: IRWAN | O5: 19801200 | P5: GIRO 30/7/21 | R5: 500
B6: SARUNG JOK RUSH HITAM MERAH | C6: NVM | D6: 1 | E6: SET | F6: 700000 | G6: =F6*D6 -> 700000 | L6: 4 | M6: 44232 | N6: JKI | O6: 2200000 | P6: LUNAS TF. 25/8/21 | R6: 330
B7: SARUNG JOK RUSH HITAM CREAM | C7: NVM | D7: 1 | E7: SET | F7: 700000 | G7: =F7*D7 -> 700000 | L7: 5 | M7: 44232 | N7: JKI | O7: 9900000 | P7: LUNAS TF TGL 14/8/21 | R7: 550
A8: 44256 | B8: GARNIS LAMPU DEPAN HRV'18 CHROME | C8: HENDRIK | D8: 2 | E8: SET | F8: 140000 | G8: =F8*D8 -> 280000 | H8: =SUM(G8:G12) -> 4150000 | I8: JULI | L8: 6 | M8: 44232 | N8: JSL | O8: 330000 | P8: GIRO 15/7/21 | R8: 850
B9: GARNIS LAMPU BELAKANG HRV'18 CHROME | C9: HENDRIK | D9: 2 | E9: SET | F9: 160000 | G9: =F9*D9 -> 320000 | L9: 7 | M9: 44232 | N9: JSL | O9: 850000 | P9: GIRO 15/7/21
B10: GARNIS LAMPU DEPAN HRV'18 BLACKDOFF | C10: HENDRIK | D10: 5 | E10: SET | F10: 140000 | G10: =F10*D10 -> 700000 | L10: 8 | M10: 44235 | N10: IRWAN | O10: 2985000 | P10: GIRO 30/7/21 | R10: =SUM(R4:R9) -> 4930
B11: GARNIS LAMPU DEPAN RUSH'18 BLACKDOFF | C11: HENDRIK | D11: 10 | E11: SET | F11: 135000 | G11: =F11*D11 -> 1350000 | L11: 9 | M11: 44239 | N11: JSL | O11: 550000 | P11: GIRO 15/7/21 | S11: =O12+O13 -> 6000000
B12: GARNIS LAMPU BELAKANG RUSH'18 BLACKDOFF | C12: HENDRIK | D12: 10 | E12: SET | F12: 150000 | G12: =F12*D12 -> 1500000 | L12: 10 | M12: 44239 | N12: HERMAN | O12: 3500000 | P12: GIRO 30/7/21 | R12: =O4+O8+O9+O11 -> 4930000
A13: 44257 | B13: FOGLAMP BRIO'18 (DRL) | C13: JSL | D13: 6 | E13: SET | F13: 400000 | G13: =F13*D13 -> 2400000 | H13: =SUM(G13) -> 2400000 | I13: AGUSTUS | J13: 44275 | L13: 11 | M13: 44247 | N13: HERMAN | O13: 2500000 | P13: GIRO 30/7/21 | R13: =SUM(O5+O10) -> 22786200
A14: 44258 | B14: KARPET MI 2 RAY ABU HITAM | C14: HERMAN | D14: 3 | E14: SET | F14: 285000 | G14: =F14*D14 -> 855000 | H14: =SUM(G14:G15) -> 1710000 | I14: GIRO AGUSTUS | L14: 12 | M14: 44249 | N14: NVM | O14: 21550000 | P14: GIRO 30/7/21
B15: KARPET MI 2 RAY CREAM COKLAT | C15: HERMAN | D15: 3 | E15: SET | F15: 285000 | G15: =F15*D15 -> 855000 | L15: 13 | M15: 44256 | N15: NVM | O15: 3800000 | P15: GIRO 30/7/21 | Q15: =SUM(O14+O15) -> 25350000 | T15: =SUM(O6:O7) -> 12100000
A16: 44258 | B16: KACA FILM SRC 80 BLACK (AG 80%) | C16: JKI | D16: 2 | E16: ROL | F16: 1100000 | G16: =F16*D16 -> 2200000 | H16: =SUM(G16) -> 2200000 | I16: AGUSTUS | L16: 14 | M16: 44260 | N16: ROYAL CITY | O16: 6000000 | P16: GIRO 30/7/21 | Q16: =O16+O18 -> 11403000 | R16: =SUM(O16+O18) -> 11403000
A17: 44259 | B17: TANKI INNOVA HITAM | C17: HENDRIK | D17: 5 | E17: SET | F17: 40000 | G17: =F17*D17 -> 200000 | H17: =SUM(G17:G28) -> 5820000 | I17: AGUSTUS | J17: 44301 | L17: 15 | M17: 44256 | N17: HENDRIK | O17: 4150000 | P17: GIRO 30/7/21
B18: OUTER INNOVA HITAM | C18: HENDRIK | D18: 5 | E18: SET | F18: 125000 | G18: =F18*D18 -> 625000 | J18: DI TAMBAH + DIFFUSER 13 SET (4.225.000) TOTAL Rp 10.045.000 | L18: 16 | M18: 44280 | N18: ROYAL CITY | O18: 5403000 | P18: GIRO 30/7/21 | R18: =SUM(O12:O13) -> 6000000
B19: HANDLE INNOVA HITAM | C19: HENDRIK | D19: 5 | E19: SET | F19: 110000 | G19: =F19*D19 -> 550000 | L19: 17 | M19: 44295 | N19: TJM | O19: 4300000 | P19: LUNAS 28/7/21
B20: TANKI YARIS'18 HITAM | C20: HENDRIK | D20: 3 | E20: SET | F20: 40000 | G20: =F20*D20 -> 120000 | L20: 18 | M20: 44355 | N20: OTOPROJECT | O20: 7999000 | P20: LUNAS TF. 12/8/21
A21: TITIPAN | B21: GARNIS LAMPU DEPAN RUSH'18 BLACKDOFF | C21: HENDRIK | D21: 10 | E21: SET | G21: =F21*D21 -> 0 | L21: 19 | M21: 44261 | N21: GREAT | O21: 7250000 | P21: LUNAS 29/7/21
A22: TITIPAN | B22: GARNIS LAMPU BELAKANG RUSH'18 BLACKDOFF | C22: HENDRIK | D22: 10 | E22: SET | G22: =F22*D22 -> 0 | L22: 20 | M22: 44270 | N22: GREAT | O22: 2900000 | P22: LUNAS 29/7/21
A23: TDK ORDER | B23: DIFFUSER BRIO'18 | C23: HENDRIK | D23: 60 | E23: SET | G23: =F23*D23 -> 0
B24: SILT PLAT SAMPING BRIO'18 | C24: HENDRIK | D24: 10 | E24: SET | F24: 200000 | G24: =F24*D24 -> 2000000
B25: SILT PLAT SAMPING BRIO'18 LED | C25: HENDRIK | D25: 5 | E25: SET | F25: 300000 | G25: =F25*D25 -> 1500000 | O25: =SUM(O3:O24) -> 109948200
B26: HANDLE CRV'17 HITAM | C26: HENDRIK | D26: 3 | E26: SET | F26: 110000 | G26: =F26*D26 -> 330000
B27: OUTER CRV'17 HITAM | C27: HENDRIK | D27: 3 | E27: SET | F27: 125000 | G27: =F27*D27 -> 375000
B28: TANKI CRV'18 HITAM | C28: HENDRIK | D28: 3 | E28: SET | F28: 40000 | G28: =F28*D28 -> 120000
A29: 44259 | B29: SPOILER BRIO'18 PUTIH | C29: HENDRIK | D29: 3 | E29: SET | F29: 360000 | G29: =F29*D29 -> 1080000 | H29: =SUM(G29:G30) -> 3600000 | I29: LUNAS 5/3
B30: SPOILER BRIO'18 GRAY | C30: HENDRIK | D30: 7 | E30: SET | F30: 360000 | G30: =F30*D30 -> 2520000
A31: 44259 | B31: KARPET DASAR YARIS HITAM | C31: NVM | D31: 5 | E31: SET | F31: 180000 | G31: =F31*D31 -> 900000 | H31: =SUM(G31:G35) -> 3420000 | I31: JUNI | J31: GIRO 30/6/21
B32: KARPET DASAR AVANZA HITAM | C32: NVM | D32: 6 | E32: SET | F32: 180000 | G32: =F32*D32 -> 1080000
B33: KARPET DASAR XPANDER HITAM | C33: NVM | D33: 3 | E33: SET | F33: 180000 | G33: =F33*D33 -> 540000
B34: KARPET DASAR RUSH HITAM | C34: NVM | D34: 5 | E34: SET | F34: 180000 | G34: =F34*D34 -> 900000
B35: SARUNG STIR MB TECH HITAM MERAH | C35: NVM | D35: 1 | E35: SET | F35: 0 | G35: =F35*D35 -> 0
A36: 44260 | B36: TOWING ARB RUSH'18 MODEL FULL BODY KAKI PISAH | C36: ROYAL CITY | D36: 15 | E36: SET | F36: 400000 | G36: =F36*D36 -> 6000000 | H36: =SUM(G36) -> 6000000 | I36: JULI | J36: GIRO 30/7/21
A37: 44260 | B37: SARUNG JOK SATYA HITAM MERAH | C37: BUK IDA | D37: 2 | E37: SET | F37: 0 | G37: =F37*D37 -> 0
B38: SARUNG JOK GRAND INNOVA HITAM COKLAT | C38: BUK IDA | D38: 1 | E38: SET | F38: 0 | G38: =F38*D38 -> 0
A39: 44260 | B39: KARPET DASAR BRIO HITAM TIPIS | C39: HERMAN | D39: 25 | E39: SET | F39: 150000 | G39: =F39*D39 -> 3750000 | H39: =SUM(G39) -> 3750000 | I39: AGUSTUS
A40: 44261 | B40: FOOTSTEP (TANGGA)SAMPING INNOVA | C40: GREAT | D40: 5 | E40: SET | F40: 1450000 | G40: =F40*D40 -> 7250000 | H40: =SUM(G40) -> 7250000 | I40: JULI | J40: LUNAS TF29/7/21
A41: 44261 | B41: KARPET DASAR BRIO HITAM TIPIS | C41: HERMAN | D41: 25 | E41: SET | F41: 150000 | G41: =F41*D41 -> 3750000 | H41: =SUM(G41) -> 3750000 | I41: AGUSTUS
A42: 44261 | B42: KARPET MI 3 RAY HITAM GREY | C42: MR.BOSS | D42: 3 | E42: ROL | F42: 500000 | G42: =F42*D42 -> 1500000 | H42: =SUM(G42) -> 1500000 | I42: JULI | J42: GIRO 30/7/21
A43: 44263 | B43: FRONT GRILL RUSH'18 APOLLO BLACK+LIST CHROME | C43: OTO PROJECT | D43: 6 | E43: SET | F43: 729000 | G43: =F43*D43 -> 4374000 | H43: =G43 -> 4374000 | I43: MEI | J43: LUNAS TF. 29/4/21
A44: 44263 | B44: SARUNG JOK GRAND AVANZA HITAM+MERAH VARIASI | C44: HERMAN | D44: 2 | E44: SET | F44: 740000 | G44: =F44*D44 -> 1480000 | H44: =G44+G45 -> 2960000 | I44: AGUSTUS
B45: SARUNG JOK GRAND AVANZA HITAM+GRAY VARIASI | C45: HERMAN | D45: 2 | E45: SET | F45: 740000 | G45: =F45*D45 -> 1480000
A46: 44263 | B46: KACA FILM SPARTA 40% | C46: JKI | D46: 1 | E46: ROL | F46: 1056000 | G46: =F46*D46 -> 1056000 | H46: =G46 -> 1056000 | I46: AGUSTUS
A47: 44263 | B47: SARUNG JOK RUSH'20 HITAM+GRAY VARIASI | C47: HERMAN | D47: 4 | E47: SET | F47: 740000 | G47: =F47*D47 -> 2960000 | H47: =SUM(G47:G52) -> 11630000 | I47: AGUSTUS
B48: SARUNG JOK RUSH'20 HITAM+MERAH VARIASI | C48: HERMAN | D48: 4 | E48: SET | F48: 740000 | G48: =F48*D48 -> 2960000
B49: SARUNG JOK GRAND AVANZA HITAM+MERAH VARIASI | C49: HERMAN | D49: 2 | E49: SET | F49: 740000 | G49: =F49*D49 -> 1480000
B50: SARUNG JOK XPANDER CROSS'20 HITAM+MERAH VARIASI | C50: HERMAN | D50: 2 | E50: SET | F50: 740000 | G50: =F50*D50 -> 1480000
B51: SARUNG JOK INNOVA'20 HITAM+COKLAT VARIASI | C51: HERMAN | D51: 2 | E51: SET | F51: 740000 | G51: =F51*D51 -> 1480000
B52: SARUNG JOK BRIO RS'20 HITAM | C52: HERMAN | D52: 2 | E52: SET | F52: 635000 | G52: =F52*D52 -> 1270000
A53: 44264 | B53: TANGGA SAMPING RUSH'18 ORI | C53: IRWAN | D53: 10 | E53: SET | F53: 1650000 | G53: =F53*D53 -> 16500000 | H53: =SUM(G53:G60) -> 24960000 | I53: AGUSTUS | J53: 44292
B54: TRUNK LID FORTUNER'16 RUNING | C54: IRWAN | D54: 2 | E54: SET | F54: 1050000 | G54: =F54*D54 -> 2100000
B55: KARET PINTU HONDA | C55: IRWAN | D55: 10 | E55: SET | F55: 45000 | G55: =F55*D55 -> 450000
B56: KARET PINTU DAIHATSU | C56: IRWAN | D56: 5 | E56: SET | F56: 45000 | G56: =F56*D56 -> 225000
B57: TURBO TIMER INNOVA RIBON | C57: IRWAN | D57: 4 | E57: SET | F57: 840000 | G57: =F57*D57 -> 3360000
B58: GERNIS DEPAN ATAS PAJERO'21 HITAM | C58: IRWAN | D58: 5 | E58: SET | F58: 150000 | G58: =F58*D58 -> 750000
B59: GARNIS DEPAN BAWAH PAJERO'21 HITAM | C59: IRWAN | D59: 5 | E59: SET | F59: 150000 | G59: =F59*D59 -> 750000
B60: GARNIS BELAKANG PAJERO'21 HITAM | C60: IRWAN | D60: 5 | E60: SET | F60: 165000 | G60: =F60*D60 -> 825000
A61: 44264 | B61: SARUNG JOK BRIO'20 HITAM | C61: HERMAN | D61: 2 | E61: SET | F61: 635000 | G61: =F61*D61 -> 1270000 | H61: =SUM(G61:G65) -> 9310000 | I61: AGUSTUS
B62: SARUNG JOK BRIO RS'20 HITAM+GRAY | C62: HERMAN | D62: 2 | E62: SET | F62: 635000 | G62: =F62*D62 -> 1270000
B63: SARUNG JOK GRAND AVANZA'20 HITAM | C63: HERMAN | D63: 2 | E63: SET | F63: 740000 | G63: =F63*D63 -> 1480000
B64: SARUNG JOK BRIO'20 HITAM | C64: HERMAN | D64: 6 | E64: SET | F64: 635000 | G64: =F64*D64 -> 3810000
B65: SARUNG JOK INNOVA TIPE G HITAM+COKLAT | C65: HERMAN | D65: 2 | E65: SET | F65: 740000 | G65: =F65*D65 -> 1480000
A66: 44267 | B66: SARUNG JOK BRIO SATYA (MB 9007+9004) | C66: BUK IDA | D66: 1 | E66: SET | G66: =F66*D66 -> 0
B67: SARUNG JOK BRIO RS (MB 9001+7002) | C67: BUK IDA | D67: 1 | E67: SET | G67: =F67*D67 -> 0
A68: 44268 | B68: SARUNG JOK INNOVA V 20 HITAM | C68: HERMAN | D68: 2 | E68: SET | F68: 740000 | G68: =F68*D68 -> 1480000 | H68: =SUM(G68:G74) -> 12060000 | I68: AGUSTUS
B69: SARUNG JOK XPANDER CROSS 20 HITAM | C69: HERMAN | D69: 2 | E69: SET | F69: 740000 | G69: =F69*D69 -> 1480000
B70: SARUNG JOK KARIMUN WAGON 20 HITAM | C70: HERMAN | D70: 4 | E70: SET | F70: 635000 | G70: =F70*D70 -> 2540000
B71: SARUNG JOK BRIO SATYA 20 HITAM | C71: HERMAN | D71: 4 | E71: SET | F71: 635000 | G71: =F71*D71 -> 2540000
B72: SARUNG JOK HRV 21 HITAM | C72: HERMAN | D72: 2 | E72: SET | F72: 635000 | G72: =F72*D72 -> 1270000
B73: SARUNG JOK HILUX 21 HITAM | C73: HERMAN | D73: 2 | E73: SET | F73: 635000 | G73: =F73*D73 -> 1270000
B74: SARUNG JOK INNOVA G 20 HITAM | C74: HERMAN | D74: 2 | E74: SET | F74: 740000 | G74: =F74*D74 -> 1480000
A75: 44268 | B75: SARUNG JOK BRIO SATYA 20 HITAM CAPPUCINO | C75: HERMAN | D75: 4 | E75: SET | F75: 635000 | G75: =F75*D75 -> 2540000 | H75: =SUM(G75:G80) -> 6970000 | I75: AGUSTUS
B76: SARUNG JOK BRIO RS 20 HITAM CAPPUCINO | C76: HERMAN | D76: 2 | E76: SET | F76: 635000 | G76: =F76*D76 -> 1270000
B77: SARUNG JOK AVANZA HITAM CAPPUCINO 20 HITAM | C77: HERMAN | D77: 2 | E77: SET | F77: 740000 | G77: =F77*D77 -> 1480000
B78: BODY COVER PAJERO SPORT'16 HITAM BIRU | C78: HERMAN | D78: 2 | E78: SET | F78: 280000 | G78: =F78*D78 -> 560000
B79: BODY COVER PAJERO SPORT'16 HITAM MERAH | C79: HERMAN | D79: 2 | E79: SET | F79: 280000 | G79: =F79*D79 -> 560000
B80: BODY COVER FORTUNER'16 HITAM MERAH | C80: HERMAN | D80: 2 | E80: SET | F80: 280000 | G80: =F80*D80 -> 560000
A81: 44270 | B81: FOOTSTEP(TANGGA) SAMPING HRV | C81: GREAT | D81: 2 | E81: SET | F81: 1450000 | G81: =F81*D81 -> 2900000 | H81: =SUM(G81) -> 2900000 | I81: LUNAS TF 21/7/21
A82: 44272 | B82: KACA FILM WINCOS WB 70i+ (2011200010K2AS) | C82: WINCOS | D82: 1 | E82: ROL | F82: 7920000 | G82: =F82*D82 -> 7920000 | H82: =SUM(G82) -> 7920000 | I82: LUNAS
A83: 44273 | B83: SARUNG JOK MB-TEACH RUSH'19 (8801-BLACK) | C83: BUK IDA | D83: 1 | E83: SET | G83: =F83*D83 -> 0
A84: 44273 | B84: SARUNG JOK MB-TEACH FORTUNER'13(9012-9007) | C84: BUK IDA | D84: 2 | E84: SET | G84: =F84*D84 -> 0
A85: 44274 | B85: LED TEMBAK RING BULAT PUTIH ICC | C85: MOBILINDO | D85: 4 | E85: SET | F85: 150000 | G85: =F85*D85 -> 600000 | H85: =SUM(G85:G95) -> 7890000 | I85: 4 JUTA BULAN 8,SISANYA BULAN 9
A86: SEPTEMBER | B86: LED TEMBAK RING BULAT MERAH | C86: MOBILINDO | D86: 4 | E86: SET | F86: 150000 | G86: =F86*D86 -> 600000 | I86: GIRO 20/9/21
B87: BUMPER KAP MESIN PAJERO | C87: MOBILINDO | D87: 1 | E87: SET | F87: 850000 | G87: =F87*D87 -> 850000
B88: BUMPER KAP MESIN INNOVA REBORN | C88: MOBILINDO | D88: 1 | E88: SET | F88: 850000 | G88: =F88*D88 -> 850000
B89: BUMPER KAP MESIN HRV | C89: MOBILINDO | D89: 1 | E89: SET | F89: 850000 | G89: =F89*D89 -> 850000
B90: LED TEMBAK 6 LED PUTIH KUNING | C90: MOBILINDO | D90: 6 | E90: SET | F90: 100000 | G90: =F90*D90 -> 600000
B91: LED TEMBAK 12 LED BIRU STROBO | C91: MOBILINDO | D91: 4 | E91: SET | F91: 125000 | G91: =F91*D91 -> 500000
B92: LED TEMBAK 16 LED SEGI HITAM | C92: MOBILINDO | D92: 4 | E92: SET | F92: 250000 | G92: =F92*D92 -> 1000000
B93: LED TEMBAK 16 LED SEGI MERAH | C93: MOBILINDO | D93: 4 | E93: SET | F93: 250000 | G93: =F93*D93 -> 1000000
B94: LED TEMBAK 12 LED 4 SISI | C94: MOBILINDO | D94: 4 | E94: SET | F94: 125000 | G94: =F94*D94 -> 500000
B95: LED TEMBAK 20 CM | C95: MOBILINDO | D95: 6 | E95: SET | F95: 90000 | G95: =F95*D95 -> 540000
A96: SEPTEMBER | B96: LED TEMBAK 48 LED | C96: MOBILINDO | D96: 6 | E96: SET | F96: 150000 | G96: =F96*D96 -> 900000 | H96: =SUM(G96:G107) -> 10335000
B97: HEADLAMP BULAT 7" | C97: MOBILINDO | D97: 1 | E97: SET | F97: 1200000 | G97: =F97*D97 -> 1200000
B98: SARUNG STIR MSV HITAM | C98: MOBILINDO | D98: 14 | E98: SET | F98: 90000 | G98: =F98*D98 -> 1260000
B99: SARUNG STIR KULIT | C99: MOBILINDO | D99: 6 | E99: SET | F99: 120000 | G99: =F99*D99 -> 720000
B100: HEADLAMP KOTAK 7" | C100: MOBILINDO | D100: 1 | E100: SET | F100: 1200000 | G100: =F100*D100 -> 1200000
...

Sheet APRIL
A1: BARANG MASUK ARAW FILM | L1: BON JATUH TEMPO AGUSTUS 2021 ( JT)
A2: TGL MASUK | B2: NAMA BARANG | C2: SUPLIER | D2: QTY | E2: SAT | F2: HARGA/PCS/SET | G2: JUMLAH | H2: TOTAL FAKTUR | I2: KET | L2: NO | M2: TGL BARANG MASUK | N2: NAMA SALES/ SUPLIER | O2: JUMLAH BON | P2: KET
A3: 44287 | B3: GPS GT 06N | C3: ASMIATI | D3: 6 | E3: SET | F3: 385000 | G3: =F3*D3 -> 2310000 | H3: =SUM(G3) -> 2310000 | I3: LUNAS | L3: 1 | M3: 44257 | N3: JSL | O3: 2400000 | P3: GIRO 15/8/21 | S3: 2400
A4: 44287 | B4: TOWING BAR MCC, TY FORTUNER 10-16/ INNOVA 12-16 | C4: NVM | D4: 4 | E4: SET | F4: 1250000 | G4: =F4*D4 -> 5000000 | H4: =G4 -> 5000000 | I4: AGUSTUS | J4: GIRO 30/8/21 | L4: 2 | M4: 44258 | N4: HERMAN | O4: 1710000 | P4: GIRO TGL 15/ TGL 30 | R4: =O4+O8+O9+O11+O12+O13+O15+O16+O17 -> 59030000 | S4: 4930
A5: 44288 | B5: GARNIS LAMPU DEPAN INNOVA'16 CHROME | C5: JSL | D5: 5 | E5: SET | F5: 110000 | G5: =F5*D5 -> 550000 | H5: =SUM(G5:G13) -> 6425000 | I5: SEPTEMBER | J5: GIRO 14/09/21 | L5: 3 | M5: 44258 | N5: JKI | O5: 2200000 | P5: LUNAS TF. TGL 25/8/21 | S5: 36626
B6: MIRROR COVER CHROME INNOVA'16/FORTUNER'16 | C6: JSL | D6: 5 | E6: SET | F6: 100000 | G6: =F6*D6 -> 500000 | L6: 4 | M6: 44259 | N6: HENDRIK | O6: 4225000 | P6: GIRO 17/8/21 | R6: =SUM(O5+O10) -> 3256000 | S6: 11700 | T6: =O4+O8+O9+O11+O12+O13+O15+O16+O17 -> 59030000
B7: GARNIS LAMPU DEPAN CALYA'19 CHROME | C7: JSL | D7: 5 | E7: SET | F7: 125000 | G7: =F7*D7 -> 625000 | L7: 5 | M7: 44259 | N7: HENDRIK | O7: 5820000
B8: GARNIS LAMPU BELAKANG CALYA'16 CHROME | C8: JSL | D8: 5 | E8: SET | F8: 110000 | G8: =F8*D8 -> 550000 | L8: 6 | M8: 44260 | N8: HERMAN | O8: 3750000 | P8: GIRO TGL 15/ TGL 30 | R8: =SUM(O6:O7) -> 10045000 | S8: =SUM(S3:S7) -> 55656
B9: GARNIS LAMPU DEPAN PAJERO '16 HITAM | C9: JSL | D9: 5 | E9: SET | F9: 110000 | G9: =F9*D9 -> 550000 | L9: 7 | M9: 44261 | N9: HERMAN | O9: 3750000 | P9: GIRO TGL 15/ TGL 30
B10: GARNIS LAMPU BELAKANG PAJERO'16 HITAM | C10: JSL | D10: 5 | E10: SET | F10: 125000 | G10: =F10*D10 -> 625000 | L10: 8 | M10: 44263 | N10: JKI | O10: 1056000 | P10: LUNAS TF. TGL 25/8/21
B11: OUTER CHROME INNOVA'16 | C11: JSL | D11: 10 | E11: SET | F11: 85000 | G11: =F11*D11 -> 850000 | L11: 9 | M11: 44263 | N11: HERMAN | O11: 2960000 | P11: GIRO TGL 15/ TGL 30 | R11: =O4+O8+O9+O11+O12+O13+O15+O16+O17 -> 59030000
B12: SILT PLATE SAMPING AVANZA/XENIA | C12: JSL | D12: 5 | E12: SET | F12: 35000 | G12: =F12*D12 -> 175000 | L12: 10 | M12: 44263 | N12: HERMAN | O12: 11630000 | P12: GIRO TGL 15/ TGL 30
B13: SILT PLATE BELAKANG BRIO'19 | C13: JSL | D13: 10 | E13: SET | F13: 200000 | G13: =F13*D13 -> 2000000 | L13: 11 | M13: 44264 | N13: HERMAN | O13: 9310000 | P13: GIRO TGL 15/ TGL 30 | R13: =O4+O8+O9+O11+O12 -> 23800000
A14: 44288 | B14: BESTCO(BODY COVER )XPANDER | C14: JSL | D14: 10 | E14: SET | F14: 118000 | G14: =F14*D14 -> 1180000 | H14: =SUM(G14) -> 1180000 | I14: SEPTEMBER | L14: 12 | M14: 44264 | N14: IRWAN | O14: 24960000 | P14: GIRO 30/8/21
A15: 44289 | B15: SARUNG JOK MB AGYA (MB 9001+9006) | C15: B'IDA | D15: 1 | E15: SET | F15: 0 | G15: =F15*D15 -> 0 | L15: 13 | M15: 44268 | N15: HERMAN | O15: 12060000 | P15: GIRO TGL 15/ TGL 30
A16: 44289 | B16: OUTER HITAM RUSH'18 | C16: JSL | D16: 10 | E16: SET | F16: 85000 | G16: =F16*D16 -> 850000 | H16: =SUM(G16:G18) -> 1825000 | I16: SEPTEMBER | J16: GIRO 14/09/21 | L16: 14 | M16: 44268 | N16: HERMAN | O16: 6970000 | P16: GIRO TGL 15/ TGL 30 | T16: =SUM(MARET!O21+MARET!O22) -> 10150000
B17: GARNIS LAMPU BELAKANG INNOVA'16 CHROME | C17: JSL | D17: 5 | E17: SET | F17: 125000 | G17: =F17*D17 -> 625000 | L17: 15 | M17: 44274 | N17: HERMAN | O17: 6890000 | P17: GIRO TGL 15/ TGL 30
B18: TANKI RUSH '18 HITAM | C18: JSL | D18: 10 | E18: SET | F18: 35000 | G18: =F18*D18 -> 350000 | L18: 16 | M18: 44274 | N18: MOBILINDO | O18: 4010000 | P18: GIRO 30/8/21
A19: 44289 | B19: TV ANDROID ENIGMA 10" | C19: MOBILINDO | D19: 5 | E19: SET | F19: 2000000 | G19: =F19*D19 -> 10000000 | H19: =SUM(G19) -> 10000000 | I19: SEPTEMBER | J19: GIRO 20/9/21 | L19: 17 | M19: 44287 | N19: NVM | O19: 5000000 | P19: GIRO 30/8/21
A20: 44294 | B20: KARPET KARET 3D HITAM | C20: HERMAN | D20: 12 | E20: SET | F20: 175000 | G20: =F20*D20 -> 2100000 | H20: =SUM(G20) -> 2100000 | I20: SEPTEMBER | J20: GIRO 30/9/21 | L20: 18 | M20: 44301 | N20: TJM | O20: 6350000 | R20: =SUM(O19+O20) -> 11350000
A21: 44295 | B21: FRONT GUARD(PLANG DEPAN)RHINO GUARD PAJERO'19 | C21: TJM | D21: 1 | E21: SET | F21: 2150000 | G21: =F21*D21 -> 2150000 | H21: =SUM(G21:G22) -> 4300000 | I21: JULI | J21: LUNAS TF 28/7/21 | L21: 19 | M21: 44312 | N21: HENDRIK | O21: 2550000 | P21: GIRO TGL 30/8/21
B22: FRONT GUARD(PLANG DEPAN)RHINO GUARD FORTUNER'16 | C22: TJM | D22: 1 | E22: SET | F22: 2150000 | G22: =F22*D22 -> 2150000 | L22: 20 | M22: 44366 | N22: OTOPROJECT | O22: 5790000 | P22: LUNAS TF. TGL 12/8/21
A23: 44296 | B23: AN INNOVA 16 SIDE WINDOW TRIM CHROME 8PCS | C23: JSL | D23: 5 | E23: SET | F23: 150000 | G23: =F23*D23 -> 750000 | H23: =SUM(G23:G26) -> 3425000 | I23: SEPTEMBER | J23: GIRO 14/09/21 | L23: 21 | M23: 44410 | N23: JAYA MADANI | O23: 3600000 | P23: LUNAS TF. TGL 14/8/21
B24: AN INNOVA 16 SIDE BODY MOLDING CHROME | C24: JSL | D24: 5 | E24: SET | F24: 300000 | G24: =F24*D24 -> 1500000 | L24: 22 | M24: 44398 | N24: BAN PEMKO PARIAMAN | O24: 4450000 | P24: GIRO TGL 25/8/21
B25: CALYA 19/ SIGRA 19 HEAD LAMP GARNISH BLACKTIVO | C25: JSL | D25: 5 | E25: SET | F25: 125000 | G25: =F25*D25 -> 625000 | L25: 23 | M25: 44302 | N25: MR BOSS | O25: 1230000 | P25: GIRO TGL 30/8/21 | R25: =O25+O26 -> 2190000
B26: CALYA 16/SIGRA 16 TAIL LAMP GARNISH BLACTIVO | C26: JSL | D26: 5 | E26: SET | F26: 110000 | G26: =F26*D26 -> 550000 | L26: 24 | M26: 44316 | N26: MR BOSS | O26: 960000 | P26: GIRO TGL 30/8/22
A27: 44296 | B27: KACAFILM WINTERBLAS HCD 10G C 70 (2101080049KA2E) | C27: WINCOS | D27: 1 | E27: ROL | F27: 0 | G27: =F27*D27 -> 0 | I27: BRIO | L27: 25 | M27: 44261 | N27: MR.BOSS | O27: 1500000 | P27: GIRO 30/7/21
B28: KACAFILM WINTERBLAS HCD 10G C 70 (2101080052KA28) | C28: WINCOS | D28: 1 | E28: ROL | F28: 0 | G28: =F28*D28 -> 0 | I28: BRIO | L28: 26 | M28: 44415 | N28: WINCOS | O28: 39600000 | P28: LUNAS TGL 30/8/21
B29: KACAFILM WINTERBLAS HCD 30G C 70 (2004240080EGAH) | C29: WINCOS | D29: 1 | E29: ROL | F29: 0 | G29: =F29*D29 -> 0 | I29: BRIO
A30: 44298 | B30: SARUNG JOK GRAND INNOVA G mb 9001 BD + 9012 BD | C30: BUK IDA | D30: 1 | E30: SET | F30: 0 | G30: =F30*D30 -> 0 | N30: TOTAL | O30: =SUM(O3:O29) -> 174731000
B31: SARUNG JOK XPANDER mb 9001 + 9015 | C31: BUK IDA | D31: 1 | E31: SET | F31: 0 | G31: =F31*D31 -> 0
A32: 44299 | B32: SPOILER BRIO'18 BLACK | C32: HENDRIK | D32: 5 | E32: SET | F32: 375000 | G32: =F32*D32 -> 1875000 | H32: =SUM(G32:G33) -> 3750000 | I32: LUNAS 13 APRIL 2021 | N32: LUNAS TRANSFER | O32: =O5+O10+O22+O23+O28 -> 52246000
B33: SPOILER BRIO'18 RED | C33: HENDRIK | D33: 5 | E33: SET | F33: 375000 | G33: =F33*D33 -> 1875000
A34: 44301 | B34: LEM 3M | C34: LEO | D34: 50 | E34: SET | F34: 37500 | G34: =F34*D34 -> 1875000 | H34: =SUM(G34) -> 1875000 | I34: SEPTEMBER | N34: DI BYR DENGAN GIRO | O34: =O3+O4+O6+O7+O8+O9+O11+O12+O13+O14+O15+O16+O17+O18+O19+O20+O21+O24+O25+O26+O27 -> 122485000
A35: 44301 | B35: KARPET DASAR PAJERO'16 HITAM | C35: TJM | D35: 10 | E35: SET | F35: 180000 | G35: =F35*D35 -> 1800000 | H35: =SUM(G35:G40) -> 6350000 | I35: AGUSTUS | J35: GIRO 30/8/21
B36: KARPET DASAR XPANDER HITAM | C36: TJM | D36: 10 | E36: SET | F36: 185000 | G36: =F36*D36 -> 1850000
B37: KARPET DASAR FORTUNER HITAM | C37: TJM | D37: 5 | E37: SET | F37: 180000 | G37: =F37*D37 -> 900000
B38: KARPET DASAR BRIO'18 HITAM | C38: TJM | D38: 5 | E38: SET | F38: 180000 | G38: =F38*D38 -> 900000
B39: KARPET DASAR INNOVA'16 HITAM | C39: TJM | D39: 5 | E39: SET | F39: 180000 | G39: =F39*D39 -> 900000
B40: SARUNG STIR MBTECH | C40: TJM | D40: 4 | E40: SET | G40: =F40*D40 -> 0
A41: 44302 | B41: TALANG AIR H-TECH HITAM XPANDER (D/T) | C41: MR. BOSS | D41: 10 | E41: SET | F41: 123000 | G41: =F41*D41 -> 1230000 | H41: =G41 -> 1230000 | I41: GIRO 30/8/21
A42: 44303 | B42: MOBILIO 17 RS / AN BRIO 18 HEAD LAMP GARNIS BLACKIVO | C42: JSL | D42: 15 | E42: SET | F42: 110000 | G42: =F42*D42 -> 1650000 | H42: =SUM(G42:G44) -> 3550000 | I42: SEPTEMBER | J42: F | K42: GIRO 14/09/21
B43: AN BRIO 18 TAIL LAMP GARNISH BLACKTIVO | C43: JSL | D43: 15 | E43: SET | F43: 100000 | G43: =F43*D43 -> 1500000
B44: XPANDER 17 OUTER HANDLE COVER ELEGANT BLACKTIVO | C44: JSL | D44: 5 | E44: SET | F44: 80000 | G44: =F44*D44 -> 400000
A45: 44303 | B45: AN INNOVA 16 TANK COVER PRESTIGE | C45: JSL | D45: 10 | E45: PCS | F45: 35000 | G45: =F45*D45 -> 350000 | H45: =SUM(G45:G51) -> 1575000 | I45: SEPTEMBER
B46: XPANDER 17 TANK COVER BESTIVO BLACKTIVO | C46: JSL | D46: 5 | E46: PCS | F46: 35000 | G46: =F46*D46 -> 175000
B47: AN AVANZA TANK COVER CROSSTIVO BLACKTIVO | C47: JSL | D47: 5 | E47: SET | F47: 30000 | G47: =F47*D47 -> 150000
B48: AN AVANZA / AN XENIA SIDE SCUFF PLATE BLACK | C48: JSL | D48: 5 | E48: SET | F48: 35000 | G48: =F48*D48 -> 175000
C49: JSL | D49: 5 | E49: SET | F49: 75000 | G49: =F49*D49 -> 375000
B50: AN RUSH 18 TANK COVER CADILLAC BLACKTIVO | C50: JSL | D50: 5 | E50: PCS | F50: 35000 | G50: =F50*D50 -> 175000
B51: AN BRIO 18 TANK COVER CADILLAC BLACKTIVO | C51: JSL | D51: 5 | E51: PCS | F51: 35000 | G51: =F51*D51 -> 175000
A52: 44305 | B52: SARUNG JOK INNOVA AN 16 (G) S/S GARIS 04 VL. HITAM + COKLAT | C52: NVM | D52: 2 | E52: SET | F52: 700000 | G52: =F52*D52 -> 1400000 | H52: =SUM(G52:G54) -> 4200000 | I52: SEPTEMBER | J52: DIKEMBALIKAN
B53: SARUNG JOK INNOVA AN 16 (V). S/S GARIS 04 VL HITAM+ COKLAT | C53: NVM | D53: 2 | E53: SET | F53: 700000 | G53: =F53*D53 -> 1400000
B54: SARUNG JOK INNOVA AN 16 (V). S/S GARIS 01 VL HITAM+ COKLAT | C54: NVM | D54: 2 | E54: SET | F54: 700000 | G54: =F54*D54 -> 1400000
A55: 44305 | B55: KACA FILM XAP-35 (INFINITY 40%) | C55: SUNMASTER | D55: 1 | E55: ROL | F55: 7700000 | G55: =F55*D55 -> 7700000 | H55: =SUM(G55) -> 7700000 | I55: OKTOBER
B56: KANEBO | C56: SUNMASTER | D56: 10 | E56: PCS | G56: =F56*D56 -> 0
B57: BODYBAG | C57: SUNMASTER | D57: 41 | E57: PCS | G57: =F57*D57 -> 0
A58: 44306 | B58: PLANG BELAKANG ARB AVANZA/RUSH'18 | C58: AM77 | D58: 5 | E58: SET | F58: 375000 | G58: =F58*D58 -> 1875000 | H58: =SUM(G58:G59) -> 3750000 | I58: APRIL | J58: LUNAS TF. 29/4/21
B59: PLANG BELAKANG ARB CALYA/SIGRA | C59: AM77 | D59: 5 | E59: SET | F59: 375000 | G59: =F59*D59 -> 1875000
A60: 44308 | B60: SARUNG JOK GRAND LIVINA 2019 MB.9001 LIS MERAH+ 2 BH BANTAL | C60: BUK IDA | D60: 1 | E60: SET | F60: 0 | G60: =F60*D60 -> 0 | H60: 0
A61: 44308 | B61: BODY COVER BRIO | C61: JSL | D61: 8 | E61: PCS | F61: 105000 | G61: =F61*D61 -> 840000 | H61: =SUM(G61:G62) -> 1890000 | I61: SEPTEMBER | J61: GIRO 14/09/21
B62: BODY COVER AGYA / AYLA | C62: JSL | D62: 10 | E62: PCS | F62: 105000 | G62: =F62*D62 -> 1050000
A63: 44308 | B63: GARNIS LAMPU DEPAN FORTUNER '16 HITAM DOFF | C63: HENDRIK | D63: 5 | E63: SET | F63: 140000 | G63: =F63*D63 -> 700000 | H63: =SUM(G63:G76) -> 6950000 | I63: SEPTEMBER (AWAL)
B64: GARNIS LAMPU BELAKANG FORTUNER '16 HITAM DOFF | C64: HENDRIK | D64: 5 | E64: SET | F64: 160000 | G64: =F64*D64 -> 800000
B65: GARNIS LAMPU DEPAN XPANDER CROSS HITAM DOFF | C65: HENDRIK | D65: 5 | E65: SET | F65: 140000 | G65: =F65*D65 -> 700000
B66: GARNIS LAMPU BELAKANG XPANDER CROSS HITAM DOFF | C66: HENDRIK | D66: 5 | E66: SET | F66: 160000 | G66: =F66*D66 -> 800000
B67: GARNIS LAMPU DEPAN HILUX '21 HITAM DOFF | C67: HENDRIK | D67: 3 | E67: SET | F67: 150000 | G67: =F67*D67 -> 450000
B68: GARNIS LAMPU BELAKANG HILUX '21 HITAM DOFF | C68: HENDRIK | D68: 3 | E68: SET | F68: 150000 | G68: =F68*D68 -> 450000
B69: GARNIS LAMPU DEPAN BRIO '18 HITAM DOFF | C69: HENDRIK | D69: 10 | E69: SET | F69: 125000 | G69: =F69*D69 -> 1250000
B70: GARNIS LAMPU BELAKANG BRIO'18 HITAM DOFF | C70: HENDRIK | D70: 10 | E70: SET | F70: 125000 | G70: =F70*D70 -> 1250000
B71: HANDLE FORTUNER'16 HITAM DOFF | C71: HENDRIK | D71: 5 | E71: SET | F71: 110000 | G71: =F71*D71 -> 550000
B72: GARNIS LAMPU DEPAN HRV'18 HITAM DOFF | C72: HENDRIK | D72: 1 | E72: SET | F72: 0 | G72: =F72*D72 -> 0
B73: GARNIS LAMPU BELAKANG HRV'18 HITAM DOFF | C73: HENDRIK | D73: 1 | E73: SET | F73: 0 | G73: =F73*D73 -> 0
B74: HANDLE HRV HITAM DOFF | C74: HENDRIK | D74: 1 | E74: SET | F74: 0 | G74: =F74*D74 -> 0
B75: OUTER HRV HITAM DOFF | C75: HENDRIK | D75: 1 | E75: SET | F75: 0 | G75: =F75*D75 -> 0
B76: TANKI HRV HITAM DOFF | C76: HENDRIK | D76: 1 | E76: SET | F76: 0 | G76: =F76*D76 -> 0
A77: 44309 | B77: KARPET DASAR BRIO HITAM TIPIS | C77: HERMAN | D77: 50 | E77: PCS | F77: 150000 | G77: =F77*D77 -> 7500000 | H77: =SUM(G77:G79) -> 8835000 | I77: SEPTEMBER | J77: GIRO 30/9/21
B78: BODY COVER AN FORTUNER '18 H/M | C78: HERMAN | D78: 2 | E78: PCS | F78: 285000 | G78: =F78*D78 -> 570000
B79: BODY COVER BRIO '18 H+B | C79: HERMAN | D79: 3 | E79: PCS | F79: 255000 | G79: =F79*D79 -> 765000
A80: 44309 | B80: TWIST TW 6512 | C80: YUSUF ORCA | D80: 14 | E80: SET | F80: 80000 | G80: =F80*D80 -> 1120000 | H80: =SUM(G80) -> 1120000 | I80: OKTOBER
A81: 44310 | B81: RACK HUMMER/FOXCO LARGE(BSR) | C81: AM77 | D81: 6 | E81: SET | F81: 600000 | G81: =F81*D81 -> 3600000 | H81: =SUM(G81) -> 3600000 | I81: SEPTEMBER
A82: 44310 | B82: KARPET DASAR SIGRA HITAM TIPIS | C82: HERMAN | D82: 10 | E82: SET | F82: 150000 | G82: =F82*D82 -> 1500000 | H82: =SUM(G82) -> 1500000 | I82: GIRO 30/10/21
A83: 44312 | B83: GARNIS LAMPU DEPAN HILUX'21 TYPE G HITAM | C83: HENDRIK | D83: 3 | E83: SET | F83: 150000 | G83: =F83*D83 -> 450000 | H83: =SUM(G83:G90) -> 2550000 | I83: AGUSTUS
B84: GARNIS LAMPU BELAKANG HILUX'21 TYPE G HITAM | C84: HENDRIK | D84: 3 | E84: SET | F84: 150000 | G84: =F84*D84 -> 450000
B85: OUTER HILUX'21 HITAM | C85: HENDRIK | D85: 3 | E85: SET | F85: 125000 | G85: =F85*D85 -> 375000
B86: OUTER HILUX'21 CHROME | C86: HENDRIK | D86: 3 | E86: SET | F86: 125000 | G86: =F86*D86 -> 375000
B87: HANDLE HILUX'21 HITAM | C87: HENDRIK | D87: 3 | E87: SET | F87: 110000 | G87: =F87*D87 -> 330000
B88: HANDLE HILUX'21 CHROME | C88: HENDRIK | D88: 3 | E88: SET | F88: 110000 | G88: =F88*D88 -> 330000
B89: TANKI HILUX'21 HITAM | C89: HENDRIK | D89: 3 | E89: SET | F89: 40000 | G89: =F89*D89 -> 120000
B90: TANKI HILUX'21 CHROME | C90: HENDRIK | D90: 3 | E90: SET | F90: 40000 | G90: =F90*D90 -> 120000
A91: 44313 | B91: KACA FILM ANTI GORES 60% SLR | C91: JKI | D91: 2 | E91: ROL | F91: 1100000 | G91: =F91*D91 -> 2200000 | H91: =SUM(G91) -> 2200000 | I91: SEPTEMBER
A92: 44313 | B92: TOWING DEPAN TRD AVANZA/RUSH'18 | C92: AM77 | D92: 3 | E92: SET | F92: 600000 | G92: =F92*D92 -> 1800000 | H92: =SUM(G92:G94) -> 4200000 | I92: OKTOBER
B93: TOWING DEPAN TRD AVANZA ALL NEW | C93: AM77 | D93: 2 | E93: SET | F93: 600000 | G93: =F93*D93 -> 1200000
B94: TOWING DEPAN TRD CALYA | C94: AM77 | D94: 2 | E94: SET | F94: 600000 | G94: =F94*D94 -> 1200000
A95: 44315 | B95: TOWING MCC FORTUNER '16 (ISI PAJERO 3) | C95: IRWAN | D95: 6 | E95: SET | F95: 1350000 | G95: =F95*D95 -> 8100000 | H95: =SUM(G95:G107) -> 22160000 | I95: OKTOBER | J95: GIRO 30/10/21
B96: TOWING MCC RUSH '18 | C96: IRWAN | D96: 2 | E96: SET | F96: 1350000 | G96: =F96*D96 -> 2700000
B97: TOWING MCC XPANDER | C97: IRWAN | D97: 2 | E97: SET | F97: 1350000 | G97: =F97*D97 -> 2700000
B98: TANK COVER CARBON A/N BRIO | C98: IRWAN | D98: 5 | E98: PCS | F98: 50000 | G98: =F98*D98 -> 250000
B99: KLAKSON GOZZO | C99: IRWAN | D99: 25 | E99: SET | F99: 100000 | G99: =F99*D99 -> 2500000
B100: ALARM KONE A/N FORTUNER | C100: IRWAN | D100: 15 | E100: SET | F100: 160000 | G100: =F100*D100 -> 2400000
...

Sheet MEI
A1: BARANG MASUK ARAW FILM
A2: TGL MASUK | B2: NAMA BARANG | C2: SUPLIER | D2: QTY | E2: SAT | F2: HARGA/PCS/SET | G2: JUMLAH | H2: TOTAL FAKTUR | I2: KET | L2: BON JATUH TEMPO SEPTEMBER 2021 ( JT)
A3: 44317 | B3: KLAKSON ORCA | C3: ORCA | D3: 100 | E3: SET | F3: 80000 | G3: =F3*D3 -> 8000000 | H3: =SUM(G3) -> 8000000 | I3: OKTOBER | L3: NO | M3: TGL BARANG MASUK | N3: NAMA SALES/ SUPLIER | O3: JUMLAH BON | P3: KET
A4: 44317 | B4: LOGO RS | C4: HERMAN | D4: 50 | E4: SET | F4: 30000 | G4: =F4*D4 -> 1500000 | H4: =SUM(G4) -> 1500000 | I4: GIRO 30/10/21 | L4: 1 | M4: 44278 | N4: IRWAN | O4: 700000 | P4: GIRO 30/9/2021 | Q4: V
A5: 44319 | B5: KD CALYA HITAM | C5: TJM | D5: 10 | E5: SET | F5: 180000 | G5: =F5*D5 -> 1800000 | H5: =SUM(G5) -> 1800000 | I5: SEPTEMBER | L5: 2 | M5: 44274 | N5: MOBILINDO | O5: 7890000 | P5: GIRO 20/9/21 | Q5: V
A6: 44319 | B6: SARUNG JOK AGYA (MB 9001 +MB 9007) | C6: B'IDA | D6: 1 | E6: SET | F6: 0 | G6: 0 | L6: 3 | M6: 44274 | N6: MOBILINDO | O6: 10335000 | P6: GIRO 20/9/21 | Q6: V
A7: 44319 | B7: BESTCO CAR COVER FORTUNER | C7: JSL | D7: 5 | E7: SET | F7: 142000 | G7: =F7*D7 -> 710000 | H7: =SUM(G7:G11) -> 5695000 | I7: OKTOBER | J7: GIRO 14/10/21 | L7: 4 | M7: 44274 | N7: HERMAN | O7: 6560000 | P7: GIRO 10/9/21 | Q7: V
B8: BESTCO CAR COVER BRIO'18 | C8: JSL | D8: 20 | E8: SET | F8: 105000 | G8: =F8*D8 -> 2100000 | L8: 5 | M8: 44281 | N8: MOBILINDO | O8: 2250000 | P8: GIRO 20/9/21 | Q8: V
B9: BESTCO CAR COVER BRIO | C9: JSL | D9: 12 | E9: SET | F9: 105000 | G9: =F9*D9 -> 1260000 | L9: 6 | M9: 44284 | N9: HERMAN | O9: 0 | P9: DIKEMBALIKAN
B10: BESTCO CAR COVER YARIS | C10: JSL | D10: 5 | E10: SET | F10: 105000 | G10: =F10*D10 -> 525000 | L10: 7 | M10: 44288 | N10: JSL | O10: 6425000 | P10: GIRO 14/09/21 | Q10: V
B11: BESTCO CAR COVER CALYA/SIGRA | C11: JSL | D11: 10 | E11: SET | F11: 110000 | G11: =F11*D11 -> 1100000 | L11: 8 | M11: 44288 | N11: JSL | O11: 1180000
A12: 44319 | B12: GRILL PAJERO MDL ALPARD (DIKEMBALIKAN) | C12: IRWAN | D12: 1 | E12: SET | F12: 1250000 | G12: =F12*D12 -> 1250000 | H12: =SUM(G12:G18) -> 20950000 | I12: OKTOBER | J12: GIRO 30/10/21 | L12: 9 | M12: 44289 | N12: JSL | O12: 1825000
B13: GRILL RUSH'18 MDL PRADO | C13: IRWAN | D13: 2 | E13: SET | F13: 700000 | G13: =F13*D13 -> 1400000 | L13: 10 | M13: 44289 | N13: MOBILINDO | O13: 10000000 | P13: GIRO 20/9/21 | Q13: V
B14: GRILL INNOVA'16 MDL ALPARD | C14: IRWAN | D14: 1 | E14: SET | F14: 1500000 | G14: =F14*D14 -> 1500000 | L14: 11 | M14: 44294 | N14: HERMAN | O14: 2100000 | P14: GIRO TGL 30/9/21 | Q14: V
B15: DOUBLE TIPE TRANSPARAN | C15: IRWAN | D15: 150 | E15: SET | F15: 40000 | G15: =F15*D15 -> 6000000 | L15: 12 | M15: 44296 | N15: JSL | O15: 3425000 | P15: GIRO 14/09/21 | Q15: V
C16: IRWAN | D16: 12 | E16: SET | F16: 300000 | G16: =F16*D16 -> 3600000 | L16: 13 | M16: 44301 | N16: LEO | O16: 1875000 | P16: GIRO TGL 15/9/21 | Q16: V
B17: FOGLAMP ALL NEW AVZ RUSH '18 | C17: IRWAN | D17: 5 | E17: SET | F17: 450000 | G17: =F17*D17 -> 2250000 | L17: 14 | M17: 44303 | N17: JSL | O17: 5125000 | P17: GIRO 14/9/21 | Q17: V
B18: KAKI SPORT RACK | C18: IRWAN | D18: 11 | E18: SET | F18: 450000 | G18: =F18*D18 -> 4950000 | L18: 15 | M18: 44308 | N18: JSL | O18: 1890000
A19: 44319 | B19: SILICON KUNCI HONDA BRIO HITAM | C19: HERMAN | D19: 10 | E19: SET | F19: 15000 | G19: =F19*D19 -> 150000 | H19: =SUM(G19:G30) -> 2875000 | I19: GIRO 30/10/21 | L19: 16 | M19: 44308 | N19: HENDRIK | O19: 6950000 | P19: GIRO TGL 20/09/21 | Q19: V
B20: SILICON KUNCI HONDA BRIO MERAH | C20: HERMAN | D20: 5 | E20: SET | F20: 15000 | G20: =F20*D20 -> 75000 | L20: 17 | M20: 44351 | N20: HENDRIK | O20: 1500000
B21: SILICON KUNCI HONDA BRIO BIRU | C21: HERMAN | D21: 5 | E21: SET | F21: 15000 | G21: =F21*D21 -> 75000 | L21: 18 | M21: 44309 | N21: HERMAN | O21: 8835000 | P21: GIRO TGL 30/9/21 | Q21: V
B22: SILICON KUNCI HONDA INNOVA HITAM | C22: HERMAN | D22: 10 | E22: SET | F22: 15000 | G22: =F22*D22 -> 150000 | L22: 19 | M22: 44310 | N22: AM77 | O22: 3600000 | P22: GIRO 30/9/21 | Q22: V
B23: SILICON KUNCI HONDA INNOVA MERAH | C23: HERMAN | D23: 5 | E23: SET | F23: 15000 | G23: =F23*D23 -> 75000 | L23: 20 | M23: 44319 | N23: TJM | O23: 1800000 | P23: GIRO 30/9/21 | Q23: V
B24: SILICON KUNCI HONDA INNOVA BIRU | C24: HERMAN | D24: 5 | E24: SET | F24: 15000 | G24: =F24*D24 -> 75000 | L24: 21 | M24: 44362 | N24: MR. BOSS | O24: 2700000 | P24: GIRO TGL 30/9/21 | Q24: V
B25: SILICON KUNCI HONDA RUSH/VELOZ BIRU | C25: HERMAN | D25: 5 | E25: SET | F25: 15000 | G25: =F25*D25 -> 75000 | L25: 23 | M25: 44313 | N25: JKI | O25: 2200000 | P25: GIRO TGL 30/9/21 | Q25: V
B26: SILICON KUNCI CALYA HITAM | C26: HERMAN | D26: 10 | E26: SET | F26: 15000 | G26: =F26*D26 -> 150000 | L26: 24 | M26: 44396 | N26: OTOPROJECT | O26: 10305000 | P26: LUNAS TF. 22/9/21
B27: SILICON KUNCI CALYA MERAH | C27: HERMAN | D27: 5 | E27: SET | F27: 15000 | G27: =F27*D27 -> 75000 | L27: 25 | M27: 44404 | N27: OTOPROJECT | O27: 2975000
B28: SILICON KUNCI CALYA BIRU | C28: HERMAN | D28: 5 | E28: SET | F28: 15000 | G28: =F28*D28 -> 75000 | L28: 26 | M28: 44442 | N28: WINCOS | O28: 19800000 | P28: LUNAS TF 29/9/21
B29: EMBLEM CUP MESIN PAJERO SPORT'16 CHROME | C29: HERMAN | D29: 10 | E29: SET | F29: 95000 | G29: =F29*D29 -> 950000 | L29: 27 | M29: 44434 | N29: JAYA MADANI | O29: 3600000 | P29: LUNAS TF. 20/9/21
B30: EMBLEM CUP MESIN PAJERO SPORT'16 HITAM | C30: HERMAN | D30: 10 | E30: SET | F30: 95000 | G30: =F30*D30 -> 950000
A31: 44319 | B31: KACA FILM WINTERBLAST HCD 30G C 70 (2101080254K2AC) | C31: WINCOS | D31: 1 | E31: ROLL | F31: 0 | G31: =F31*D31 -> 0 | H31: BRIO | I31: BRIO | N31: TOTAL | O31: =SUM(O4:O30) -> 125845000
A32: 44322 | B32: SPOILER BRIO'18 WHITE | C32: HENDRIK | D32: 3 | E32: SET | F32: 375000 | G32: =F32*D32 -> 1125000 | H32: =SUM(G32:G35) -> 3750000 | I32: LUNAS TF. 18/5/21
B33: SPOILER BRIO'18 MODREN STEEL | C33: HENDRIK | D33: 3 | E33: SET | F33: 375000 | G33: =F33*D33 -> 1125000 | N33: BYR DG GIRO | O33: =O25+O24+O23+O21+O20+O19+O17+O16+O15+O14+O13+O12+O11+O10+O8+O7+O6+O5+O4+O18+O22 -> 89165000
B34: SPOILER BRIO'18 RED | C34: HENDRIK | D34: 2 | E34: SET | F34: 375000 | G34: =F34*D34 -> 750000 | N34: GIRO 50 JT AWAL | O34: =O5+O6+O7+O8+O10+O11+O12+O15+O16+O17+O18 -> 48780000 | P34: V
B35: SPOILER BRIO'18 YELLOW | C35: HENDRIK | D35: 2 | E35: SET | F35: 375000 | G35: =F35*D35 -> 750000 | N35: GIRO 30 JT AKHIR | O35: =O4+O13+O14+O19+O20+O21 -> 30085000 | P35: V
A36: 44327 | B36: KACA FILM WINTERBLAST HCD 30G C 70 (2102150119K2AB) | C36: WINCOS | D36: 1 | E36: ROLL | F36: 0 | G36: 0 | H36: 0 | I36: BRIO | N36: GIRO 8.5 JT | O36: =O22+O23+O24+O25 -> 10300000 | P36: V
A37: 44335 | B37: GRILL COVER BRIO 18 BLACK | C37: JSL | D37: 1 | E37: PCS | F37: 550000 | G37: =SUM(F37*D37) -> 550000 | H37: =SUM(G37:G40) -> 2200000 | I37: OKTOBER | N37: LUNAS TRANSFER | O37: =O29+O27+O26+O28 -> 36680000
B38: GRILL COVER BRIO 18 BLACKTIVO | C38: JSL | D38: 1 | E38: PCS | F38: 550000 | G38: =SUM(F38*D38) -> 550000
B39: GRILL COVER BRIO 18 SILVER KOMB | C39: JSL | D39: 1 | E39: PCS | F39: 550000 | G39: =SUM(F39*D39) -> 550000
B40: GRILL COVER BRIO 18 TAFFETA WHITE | C40: JSL | D40: 1 | E40: PCS | F40: 550000 | G40: =SUM(F40*D40) -> 550000
A41: 44340 | B41: KACA FILM WINTERBLAST HCD 10G C 70 (2101080150K2A7) | C41: WINCOS | D41: 1 | E41: ROLL | F41: 0 | G41: =SUM(F41*D41) -> 0 | H41: BRIO | I41: BRIO
B42: KACA FILM WINTERBLAST HCD 10G C 70 (2101080146K2AC) | C42: WINCOS | D42: 1 | E42: ROLL | F42: 0 | G42: =SUM(F42*D42) -> 0
B43: KACA FILM WINTERBLAST HCD 30G C 70 (2102150161K2A8) | C43: WINCOS | D43: 1 | E43: ROLL | F43: 0 | G43: =SUM(F43*D43) -> 0
B44: KACA FILM WINTERBLAST HCD 30G C 70 (2102150186K2AF) | C44: WINCOS | D44: 1 | E44: ROLL | F44: 0 | G44: =SUM(F44*D44) -> 0
A45: 44343 | B45: DIFFUSER BRIO | C45: KO AKHON | D45: 30 | E45: SET | F45: 320000 | G45: =SUM(F45*D45) -> 9600000 | H45: =SUM(G45) -> 9600000 | I45: NOVEMBER (PERTENGAHAN)
A46: 44343 | B46: SPOILER BRIO'18 BLACK | C46: HENDRIK | D46: 3 | E46: SET | F46: 375000 | G46: =SUM(F46*D46) -> 1125000 | H46: =SUM(G46:G50) -> 3750000 | I46: MEI (CASH) | J46: LUNAS TF 01/6/21
B47: SPOILER BRIO'18 MODREN STEEL | C47: HENDRIK | D47: 1 | E47: SET | F47: 375000 | G47: =SUM(F47*D47) -> 375000
B48: SPOILER BRIO'18 SILVER | C48: HENDRIK | D48: 1 | E48: SET | F48: 375000 | G48: =SUM(F48*D48) -> 375000
B49: SPOILER BRIO'18 RED | C49: HENDRIK | D49: 3 | E49: SET | F49: 375000 | G49: =SUM(F49*D49) -> 1125000
B50: SPOILER BRIO'18 YELLOW | C50: HENDRIK | D50: 2 | E50: SET | F50: 375000 | G50: =SUM(F50*D50) -> 750000
A51: 44343 | B51: GARNIS LAMP '20 CHROME HEAD | C51: JSL | D51: 5 | E51: SET | F51: 140000 | G51: =SUM(F51*D51) -> 700000 | H51: =SUM(G51:G52) -> 1500000 | I51: OKTOBER
B52: GARNIS LAMP '20 CHROME TAIL | C52: JSL | D52: 5 | E52: SET | F52: 160000 | G52: =SUM(F52*D52) -> 800000
A53: 44343 | B53: FRONT GRILLE COVER BRIO '18 CARNIVAL YELLOW | C53: JSL | D53: 1 | E53: PCS | F53: 550000 | G53: =SUM(F53*D53) -> 550000 | H53: =SUM(G53:G54) -> 1100000 | I53: OKTOBER
B54: FRONT GRILLE COVER BRIO '18 RALLYE RED | C54: JSL | D54: 1 | E54: PCS | F54: 550000 | G54: =SUM(F54*D54) -> 550000
A55: 44344 | B55: SARUNG JOK RUSH'18 HITAM | C55: HERMAN | D55: 2 | E55: SET | F55: 740000 | G55: =SUM(F55*D55) -> 1480000 | H55: =SUM(G55:G57) -> 5940000 | I55: GIRO 10/11/21
B56: SARUNG JOK XPANDER HITAM CREAM | C56: HERMAN | D56: 4 | E56: SET | F56: 740000 | G56: =SUM(F56*D56) -> 2960000
B57: KARPET DASAR JAZZ HITAM | C57: HERMAN | D57: 10 | E57: SET | F57: 150000 | G57: =SUM(F57*D57) -> 1500000
A58: 44344 | B58: TALANG AIR BRIO | C58: IRWAN | D58: 55 | E58: SET | F58: 120000 | G58: =SUM(F58*D58) -> 6600000 | H58: =SUM(G58:G65) -> 15782500 | I58: NOVEMBER (PERTENGAHAN) | J58: =SUM(H58:H68) -> 17507500
B59: COVER SPION RUSH'18 CHROME | C59: IRWAN | D59: 5 | E59: SET | F59: 120000 | G59: =SUM(F59*D59) -> 600000 | J59: GIRO 10/11/21
B60: OUTER BRIO HITAM | C60: IRWAN | D60: 20 | E60: SET | F60: 95000 | G60: =SUM(F60*D60) -> 1900000
B61: OUTER RUSH'18 HITAM | C61: IRWAN | D61: 15 | E61: SET | F61: 95000 | G61: =SUM(F61*D61) -> 1425000
B62: HANDLE BRIO HITAM | C62: IRWAN | D62: 20 | E62: SET | F62: 85000 | G62: =SUM(F62*D62) -> 1700000
B63: TANK COVER BRIO HITAM | C63: IRWAN | D63: 20 | E63: SET | F63: 45000 | G63: =SUM(F63*D63) -> 900000
B64: SWITCH PINTU AVANZA (ORDERAN LAMA) | C64: IRWAN | D64: 5 | E64: SET | F64: 27500 | G64: =SUM(F64*D64) -> 137500
B65: TURBO TIMER FORTUNER'16( ORDERAN LAMA) | C65: IRWAN | D65: 3 | E65: SET | F65: 840000 | G65: =SUM(F65*D65) -> 2520000
A66: 44344 | B66: GRILL PAJERO MODEL ALPHARD '16 | C66: IRWAN | D66: 1 | E66: SET | F66: 1250000 | G66: =SUM(F66*D66) -> 1250000 | H66: =SUM(G66:G68) -> 1725000 | I66: NOVEMBER (PERTENGAHAN)
B67: TALANG AIR PAJERO'16 (GANTI YG DIKEMBALIKAN) | C67: IRWAN | D67: 11 | E67: SET | F67: 0 | G67: 0
B68: OUTER RUSH'18 HITAM | C68: IRWAN | D68: 5 | E68: SET | F68: 95000 | G68: =SUM(F68*D68) -> 475000
A69: 44345 | B69: KACA FILM FX 3M (40%,60%) | C69: LEO | D69: 2 | E69: ROLL | F69: 1950000 | G69: =SUM(F69*D69) -> 3900000 | H69: =SUM(G69) -> 3900000 | I69: NOVEMBER
A70: 44347 | B70: ROOF BOX KANAKA (BC) HITAM | C70: AM77 | D70: 1 | E70: PCS | F70: 3700000 | G70: =SUM(F70*D70) -> 3700000 | H70: =SUM(G70) -> 3700000 | I70: GIRO OKTOBER
A71: 44347 | B71: SARUNG JOK BRIO SATYA (MBTECK) | C71: BUK IDA | D71: 1 | E71: SET | F71: 0 | G71: =SUM(F71*D71) -> 0 | H71: 0

Sheet JUNI
A1: BARANG MASUK ARAW FILM | K1: BON JATUH TEMPO OKTOBER 2021 ( JT)
A2: TGL MASUK | B2: NAMA BARANG | C2: SUPLIER | D2: QTY | E2: SAT | F2: HARGA/PCS/SET | G2: JUMLAH | H2: TOTAL FAKTUR | I2: KET | K2: NO | L2: TGL BARANG MASUK | M2: NAMA SALES/ SUPLIER | N2: JUMLAH BON | O2: KET | P2: CEK
A3: 44348 | B3: SPOILER A.N BRIO HITAM | C3: KO AKHON | D3: 3 | E3: PCS | F3: 400000 | G3: =SUM(F3*D3) -> 1200000 | H3: =SUM(G3:G8) -> 11600000 | I3: NOVEMBER (PERTENGAHAN) | K3: 1 | L3: 44305 | M3: JKI | N3: 7700000 | O3: GIRO TGL 30/10/21
B4: SPOILER A.N BRIO MERAH | C4: KO AKHON | D4: 5 | E4: PCS | F4: 400000 | G4: =SUM(F4*D5) -> 2000000 | K4: 2 | L4: 44309 | M4: YUSUF ORCA | N4: 1120000 | O4: GIRO TF. TGL 30/10/21
B5: SPOILER A.N BRIO KUNING | C5: KO AKHON | D5: 5 | E5: PCS | F5: 400000 | G5: =SUM(F5*D6) -> 2000000 | K5: 3 | L5: 44310 | M5: HERMAN | N5: 1500000 | O5: GIRO TGL 30/10/21 | P5: V
B6: SPOILER A.N BRIO GREY | C6: KO AKHON | D6: 5 | E6: PCS | F6: 400000 | G6: =SUM(F6*D6) -> 2000000 | K6: 4 | L6: 44313 | M6: AM77 | N6: 4200000 | O6: GIRO 30/10/21
B7: SPOILER A.N BRIO PUTIH | C7: KO AKHON | D7: 6 | E7: PCS | F7: 400000 | G7: =SUM(F7*D7) -> 2400000 | K7: 5 | L7: 44315 | M7: IRWAN | N7: 22160000 | O7: GIRO 30/10/21
B8: SPOILER A.N BRIO SILVER | C8: KO AKHON | D8: 5 | E8: PCS | F8: 400000 | G8: =SUM(F8*D8) -> 2000000 | K8: 6 | L8: 44317 | M8: HERMAN | N8: 1500000 | O8: GIRO TGL 30/10/21 | P8: V | Q8: =N5+N8+N14 -> 5875000
A9: 44348 | B9: TOW BEL CUSTOM W/L + ANTING -PAJERO SPORT DUDUKAN MERAH FB | C9: AM77 | D9: 2 | E9: SET | F9: 2200000 | G9: =SUM(F9*D9) -> 4400000 | H9: =SUM(G9) -> 4400000 | I9: GIRO OKTOBER | K9: 7 | L9: 44317 | M9: ORCA | N9: 8000000 | O9: GIRO TF. TGL 30/10/21 | Q9: =5000000+Q8 -> 10875000
A10: 44348 | B10: ROOF BOX KANAKA (BC) HITAM | C10: AM77 | D10: 1 | E10: PCS | F10: 3700000 | G10: =SUM(F10*D10) -> 3700000 | H10: =SUM(G10) -> 3700000 | K10: 8 | L10: 44316 | M10: ORCA | N10: 7500000
A11: 44348 | B11: KARPET MIE 3RAY HITAM /MERAH | C11: KO AKHON | D11: 5 | E11: ROL | F11: 525000 | G11: =SUM(F11*D11) -> 2625000 | H11: =SUM(G11:G12) -> 4725000 | I11: NOVEMBER (PERTENGAHAN) | K11: 9 | L11: 44316 | M11: ORCA | N11: 365000
B12: KARPET MIE 3 RAY COKLAT/CREAM | C12: KO AKHON | D12: 4 | E12: ROL | F12: 525000 | G12: =SUM(F12*D12) -> 2100000 | K12: 10 | L12: 44319 | M12: JSL | N12: 5695000 | O12: GIRO 14/10/21 | P12: V
A13: 44350 | B13: KARPET DASAR BRIO TIPIS | C13: HERMAN | D13: 50 | E13: SET | F13: 150000 | G13: =F13*D13 -> 7500000 | H13: =SUM(G13) -> 7500000 | I13: GIRO 10/11/21 | K13: 11 | L13: 44319 | M13: IRWAN | N13: 20950000 | O13: GIRO 30/10/21
A14: 44350 | B14: KACA FILM AG 80% | C14: JKI | D14: 3 | E14: SET | F14: 1100000 | G14: =F14*D14 -> 3300000 | H14: =SUM(G14) -> 3300000 | I14: NOVEMBER | K14: 12 | L14: 44319 | M14: HERMAN | N14: 2875000 | O14: GIRO TGL 30/10/21
A15: 44351 | B15: TALANG AIR CITY HB | C15: HENDRIK | D15: 10 | E15: SET | F15: 150000 | G15: =SUM(F15*D15) -> 1500000 | H15: =SUM(G15) -> 1500000 | I15: OKTOBER | K15: 13 | L15: 44335 | M15: JSL | N15: 2200000 | O15: GIRO TGL 10/10/21 | P15: V | Q15: =SUM(N15:N17) -> 4800000
A16: 44352 | B16: REFLEKTOR BUMPER HRV | C16: KO AKHON | D16: 3 | E16: SET | F16: 325000 | G16: =SUM(F16*D16) -> 975000 | H16: =SUM(G16) -> 975000 | I16: NOVEMBER | K16: 14 | L16: 44343 | M16: JSL | N16: 1100000 | P16: V
A17: 44352 | B17: KACA FILM CPF1 60% | C17: JKI | D17: 1 | E17: ROL | F17: 5500000 | G17: =SUM(F17*D17) -> 5500000 | H17: =SUM(G17) -> 5500000 | I17: NOVEMBER | K17: 15 | L17: 44343 | M17: JSL | N17: 1500000 | P17: V
A18: 44354 | B18: TANGGA SAMPING INNOVA | C18: IRWAN | D18: 5 | E18: SET | F18: 1550000 | G18: =SUM(F18*D18) -> 7750000 | H18: =SUM(G18:G19) -> 15500000 | I18: NOVEMBER (5.500.000) | K18: 16 | L18: 44354 | M18: NVM | N18: 7040000 | O18: GIRO TGL 30/10/21 | P18: V
B19: TANGGA SAMPING INNOVA | C19: IRWAN | D19: 5 | E19: SET | F19: 1550000 | G19: =SUM(F19*D19) -> 7750000 | I19: DESEMBER (10.000.000) | K19: 17 | L19: 44361 | M19: TJM | N19: 7400000 | P19: V
A20: 44354 | B20: RETRAC MIRROR INNOVA | C20: LEO | D20: 2 | E20: SET | F20: 1000000 | G20: =SUM(F20*D20) -> 2000000 | H20: =SUM(G20) -> 2000000 | I20: NOVEMBER | K20: 18 | L20: 44424 | M20: OTOPROJECT | N20: 10656000 | O20: GIRO TGL 25/10/21 | P20: V
A21: 44354 | B21: TOWING MCC FORTUNER TRD | C21: GREAT(KO AKHON) | D21: 5 | E21: SET | F21: 1200000 | G21: =SUM(F21*D21) -> 6000000 | H21: =SUM(G21:G22) -> 12000000 | I21: NOVEMBER | K21: 19 | L21: 44347 | M21: AM77 | N21: 3700000 | O21: GIRO TGL 15/10/21 | P21: V
B22: TOWING MCC INNOVA REBRON | C22: GREAT | D22: 5 | E22: SET | F22: 1200000 | G22: =SUM(F22*D22) -> 6000000 | K22: 20 | L22: 44348 | M22: AM77 | N22: 4400000 | P22: V | Q22: PNDAHAN DARI GIRO NOVEMBER
A23: 44354 | B23: KARPET UNIVERSAL BLACK | C23: NVM | D23: 10 | E23: SET | F23: 145000 | G23: =SUM(F23*D23) -> 1450000 | H23: =SUM(G23:G42) -> 3640000 | I23: GIRO OKTOBER | J23: =SUM(H23:H44) -> 7040000 | K23: 21 | L23: 44348 | M23: AM77 | N23: 3700000 | P23: V
B24: SARUNG STIR OMAX BLACK/RED | C24: NVM | D24: 3 | E24: SET | F24: 125000 | G24: =SUM(F24*D24) -> 375000 | K24: 22 | L24: 44403 | M24: HERMAN | N24: 5000000 | O24: GIRO TGL 30/10/21
B25: CAMERA BLK CAMERA (INFRA RED) | C25: NVM | D25: 9 | E25: SET | F25: 165000 | G25: =SUM(F25*D25) -> 1485000
B26: KANCING BUMPER SPOILER/FENDER (100 PCS) | C26: NVM | D26: 1 | E26: PACK | F26: 90000 | G26: =SUM(F26*D26) -> 90000 | N26: =SUM(N3:N25) -> 130261000
B27: LAP MICROFIBER RAZO,ALL PURPOSE ,GREEEN | C27: NVM | D27: 1 | E27: SET | F27: 15000 | G27: =SUM(F27*D27) -> 15000
B28: LAP MICROFIBER RAZO,ALL PURPOSE ,PINK | C28: NVM | D28: 1 | E28: SET | F28: 15000 | G28: =SUM(F28*D28) -> 15000
B29: LAP MICROFIBER RAZO,ALL PURPOSE ,WHITE | C29: NVM | D29: 1 | E29: SET | F29: 15000 | G29: =SUM(F29*D29) -> 15000 | K29: 0 | M29: GIRO 20 JT | N29: =N15+N16+N17+N21+N22+N23+N12 -> 22295000
B30: LAP MICROFIBER RAZO,ALL PURPOSE ,PURPLE | C30: NVM | D30: 1 | E30: SET | F30: 15000 | G30: =SUM(F30*D30) -> 15000 | K30: 0 | M30: GIRO 30 JT | N30: =N20+N19+N18+N8+N5 -> 28096000
B31: LAP MICROFIBER RAZO,ALL PURPOSE ,YELLOW | C31: NVM | D31: 1 | E31: SET | F31: 15000 | G31: =SUM(F31*D31) -> 15000 | M31: GIRO 80.270 JT | N31: =N24+N13+N11+N10+N9+N7+N6+N4+N3+N14 -> 79870000
B32: LAP MICROFIBER RAZO,ALL PURPOSE ,RED(GRS) | C32: NVM | D32: 1 | E32: SET | F32: 15000 | G32: =SUM(F32*D32) -> 15000
B33: LAP MICROFIBER RAZO,ALL PURPOSE ,(GRS) WHITE | C33: NVM | D33: 1 | E33: SET | F33: 15000 | G33: =SUM(F33*D33) -> 15000 | J33: =SUM(H23+H43+H49) -> 14440000 | N33: =SUM(N29:N32) -> 130261000
B34: LAP MICROFIBER RAZO,ALL PURPOSE ,(GRS) YELLOW | C34: NVM | D34: 1 | E34: SET | F34: 15000 | G34: =SUM(F34*D34) -> 15000
B35: LAP MICROFIBER RAZO,ALL PURPOSE ,GREY | C35: NVM | D35: 1 | E35: SET | F35: 15000 | G35: =SUM(F35*D35) -> 15000
B36: LAP MICROFIBER RAZO,ALL PURPOSE ,PURPLE | C36: NVM | D36: 1 | E36: SET | F36: 15000 | G36: =SUM(F36*D36) -> 15000
B37: LAP MICROFIBER RAZO,ALL PURPOSE ,WHITE | C37: NVM | D37: 1 | E37: SET | F37: 15000 | G37: =SUM(F37*D37) -> 15000
B38: LAP MICROFIBER RAZO,ALL PURPOSE ,BLUE | C38: NVM | D38: 1 | E38: SET | F38: 15000 | G38: =SUM(F38*D38) -> 15000
B39: LAP MICROFIBER RAZO,ALL PURPOSE ,GREY | C39: NVM | D39: 1 | E39: SET | F39: 15000 | G39: =SUM(F39*D39) -> 15000
B40: LAP MICROFIBER RAZO,ALL PURPOSE ,PURPLE | C40: NVM | D40: 1 | E40: SET | F40: 15000 | G40: =SUM(F40*D40) -> 15000
B41: LAP MICROFIBER RAZO,ALL PURPOSE ,WHITE | C41: NVM | D41: 1 | E41: SET | F41: 15000 | G41: =SUM(F41*D41) -> 15000
B42: LAP MICROFIBER RAZO,ALL PURPOSE ,YELLOW | C42: NVM | D42: 1 | E42: SET | F42: 15000 | G42: =SUM(F42*D42) -> 15000
A43: 44354 | B43: TOWING WELLCO XPANDER | C43: NVM | D43: 3 | E43: SET | F43: 425000 | G43: =SUM(F43*D43) -> 1275000 | H43: =SUM(G43:G44) -> 3400000
B44: TOWING WELLCO INNOVA/FORTUNER | C44: NVM | D44: 5 | E44: SET | F44: 425000 | G44: =SUM(F44*D44) -> 2125000
A45: 44355 | B45: FOOTSTEP SAMPING LAMPU RUSH | C45: KO AKHON | D45: 2 | E45: SET | F45: 1650000 | G45: =SUM(F45*D45) -> 3300000 | H45: =SUM(G45) -> 3300000 | I45: NOVEMBER | K45: 11630000
A46: 44355 | B46: KACA FILM WINTERBLAST HCD 10G C 70 (2103150035K2AG) | C46: WINCOS | D46: 1 | E46: ROL | F46: 0 | G46: =SUM(F46*D46) -> 0 | H46: 0 | I46: BRIO
B47: KACA FILM WINTERBLAST HCD 30G C 70 (2103120200K2A0) | C47: WINCOS | D47: 1 | E47: ROL | F47: 0 | G47: =SUM(F47*D47) -> 0 | H47: 0 | I47: BRIO | K47: 0.025
A48: 44355 | B48: BODY KIT PAJERO SPORT 2021 ORI DESIGN | C48: OTOPROJECT | D48: 1 | E48: SET | F48: 7999000 | G48: =SUM(F48*D48) -> 7999000 | H48: =SUM(G48) -> 7999000 | I48: JULI | J48: LUNAS TF
A49: 44361 | B49: KARPET DASAR CITY 2021 | C49: TJM | D49: 10 | E49: SET | F49: 185000 | G49: =SUM(F49*D49) -> 1850000 | H49: =SUM(G49:G55) -> 7400000 | I49: GIRO OKTOBER | J49: FAKTUR MERAH TDK ADA | K49: =K45*K47 -> 290750
B50: KARPET DASAR BRIO | C50: TJM | D50: 10 | E50: SET | F50: 185000 | G50: =SUM(F50*D50) -> 1850000
B51: KARPET DASAR G.XENIA | C51: TJM | D51: 5 | E51: SET | F51: 185000 | G51: =SUM(F51*D51) -> 925000
B52: KARPET DASAR XPANDER | C52: TJM | D52: 5 | E52: SET | F52: 185000 | G52: =SUM(F52*D52) -> 925000
B53: KARPET DASAR TRITON DC | C53: TJM | D53: 4 | E53: SET | F53: 185000 | G53: =SUM(F53*D53) -> 740000
B54: KARPET DASAR RUSH | C54: TJM | D54: 2 | E54: SET | F54: 185000 | G54: =SUM(F54*D54) -> 370000
B55: KARPET DASAR INNOVA | C55: TJM | D55: 4 | E55: SET | F55: 185000 | G55: =SUM(F55*D55) -> 740000
A56: 44361 | B56: TALANG AIR SLIM LIVINA | C56: IRWAN | D56: 11 | E56: SET | F56: 120000 | G56: =SUM(F56*D56) -> 1320000 | H56: =SUM(G56:G60) -> 7070000 | I56: DESEMBER
B57: GARNIS LAMPU DEPAN RUSH HITAM | C57: IRWAN | D57: 15 | E57: SET | F57: 135000 | G57: =SUM(F57*D57) -> 2025000
B58: GARNIS LAMPU BELAKANG RUSH HITAM | C58: IRWAN | D58: 15 | E58: SET | F58: 145000 | G58: =SUM(F58*D58) -> 2175000
B59: OUTHER CALYA | C59: IRWAN | D59: 10 | E59: SET | F59: 95000 | G59: =SUM(F59*D59) -> 950000
B60: TALANG AIR SLIM L300 | C60: IRWAN | D60: 10 | E60: SET | F60: 60000 | G60: =SUM(F60*D60) -> 600000
A61: 44361 | B61: SPOILER A.N BRIO HITAM | C61: KO AKHON | D61: 2 | E61: PCS | F61: 400000 | G61: =F61*D61 -> 800000 | H61: =SUM(G61:G64) -> 4000000 | I61: NOVEMBER (PERTENGAHAN)
B62: SPOILER A.N BRIO MERAH | C62: KO AKHON | D62: 3 | E62: PCS | F62: 400000 | G62: =F62*D62 -> 1200000
B63: SPOILER A.N BRIO KUNING | C63: KO AKHON | D63: 3 | E63: PCS | F63: 400000 | G63: =F63*D63 -> 1200000
B64: SPOILER A.N BRIO GREY | C64: KO AKHON | D64: 2 | E64: PCS | F64: 400000 | G64: =F64*D64 -> 800000
A65: 44362 | B65: BUZZ RACK | C65: MR.BOSS | D65: 3 | E65: SET | F65: 900000 | G65: =F65*D65 -> 2700000 | H65: =SUM(G65) -> 2700000 | I65: SEPTEMBER
A66: 44365 | B66: KARPET DASAR BRIO | C66: HERMAN | D66: 50 | E66: SET | F66: 150000 | G66: =F66*D66 -> 7500000 | H66: =SUM(G66:G67) -> 8600000 | I66: GIRO 10/11/21
B67: SARUNG JOK RUSH '18 OSCAR HITAM HITAM | C67: HERMAN | D67: 2 | E67: SET | F67: 550000 | G67: =F67*D67 -> 1100000
A68: 44366 | B68: SARUNG JOK SIGRA LEXUS HITAM COFFEE | C68: AM77 | D68: 2 | E68: SET | F68: 740000 | G68: =F68*D68 -> 1480000 | H68: =SUM(G68:G72) -> 5920000 | I68: NOVEMBER GIRO
B69: SARUNG JOK SIGRA LEXUS HITAM MERAH | C69: AM77 | D69: 2 | E69: SET | F69: 740000 | G69: =F69*D69 -> 1480000
B70: SARUNG JOK SIGRA LEXUS CAPPUCINO HITAM | C70: AM77 | D70: 1 | E70: SET | F70: 740000 | G70: =F70*D70 -> 740000
B71: SARUNG JOK SIGRA LEXUS MERAH HITAM | C71: AM77 | D71: 1 | E71: SET | F71: 740000 | G71: =F71*D71 -> 740000
B72: SARUNG JOK AVANZA '12 CAPUCINO CAPUCINO | C72: AM77 | D72: 2 | E72: SET | F72: 740000 | G72: =F72*D72 -> 1480000
A73: 44366 | B73: SARUNG JOK RUSH'21 MB TECK (8801+ 8803) | C73: BUK IDA | D73: 1 | E73: SET | F73: 0 | G73: =F73*D73 -> 0 | H73: 0
A74: 44366 | B74: ROOF BOX GLOSSY BLACK | C74: OTOPROJECT | D74: 1 | E74: SET | F74: 5790000 | G74: =F74*D74 -> 5790000 | H74: =SUM(G74) -> 5790000 | I74: SEPTEMBER | J74: LUNAS TF
A75: 44368 | B75: TALANG AIR XPANDER | C75: IRWAN | D75: 11 | E75: SET | F75: 120000 | G75: =F75*D75 -> 1320000 | H75: =SUM(G75) -> 1320000 | I75: DESEMBAR
A76: 44369 | B76: SARUNG JOK RUSH'18 LEXUS HITAM CAPPUCINO | C76: AM77 | D76: 2 | E76: SET | F76: 740000 | G76: =F76*D76 -> 1480000 | H76: =SUM(G76:G80) -> 6260000 | I76: NOVEMBER GIRO
B77: SARUNG JOK BRIO E LEXUS HITAM KUNING | C77: AM77 | D77: 2 | E77: SET | F77: 640000 | G77: =F77*D77 -> 1280000
B78: SARUNG JOK SIGRA LEXUS HITAM ABU | C78: AM77 | D78: 2 | E78: SET | F78: 740000 | G78: =F78*D78 -> 1480000
B79: SARUNG JOK BRIO E LEXUS HITAM ABU | C79: AM77 | D79: 2 | E79: SET | F79: 640000 | G79: =F79*D79 -> 1280000
B80: SARUNG JOK RUSH'18 LEXUS HITAM ABU | C80: AM77 | D80: 1 | E80: SET | F80: 740000 | G80: =F80*D80 -> 740000
A81: 44370 | B81: KACA FILM WINTERBLAST HCD 10G C 70 (2103290159K2AL) | C81: WINCOS | D81: 1 | E81: ROL | F81: 0 | G81: =F81*D81 -> 0 | H81: 0 | I81: BRIO
A82: 44370 | B82: KACA FILM CPF1 60% | C82: JKI | D82: 1 | E82: ROL | F82: 5500000 | G82: =F82*D82 -> 5500000 | H82: =SUM(G82) -> 5500000 | I82: GANTI YG RUSAK
A83: 44371 | B83: SARUNG JOK RUSH MB TECK(9001 + 9007 ) | C83: BUK IDA | D83: 1 | E83: SET | F83: 0 | G83: =F83*D83 -> 0
A84: 44372 | B84: BRIO'18 REAR SCUFF PLATE ACTIVO W/REFLECTOR | C84: JSL | D84: 10 | E84: SET | F84: 200000 | G84: =F84*D84 -> 2000000 | H84: =SUM(G84:G100) -> 9475000 | I84: NOVEMBER
B85: PAJERO'21/TRITON'21 HEAD LAMP GARNISH CHROME | C85: JSL | D85: 5 | E85: SET | F85: 150000 | G85: =F85*D85 -> 750000
B86: PAJERO'21 TAIL LAMP GARNISH CHROME | C86: JSL | D86: 5 | E86: SET | F86: 160000 | G86: =F86*D86 -> 800000
B87: PAJERO'21/TRITON'21 SIGN LAMP GARNISH CHROME | C87: JSL | D87: 5 | E87: SET | F87: 160000 | G87: =F87*D87 -> 800000
B88: LIVINA'19 HEAD LAMP GARNISH BLACKTIVO | C88: JSL | D88: 2 | E88: SET | F88: 100000 | G88: =F88*D88 -> 200000
B89: LIVINA'19 TAIL LAMP GARNISH BLACKTIVO | C89: JSL | D89: 2 | E89: SET | F89: 125000 | G89: =F89*D89 -> 250000
B90: LIVINA'19 HEAD LAMP GARNISH CHROME | C90: JSL | D90: 2 | E90: SET | F90: 100000 | G90: =F90*D90 -> 200000
B91: LIVINA'19 TAIL LAMP GARNISH CHROME | C91: JSL | D91: 2 | E91: SET | F91: 125000 | G91: =F91*D91 -> 250000
B92: BRIO'18 REAR SIDE PLATE ACTIVO | C92: JSL | D92: 5 | E92: SET | F92: 150000 | G92: =F92*D92 -> 750000
B93: RUSH'18 REAR SIDE PLATE ACTIVO SPORTY | C93: JSL | D93: 5 | E93: SET | F93: 175000 | G93: =F93*D93 -> 875000
B94: LIVINA'19 OUTER HANDLE COVER ELEGANT CHROME | C94: JSL | D94: 2 | E94: SET | F94: 85000 | G94: =F94*D94 -> 170000
B95: LIVINA'19 OUTER HANDLE COVER ELEGANT BLACKTIVO | C95: JSL | D95: 1 | E95: SET | F95: 85000 | G95: =F95*D95 -> 85000
B96: LIVINA'19 TANK COVER CROSSTIVO | C96: JSL | D96: 2 | E96: SET | F96: 35000 | G96: =F96*D96 -> 70000
... B100: BRIO'18 TAIL LAMP GARNISH BLACKTIVO | C100: JSL | D100: 10 | E100: SET | F100: 100000 | G100: =F100*D100 -> 1000000
A101: 44375 | B101: GRILL DEPAN INNOVA '21 MDL PRADO | C101: IRWAN | D101: 2 | E101: SET | F101: 1200000 | G101: =F101*D101 -> 2400000 | H101: =SUM(G101) -> 2400000 | I101: DESEMBER
F102: 0 | G102: =F102*D102 -> 0
F103: 0 | G103: =F103*D103 -> 0
...

Sheet JULI
A1: BARANG MASUK ARAW FILM | K1: BON JATUH TEMPO NOVEMBER 2021 ( JT)
A2: TGL MASUK | B2: NAMA BARANG | C2: SUPLIER | D2: QTY | E2: SAT | F2: HARGA/PCS/SET | G2: JUMLAH | H2: TOTAL FAKTUR | I2: KET | K2: NO | L2: TGL BARANG MASUK | M2: NAMA SALES/ SUPLIER | N2: JUMLAH BON | O2: KET
A3: 44378 | B3: TOWBEL CUSTOM W/L + ANTING- PAJERO SPORT DUDUKAN MERAH FB | C3: AM77 | D3: 2 | E3: SET | F3: 2200000 | G3: =SUM(F3*D3) -> 4400000 | H3: =SUM(G3) -> 4400000 | I3: DESEMBER GIRO | K3: 1 | L3: 44343 | M3: KO AKHON | N3: 9600000 | O3: LUNAS TF. TGL 15/10/21
A4: 44379 | B4: SARUNG JOK BRIO SATYA MB TECK (9001+9005) | C4: BUK IDA | D4: 1 | E4: SET | F4: 0 | G4: =SUM(F4*D4) -> 0 | H4: 0 | K4: 2 | L4: 44344 | M4: HERMAN | N4: 940000 | O4: GIRO TGL 10/11/21 | R4: PINDAH KE BULAN 10 (5JT) | T4: V
A5: 44380 | B5: KACA FILM WINTERBLAST HCD 10G C 70 (2103150087K2AG) | C5: WINCOWS | D5: 1 | E5: ROL | F5: 0 | G5: 0 | H5: 0 | I5: BRIO | K5: 3 | L5: 44344 | M5: IRWAN | N5: 15782000 | O5: GIRO 15/11/21 | Q5: =N5+N6 -> 17577000 | R5: V
B6: KACA FILM WINTERBLAST HCD 10G C 70 (2103150085K2AE) | C6: WINCOWS | D6: 1 | E6: ROL | F6: 0 | G6: 0 | K6: 4 | L6: 44344 | M6: IRWAN | N6: 1795000
B7: KACA FILM WINTERBLAST HCD 30G C 70 (2103120127K2A8) | C7: WINCOWS | D7: 1 | E7: ROL | F7: 0 | G7: 0 | K7: 5 | L7: 44345 | M7: LEO | N7: 3900000 | O7: GIRO TGL 15/11/21 | Q7: V | R7: =N4+N13+N21 -> 17040000
A8: 44382 | B8: SARUNG JOK RAIZE MB TECK (9001+9016) | C8: TOLIB | D8: 1 | E8: SET | F8: 1550000 | G8: =SUM(F8*D8) -> 1550000 | H8: =SUM(G8) -> 1550000 | I8: SISA 550.000 | K8: 6 | L8: 44366 | M8: AM77 | N8: 5920000 | O8: GIRO TGL.15/11/21
A9: 44382 | B9: ROOF RACK ADVENTURE | C9: PEGASUS | D9: 1 | E9: SET | F9: 1000000 | G9: =SUM(F9*D9) -> 1000000 | H9: =SUM(G9:G11) -> 5900000 | I9: LUNAS | K9: 7 | L9: 44348 | M9: KO AKHON | N9: 11600000 | O9: LUNAS TF. TGL 15/10/21 | Q9: =N3+N9+N11+N15+N18+N19+N20 -> 46200000 | R9: 17040000
B10: MIGHTY SPORT RACK | C10: PEGASUS | D10: 1 | E10: SET | F10: 1100000 | G10: =SUM(F10*D10) -> 1100000 | K10: 8 | L10: 44369 | M10: AM77 | N10: 6260000 | O10: GIRO TGL.15/11/21 | R10: =R7-R9 -> 0
B11: PAJERO 2021 BUMPER RHINO GUARD II | C11: PEGASUS | D11: 2 | E11: SET | F11: 1900000 | G11: =SUM(F11*D11) -> 3800000 | K11: 9 | L11: 44348 | M11: KO AKHON | N11: 4725000 | O11: LUNAS TF. TGL 15/10/21
A12: 44383 | B12: SARUNG JOK SIGRA/LEXUS HITAM CAPUCINO (VARIASI) | C12: AM77 | D12: 1 | E12: SET | F12: 740000 | G12: =SUM(F12*D12) -> 740000 | H12: =SUM(G12:G16) -> 5720000 | I12: DESEMBER GIRO | K12: 10 | L12: 44350 | M12: JKI | N12: 3300000 | O12: GIRO TGL 30/11/21 | R12: =N3+N9+N11 -> 25925000
B13: SARUNG JOK RUSH '18/LEXUS HITAM ABU | C13: AM77 | D13: 1 | E13: SET | F13: 740000 | G13: =SUM(F13*D13) -> 740000 | K13: 11 | L13: 44350 | M13: HERMAN | N13: 7500000 | O13: GIRO TGL 10/11/21
B14: SARUNG JOK BRIO E/ LEXUS HITAM CAPPUCINO | C14: AM77 | D14: 2 | E14: SET | F14: 640000 | G14: =SUM(F14*D14) -> 1280000 | K14: 12 | L14: 44352 | M14: JKI | N14: 5500000 | O14: GIRO TGL 30/11/21
B15: SARUNG JOK AVANZA'15/LEXUS HITAM CAPPUCINO | C15: AM77 | D15: 2 | E15: SET | F15: 740000 | G15: =SUM(F15*D15) -> 1480000 | K15: 13 | L15: 44352 | M15: KO AKHON | N15: 975000 | O15: LUNAS TF. TGL 29/10/21 | R15: =R12+R16 -> 46200000
B16: SARUNG JOK AVANZA'15/LEXUS HITAM | C16: AM77 | D16: 2 | E16: SET | F16: 740000 | G16: =SUM(F16*D16) -> 1480000 | K16: 14 | L16: 44354 | M16: IRWAN | N16: 5500000 | O16: GIRO TGL 30/11/21 | R16: =N15+N18+N19+N20 -> 20275000
A17: 44385 | B17: SARUNG STIR DRD HITAM-MERAH | C17: IRWAN | D17: 10 | E17: SET | F17: 120000 | G17: =SUM(F17*D17) -> 1200000 | H17: =SUM(G17:G31) -> 14425000 | I17: DESEMBER | K17: 15 | L17: 44354 | M17: LEO | N17: 2000000 | O17: GIRO TGL 15/11/21
B18: SARUNG STIR DRD HITAM-ABU | C18: IRWAN | D18: 5 | E18: SET | F18: 120000 | G18: =SUM(F18*D18) -> 600000 | K18: 16 | L18: 44354 | M18: KO AKHON | N18: 12000000 | O18: LUNAS TF. TGL 29/10/21 | Q18: V | R18: =N7+N17 -> 5900000
B19: SARUNG STIR DRD HITAM-CREAM | C19: IRWAN | D19: 5 | E19: SET | F19: 120000 | G19: =SUM(F19*D19) -> 600000 | K19: 17 | L19: 44355 | M19: KO AKHON | N19: 3300000
B20: SARUNG STIR DRD HITAM-COKLAT | C20: IRWAN | D20: 5 | E20: SET | F20: 120000 | G20: =SUM(F20*D20) -> 600000 | K20: 18 | L20: 44361 | M20: KO AKHON | N20: 4000000
B21: SARUNG STIR DRD HITAM-POLOS | C21: IRWAN | D21: 5 | E21: SET | F21: 120000 | G21: =SUM(F21*D21) -> 600000 | K21: 19 | L21: 44365 | M21: HERMAN | N21: 8600000 | O21: GIRO TGL 10/11/21
B22: KAKI RAK BAGASI AUTO BOY | C22: IRWAN | D22: 2 | E22: SET | F22: 620000 | G22: =SUM(F22*D22) -> 1240000 | K22: 20 | L22: 44372 | M22: JSL | N22: 9475000 | O22: GIRO TGL 10/11/21 | Q22: V
B23: TRUNKLID PAJERO'16 HITAM | C23: IRWAN | D23: 5 | E23: SET | F23: 1000000 | G23: =SUM(F23*D23) -> 5000000 | K23: 21 | L23: 44411 | M23: TJM | N23: 18500000 | O23: LUNAS TF. TGL 06/11/21
B24: LAMPU HID I-CONCEPT 3 WARNA H4 | C24: IRWAN | D24: 3 | E24: SET | F24: 475000 | G24: =SUM(F24*D24) -> 1425000 | K24: 22 | L24: 44487 | M24: HERMAN(PINJAMAN) | N24: 15000000 | O24: GIRO 30/11/21
B25: ANTENA SIRIP HIU HYBRID MERAH | C25: IRWAN | D25: 5 | E25: SET | F25: 45000 | G25: =SUM(F25*D25) -> 225000 | K25: 23 | L25: 44517 | M25: HENDRIK | N25: 4845000 | O25: LUNAS CASH 29/11
B26: EMBLEM CUP MESIN XPANDER CROSS CHROME | C26: IRWAN | D26: 10 | E26: SET | F26: 120000 | G26: =SUM(F26*D26) -> 1200000
B27: OUTHER HITAM XPANDER | C27: IRWAN | D27: 5 | E27: SET | F27: 95000 | G27: =SUM(F27*D27) -> 475000 | M27: TOTAL | N27: =SUM(N3:N26) -> 161017000
B28: HANDLE HITAM XPANDER | C28: IRWAN | D28: 5 | E28: SET | F28: 85000 | G28: =SUM(F28*D28) -> 425000
B29: ANTENA SIRIP HIU HYBRID SILVER | C29: IRWAN | D29: 7 | E29: SET | F29: 45000 | G29: =SUM(F29*D29) -> 315000 | M29: DI BYR DG GIRO | N29: =N4+N5+N6+N7+N8+N10+N12+N13+N14+N16+N17+N21+N22+N24 -> 91472000
B30: BHOLAM STANDAR H11 55 WATT | C30: IRWAN | D30: 10 | E30: SET | F30: 25000 | G30: =SUM(F30*D30) -> 250000 | M30: LUNAS CASH/TF | N30: =N3+N9+N11+N15+N18+N19+N20+N23+N25 -> 69545000
B31: BHOLAM STANDAR H16 19 WATT | C31: IRWAN | D31: 10 | E31: SET | F31: 27000 | G31: =SUM(F31*D31) -> 270000
A32: 44385 | B32: BANTALAN LEHER RAIZE | C32: TOLIB | D32: 2 | E32: SET | F32: 0 | G32: 0 | H32: 0
A33: 44385 | B33: KARPET MOBIL FULL 360 1 LAPIS ALL NEW PAJERO '16 TYPE D | C33: MR. BOSS | D33: 1 | E33: SET | F33: 1790000 | G33: =F33*D33 -> 1790000 | H33: =SUM(G33) -> 1790000 | I33: TITIPAN MR BOSS KE ARAW
A34: 44387 | B34: CM ORCA RC-185-2F KOTAK INFRA RED TWO FUNCTION | C34: ORCA | D34: 20 | E34: PCS | F34: 100000 | G34: =D34*F34 -> 2000000 | H34: =SUM(G34) -> 2000000 | I34: DESEMBER (PERTENGAHAN) | N34: =SUM(N29:N30) -> 161017000
A35: 44389 | B35: TANDUK+ BRAKET RUSH '18 DELUXE | C35: IRWAN | D35: 5 | E35: SET | F35: 730000 | G35: =D35*F35 -> 3650000 | H35: =SUM(G35:G37) -> 5825000 | I35: DESEMBER (AKHIR)
B36: ANTENA SIRIP HIU HYBRID HITAM | C36: IRWAN | D36: 5 | E36: \P | F36: 45000 | G36: =D36*F36 -> 225000 | M36: KO AKHON 4.5 BLN
B37: TALANG AIR FLAT CITY HB | C37: IRWAN | D37: 15 | E37: ;[LK | F37: 130000 | G37: =D37*F37 -> 1950000
A38: 44396 | B38: BODY KIT CITY HB MODULO DESIGN | C38: OTOPROJECT | D38: 2 | E38: SET | F38: 2699000 | G38: =D38*F38 -> 5398000 | H38: =SUM(G38:G43) -> 10305000 | I38: SEPTEMBER
B39: DOOR SILT PLATE CITY HB W/LAMP ORI DESIGN | C39: OTOPROJECT | D39: 2 | E39: SET | F39: 425000 | G39: =D39*F39 -> 850000
B40: MUFFLER CUTTER PAJERO'16 | C40: OTOPROJECT | D40: 5 | E40: SET | F40: 150000 | G40: =D40*F40 -> 750000
B41: FRONT GRILL RUSH'18 NEW FORTUNER STYLE GLOSSY BLACK | C41: OTOPROJECT | D41: 1 | E41: SET | F41: 1069000 | G41: =D41*F41 -> 1069000
B42: FRONT GRILL RUSH'18 NEW FORTUNER STYLE MATTE BLACK | C42: OTOPROJECT | D42: 1 | E42: SET | F42: 1069000 | G42: =D42*F42 -> 1069000
B43: FRONT GRILL NEW PAJERO SPORT'21 APOLLO DESIGN GLOSSY BLACK | C43: OTOPROJECT | D43: 1 | E43: SET | F43: 1169000 | G43: =D43*F43 -> 1169000
A44: 44396 | B44: SARUNG JOK BRIO SATYA MB TECK (8801+8810) | C44: BUK IDA | D44: 1 | E44: SET | F44: 0 | G44: 0 | H44: 0
A45: 44398 | B45: SARUNG JOK RUSH '18/LEXUS HITAM | C45: AM77 | D45: 4 | E45: SET | F45: 740000 | G45: =F45*D45 -> 2960000 | H45: =SUM(G45) -> 2960000 | I45: GIRO DESEMBER
A46: 44400 | B46: SERVICE TV | C46: ORCA | D46: 1 | E46: SET | F46: 150000 | G46: =F46*D46 -> 150000 | H46: =SUM(G46) -> 150000 | I46: JULI
A47: 44400 | B47: KACA FILM WINTERBLAST HCD 10G C 70 (2106040037EGAK) | C47: WINCOWS | D47: 1 | E47: ROL | F47: 0 | G47: =F47*D47 -> 0 | H47: 0
B48: KACA FILM WINTERBLAST HCD 10G C 70 (2106040034EGAH) | C48: WINCOWS | D48: 1 | E48: ROL | F48: 0 | G48: =F48*D48 -> 0
B49: KACA FILM WINTERBLAST HCD 30G C 70 (2103290087K2AL) | C49: WINCOWS | D49: 1 | E49: ROL | F49: 0 | G49: =F49*D49 -> 0
A50: 44404 | B50: BODY KIT PAJERO 2021 SILVER | C50: IRWAN | D50: 1 | E50: SET | F50: 8500000 | G50: =F50*D50 -> 8500000 | H50: =SUM(G50:G52) -> 9900000 | I50: JANUARI
B51: GARNISH DEPAN INNOVA 2016 HITAM | C51: IRWAN | D51: 5 | E51: SET | F51: 135000 | G51: =F51*D51 -> 675000
B52: GARNISH BELAKANG INNOVA 2016 HITAM | C52: IRWAN | D52: 5 | E52: SET | F52: 145000 | G52: =F52*D52 -> 725000
B53: HANDLE AVZ 2019 CARBON | C53: IRWAN | D53: 4 | E53: SET | F53: 110000 | G53: =F53*D53 -> 440000 | H53: =SUM(G53:G55) -> 3670000 | I53: DESEMBER
B54: LAMPU STROBO GRILE TIPIS BIRU-BIRU | C54: IRWAN | D54: 9 | E54: SET | F54: 220000 | G54: =F54*D54 -> 1980000
B55: LAMPU REFLEKTOR BELAKANG FORTUNER 2016 | C55: IRWAN | D55: 5 | E55: SET | F55: 250000 | G55: =F55*D55 -> 1250000
A56: 44404 | B56: SPOILER CITY HB MODULO DESIGN | C56: OTOPROJECT | D56: 2 | E56: SET | F56: 499000 | G56: =F56*D56 -> 998000 | H56: =SUM(G56:G57) -> 2975000 | I56: SEPTEMBER
B57: SIDE SKITE BRIO 2018 RS TYPE | C57: OTOPROJECT | D57: 3 | E57: SET | F57: 659000 | G57: =F57*D57 -> 1977000

Sheet AGUSTUS
A1: BARANG MASUK ARAW FILM | K1: BON JATUH TEMPO DESEMBER 2021 ( JT)
A2: TGL MASUK | B2: NAMA BARANG | C2: SUPLIER | D2: QTY | E2: SAT | F2: HARGA/PCS/SET | G2: JUMLAH | H2: TOTAL FAKTUR | I2: KET | K2: NO | L2: TGL BARANG MASUK | M2: NAMA SALES/ SUPLIER | N2: JUMLAH BON | O2: KET
A3: 44410 | B3: KARPET DASAR JAZZ'19 HITAM TIPIS | C3: HERMAN | D3: 20 | E3: SET | F3: 145000 | G3: =F3*D3 -> 2900000 | H3: =SUM(G3) -> 2900000 | I3: JANUARI | K3: 1 | L3: 44354 | M3: IRWAN | N3: 10000000 | O3: GIRO TGL 15/12/21
A4: 44410 | B4: KERANDA | C4: JAYA MADANI | D4: 1 | E4: SET | F4: 3600000 | G4: =F4*D4 -> 3600000 | H4: =SUM(G4) -> 3600000 | I4: AGUSTUS ( AKHIR) | K4: 2 | L4: 44361 | M4: IRWAN | N4: 7070000 | R4: =960/120 -> 8
A5: 44411 | B5: KARPET DASAR SUPER BRIO HITAM | C5: NU (TOLIB) | D5: 5 | E5: SET | F5: 150000 | G5: =F5*D5 -> 750000 | H5: =SUM(G5:G6) -> 1500000 | I5: LUNAS 26/7/21 (AGUSTUS) | K5: 3 | L5: 44368 | M5: IRWAN | N5: 1320000
B6: KARPET DASAR SUPER HITAM CITY HAUS BEK | C6: NU (TOLIB) | D6: 5 | E6: SET | F6: 150000 | G6: =F6*D6 -> 750000 | K6: 4 | L6: 44375 | M6: IRWAN | N6: 2400000
A7: 44411 | B7: SUPERLID D/C HILUX REVO +KIT | C7: TJM | D7: 1 | E7: SET | F7: 18500000 | G7: =F7*D7 -> 18500000 | H7: =SUM(G7) -> 18500000 | I7: NOVEMBER | K7: 5 | L7: 44378 | M7: AM77 | N7: 4400000 | O7: GIRO TGL 15/12/21 | S7: =SUM(AGUSTUS!N7+AGUSTUS!N8+AGUSTUS!N12) -> 13080000
A8: 44411 | B8: LAMPU POLISI LED MERAH | C8: IRWAN | D8: 1 | E8: SET | F8: 2900000 | G8: =F8*D8 -> 2900000 | H8: =SUM(G8) -> 2900000 | I8: JANUARI | K8: 6 | L8: 44383 | M8: AM77 | N8: 5720000 | O8: GIRO TGL 15/12/21
A9: 44411 | B9: KARPET DASAR AN BRIO TIPTS | C9: HERMAN | D9: 30 | E9: SET | F9: 150000 | G9: =F9*D9 -> 4500000 | H9: =SUM(G9) -> 4500000 | I9: JANUARI | K9: 7 | L9: 44385 | M9: IRWAN | N9: 14425000 | O9: GIRO TGL 15/12/21 | Q9: 3600
A10: 44413 | B10: SARUNG JOK BRIO SATYA H/M | C10: BUK IDA | D10: 1 | E10: SET | F10: 0 | G10: =F10*D10 -> 0 | H10: =SUM(G10) -> 0 | K10: 8 | L10: 44387 | M10: ORCA | N10: 2000000 | O10: GIRO TGL 30/12/21 | Q10: 960
A11: 44414 | B11: KARPET DASAR BRIO HITAM TIPIS | C11: HERMAN | D11: 30 | E11: SET | F11: 150000 | G11: =F11*D11 -> 4500000 | H11: =SUM(G11:G12) -> 9000000 | I11: JANUARI | K11: 9 | L11: 44389 | M11: IRWAN | N11: 5825000 | O11: GIRO TGL 15/12/21 | Q11: 1400
B12: KARPET DASAR JAZZ'19 HITAM TIPIS | C12: HERMAN | D12: 30 | E12: SET | F12: 150000 | G12: =F12*D12 -> 4500000 | K12: 10 | L12: 44398 | M12: AM77 | N12: 2960000 | O12: GIRO TGL 15/12/21
A13: 44415 | B13: GRILLE PAJERO '21 MODEL ALPHARD | C13: IRWAN | D13: 1 | E13: SET | F13: 1300000 | G13: =F13*D13 -> 1300000 | H13: =SUM(G13:G15) -> 4950000 | I13: JANUARI | K13: 11 | L13: 44404 | M13: IRWAN | N13: 3670000 | O13: GIRO TGL 15/12/21 | Q13: =SUM(Q9:Q12) -> 5960
B14: TANDUK +BREKET AVANZA'19 DELEXU | C14: IRWAN | D14: 5 | E14: SET | F14: 730000 | G14: =F14*D14 -> 3650000 | K14: 12 | L14: 44421 | M14: MR BOSS | N14: 750000 | O14: GIRO TGL 30/12/21 | S14: =AGUSTUS!N4+AGUSTUS!N5+AGUSTUS!N6+AGUSTUS!N9+AGUSTUS!N11+AGUSTUS!N13+AGUSTUS!N3 -> 44710000
B15: TANDUK +BREKET RUSH'19 DELEXU | C15: IRWAN | D15: 1 | E15: SET | F15: BONUS | K15: 13 | L15: 44400 | M15: ORCA | N15: 150000 | O15: GIRO . TGL 30/12/21
A16: 44415 | B16: EMBLEM CUP MESIN PAJERO SPORT CHROME | C16: IRWAN | D16: 8 | E16: SET | F16: 120000 | G16: =F16*D16 -> 960000 | H16: =SUM(G16) -> 960000 | I16: MARET | K16: 14 | L16: 44464 | M16: MR BOSS | N16: 14645000 | O16: GIRO TGL 30/12/21
A17: 44415 | B17: EMBLEM RS ORI GRILL DEPAN | C17: HERMAN | D17: 5 | E17: PCS | F17: RETUR TDK COCOK | G17: 0 | H17: =SUM(G17:G29) -> 2225000 | I17: JANUARI | K17: 15 | L17: 44481 | M17: OTOPROJECT | N17: 3518400 | O17: LUNAS TF. TGL 2/12/21 | Q17: =AGUSTUS!N14+AGUSTUS!N16+AGUSTUS!N19 -> 16175000
B18: COLOKAN SEAT BELT DOUBLE HONDA | C18: HERMAN | D18: 12 | E18: PCS | F18: 45000 | G18: =D18*F18 -> 540000 | K18: 16 | L18: 44483 | M18: TJM | N18: 11190000 | O18: GIRO TGL 25/12/21 | Q18: =SUM(AGUSTUS!N14+AGUSTUS!N16) -> 15395000
B19: COLOKAN SEAT BELT DOUBLE TOYOTA | C19: HERMAN | D19: 8 | E19: PCS | F19: 45000 | G19: =D19*F19 -> 360000 | K19: 17 | L19: 44459 | M19: MR BOSS | N19: 780000 | O19: GIRO TGL 30/12/21
B20: EMBLEM CUP MENSIN XPANDER CHROME | C20: HERMAN | D20: 10 | E20: SET | F20: 82500 | G20: =D20*F20 -> 825000 | K20: 18 | L20: 44487 | M20: HERMAN (PINJAMAN) | N20: 15000000 | O20: GIRO TGL 12/12/21
B21: SILIKON KUNCI HONDA BRIO HITAM | C21: HERMAN | D21: 10 | E21: PCS | F21: 10000 | G21: =D21*F21 -> 100000 | K21: 19 | L21: 44498 | M21: V-CENT | N21: 2100000 | O21: LUNAS TF. TGL 04/01/22 | S21: =44*200 -> 8800
B22: SILIKON KUNCI HONDA BRIO MERAH | C22: HERMAN | D22: 6 | E22: PCS | F22: 10000 | G22: =D22*F22 -> 60000 | K22: 20 | L22: 44515 | M22: V-CENT | N22: 3200000 | Q22: =SUM(N21:N22) -> 5300000
B23: SILIKON KUNCI HONDA BRIO BIRU | C23: HERMAN | D23: 4 | E23: PCS | F23: 10000 | G23: =D23*F23 -> 40000 | K23: 21 | L23: 44512 | M23: JAYA MADANI | N23: 7200000 | O23: LUNAS TF
B24: SILIKON KUNCI TOYOTA RUSH/VELOZ HITAM | C24: HERMAN | D24: 10 | E24: PCS | F24: 10000 | G24: =D24*F24 -> 100000 | K24: 22 | L24: 44539 | M24: WINCOS | N24: 29800000 | O24: LUNAS TF. TGL 29/12/21
B25: SILIKON KUNCI TOYOTA RUSH/VELOZ MERAH | C25: HERMAN | D25: 6 | E25: PCS | F25: 10000 | G25: =D25*F25 -> 60000 | K25: 23 | L25: 44551 | M25: HENDRIK | N25: 4892500 | O25: LUNAS TF. 06/01/22 | Q25: 4892500
B26: SILIKON KUNCI TOYOTA RUSH/VELOZ BIRU | C26: HERMAN | D26: 4 | E26: PCS | F26: 10000 | G26: =D26*F26 -> 40000
B27: SILIKON KUNCI TOYOTA 3 TOMBOL ALL NEW FORTUNER HITAM | C27: HERMAN | D27: 5 | E27: PCS | F27: 10000 | G27: =D27*F27 -> 50000 | M27: TOTAL | N27: =SUM(N3:N26) -> 153015900
B28: SILIKON KUNCI TOYOTA 3 TOMBOL ALL NEW FORTUNER MERAH | C28: HERMAN | D28: 3 | E28: PCS | F28: 10000 | G28: =D28*F28 -> 30000
B29: SILIKON KUNCI TOYOTA 3 TOMBOL ALL NEW FORTUNER BIRU | C29: HERMAN | D29: 2 | E29: PCS | F29: 10000 | G29: =D29*F29 -> 20000
A30: 44415 | B30: KACA FILM PREMIUM HCD 03 G 2107010017K2A8 | C30: WINCOS | D30: 1 | E30: ROL | F30: 19800000 | G30: =D30*F30 -> 19800000 | H30: =SUM(G30:G31) -> 39600000 | I30: LUNAS TGL 30/8/21
B31: KACA FILM PREMIUM HCD 20 G 2107010046K2AA | C31: WINCOS | D31: 1 | E31: ROL | F31: 19800000 | G31: =D31*F31 -> 19800000 | M31: GIRO | N31: =N3+N4+N5+N6+N7+N8+N9+N10+N11+N12+N13+N14+N15+N16+N18+N19+N20 -> 102305000
A32: 44417 | B32: TOWING RUSH/TERIOS MCC | C32: GREAT | D32: 10 | E32: SET | F32: 1200000 | G32: =D32*F32 -> 12000000 | H32: =SUM(G32) -> 12000000 | I32: JANUARI
A33: 44420 | B33: TRUNKLID FORTUNER LED | C33: GREAT | D33: 10 | E33: SET | F33: 900000 | G33: =D33*F33 -> 9000000 | H33: =SUM(G33) -> 9000000 | I33: JANUARI
A34: 44421 | B34: SARUNG JOK BRIO SATYA MB TECK(9001+9005) | C34: BUK IDA | D34: 1 | E34: SET | F34: 0 | G34: =D34*F34 -> 0 | H34: 0
A35: 44421 | B35: SILT PLATE BELAKANG INNOVA'16 | C35: MR.BOSS | D35: 5 | E35: SET | F35: 150000 | G35: =D35*F35 -> 750000 | H35: =SUM(G35) -> 750000 | I35: DESEMBER
A36: 44424 | B36: FOGLAMP RUSH '18 | C36: IRWAN | D36: 4 | E36: SET | F36: 450000 | G36: =F36*D36 -> 1800000 | H36: =SUM(G36) -> 1800000 | I36: PENGGANTI BARANG
A37: 44424 | B37: TRANK LID ALL NEW FORTUNER + LAMPU RING | C37: IRWAN | D37: 10 | E37: SET | F37: 1000000 | G37: =F37*D37 -> 10000000 | H37: =SUM(G37) -> 10000000 | I37: APRIL
A38: 44424 | B38: OUTER ALL NEW PAJERO HITAM | C38: IRWAN | D38: 10 | E38: SET | F38: 95000 | G38: =D38*F38 -> 950000 | H38: =SUM(G38:G42) -> 10550000 | I38: JANUARI
B39: HANDLE ALL NEW RUSH '18 HITAM | C39: IRWAN | D39: 10 | E39: SET | F39: 85000 | G39: =D39*F39 -> 850000
B40: TANK COVER KARBON CALYA | C40: IRWAN | D40: 5 | E40: SET | F40: 50000 | G40: =D40*F40 -> 250000
B41: BODY KIT PAJERO '21 SILVER | C41: IRWAN | D41: 1 | E41: SET | F41: 8500000 | G41: =D41*F41 -> 8500000
B42: KETERANGAN : BRAKET TOWING PAJERO | C42: IRWAN | D42: 1 | E42: PCS | G42: =D42*F42 -> 0
A43: 44424 | B43: SARUNG JOK SATYA '18 HITAM BD FR | C43: HERMAN | D43: 1 | E43: SET | F43: 635000 | G43: =D43*F43 -> 635000 | H43: =SUM(G43:G45) -> 3065000 | I43: JANUARI
B44: SARUNG JOK G. AVZ HITAM BD FR | C44: HERMAN | D44: 2 | E44: SET | F44: 735000 | G44: =D44*F44 -> 1470000
B45: KARPET DASAR RUSH HITAM TIPIS | C45: HERMAN | D45: 6 | E45: SET | F45: 160000 | G45: =D45*F45 -> 960000
A46: 44424 | B46: SIDE SKITE A.N BRIO '18 RS TYPE | C46: OTOPROJECT | D46: 12 | E46: SET | F46: 888000 | G46: =D46*F46 -> 10656000 | H46: =SUM(G46:G47) -> 10656000 | I46: OKTOBER
B47: RER DIFFUSER A.N BRIO '18 RS TYPE | C47: OTOPROJECT | D47: 12 | E47: SET | F47: 0 | G47: =D47*F47 -> 0
A48: 44426 | B48: TOWING HRV MCC | C48: GREAT | D48: 3 | E48: SET | F48: 1200000 | G48: =D48*F48 -> 3600000 | H48: =SUM(G48) -> 3600000 | I48: DESEMBER
A49: 44426 | B49: SARUNG JOK BRIO SATYA HITAM POLOS | C49: HERMAN | D49: 2 | E49: SET | F49: 635000 | G49: =D49*F49 -> 1270000 | H49: =SUM(G49:G55) -> 10090000 | I49: JANUARI | J49: =SUM(H49:H59) -> 12930000
B50: SARUNG JOK CALYA HITAM POLOS | C50: HERMAN | D50: 3 | E50: SET | F50: 735000 | G50: =D50*F50 -> 2205000
B51: SARUNG JOK SIGRA HITAM POLOS | C51: HERMAN | D51: 2 | E51: SET | F51: 735000 | G51: =D51*F51 -> 1470000
B52: SARUNG JOK AVANZA AB HITAM POLOS | C52: HERMAN | D52: 1 | E52: SET | F52: 735000 | G52: =D52*F52 -> 735000
B53: SARUNG JOK XPANDER HITAM POLOS | C53: HERMAN | D53: 2 | E53: SET | F53: 735000 | G53: =D53*F53 -> 1470000
B54: SARUNG JOK G.AVANZA HITAM POLOS | C54: HERMAN | D54: 2 | E54: SET | F54: 735000 | G54: =D54*F54 -> 1470000
B55: SARUNG JOK G.XENIA HITAM POLOS | C55: HERMAN | D55: 2 | E55: SET | F55: 735000 | G55: =D55*F55 -> 1470000
A56: 44426 | B56: SARUNG JOK CALYA HITAM POLOS | C56: HERMAN | D56: 1 | E56: SET | F56: 735000 | G56: =D56*F56 -> 735000 | H56: =SUM(G56:G59) -> 2840000
B57: SARUNG JOK AVANZA AB HITAM POLOS | C57: HERMAN | D57: 1 | E57: SET | F57: 735000 | G57: =D57*F57 -> 735000
B58: SARUNG JOK BRIO SATYA HITAM POLOS | C58: HERMAN | D58: 1 | E58: SET | F58: 635000 | G58: =D58*F58 -> 635000
B59: SARUNG JOK SIGRA HITAM POLOS | C59: HERMAN | D59: 1 | E59: SET | F59: 735000 | G59: =D59*F59 -> 735000
A60: 44427 | B60: KACA FILM WINTERBLAST HCD 10G C 70 (2103300084K2AA) | C60: WINCOS | D60: 1 | E60: ROL | F60: 0 | G60: =D60*F60 -> 0 | H60: 0 | I60: BRIO
B61: KACA FILM WINTERBLAST HCD 10G C 70 (2103300089K2AF) | C61: WINCOS | D61: 1 | E61: ROL | F61: 0 | G61: =D61*F61 -> 0 | I61: BRIO
B62: KACA FILM WINTERBLAST HCD 30G C 70 (2106030086EGAN) | C62: WINCOS | D62: 1 | E62: ROL | F62: 0 | G62: =D62*F62 -> 0 | I62: BRIO
A63: 44427 | B63: SARUNG JOK BRIO SATYA MB 9001+ MB 9003 | C63: BUK IDA | D63: 1 | E63: SET | F63: 0 | G63: =D63*F63 -> 0 | H63: 0
A64: 44427 | B64: GARNISH DEPAN PAJERO'21 ATAS HITAM | C64: IRWAN | D64: 10 | E64: SET | F64: 140000 | G64: =D64*F64 -> 1400000 | H64: =SUM(G64:G69) -> 6025000 | I64: JANUARI
B65: GARNISH DEPAN PAJERO'21 BAWAH HITAM | C65: IRWAN | D65: 10 | E65: SET | F65: 140000 | G65: =D65*F65 -> 1400000
B66: GARNISH BELAKANG PAJERO'21 HITAM | C66: IRWAN | D66: 10 | E66: SET | F66: 155000 | G66: =D66*F66 -> 1550000
B67: GARNISH DEPAN AVANZA'19 HITAM | C67: IRWAN | D67: 5 | E67: SET | F67: 145000 | G67: =D67*F67 -> 725000
B68: OUTER ALL NEW FORTUNER '16 HITAM | C68: IRWAN | D68: 5 | E68: SET | F68: 95000 | G68: =D68*F68 -> 475000
B69: OUTER ALL NEW FORTUNER '16 CHROME | C69: IRWAN | D69: 5 | E69: SET | F69: 95000 | G69: =D69*F69 -> 475000
A70: 44427 | B70: GARNISH DEPAN HILUX'21 HITAM (G) | C70: IRWAN | D70: 5 | E70: SET | F70: 140000 | G70: =F70*D70 -> 700000 | H70: =SUM(G70:G71) -> 1400000 | I70: MARET
B71: GARNISH BELAKANG HILUX'21 HITAM (G) | C71: IRWAN | D71: 5 | E71: SET | F71: 140000 | G71: =F71*D71 -> 700000 | M71: 2900 | N71: 3670
A72: 44432 | B72: SARUNG JOK SATYA '18 HITAM ABU FR VARIASI | C72: HERMAN | D72: 1 | E72: SET | F72: 635000 | G72: =D72*F72 -> 635000 | H72: =SUM(G72:G76) -> 6050000 | I72: JANUARI | M72: 4950 | N72: 5825
B73: SARUNG JOK G.AVANZA HITAM ABU FR VARIASI | C73: HERMAN | D73: 1 | E73: SET | F73: 740000 | G73: =D73*F73 -> 740000 | M73: 6025 | N73: 14425 | P73: 3650
B74: SARUNG JOK SATYA '18 HITAM MERAH FR VARIASI | C74: HERMAN | D74: 1 | E74: SET | F74: 740000 | G74: =D74*F74 -> 740000 | M74: 10550 | N74: 1320 | P74: 225 | S74: 9900
B75: SARUNG JOK G.AVANZA HITAM BD FR | C75: HERMAN | D75: 1 | E75: SET | F75: 735000 | G75: =D75*F75 -> 735000 | M75: 9900 | N75: 2400 | P75: 2860 | S75: 3670
B76: KD XENIA HITAM TIPIS | C76: HERMAN | D76: 20 | E76: SET | F76: 160000 | G76: =D76*F76 -> 3200000 | N76: 7070 | P76: =SUM(P73:P75) -> 6735 | Q76: =P76-910 -> 5825
A77: 44433 | B77: WINTERBLAST HCD 60% | C77: WINCOS | D77: 1 | E77: ROLL | F77: 0 | G77: =D77*F77 -> 0 | H77: BRIO | N77: 10000 | S77: =SUM(S74:S76) -> 13570
B78: WINTERBLAST HCD 40% | C78: WINCOS | D78: 1 | E78: ROLL | F78: 0 | G78: =D78*F78 -> 0 | H78: BRIO
A79: 44434 | B79: KERANDA | C79: JAYA MADANI | D79: 1 | E79: SET | F79: 3600000 | G79: =D79*F79 -> 3600000 | H79: =SUM(G79) -> 3600000 | I79: AGUSTUS | M79: =SUM(M71:M78) -> 34325 | N79: =SUM(N71:N78) -> 44710
A80: 44438 | B80: SARUNG JOK BRIO SATYA HITAM ABU FR VARIASI | C80: HERMAN | D80: 1 | E80: SET | F80: 640000 | G80: =D80*F80 -> 640000 | H80: =SUM(G80:G82) -> 2020000 | I80: FEBRUARI | J80: =SUM(H80:H86) -> 7955000
B81: SARUNG JOK BRIO SATYA HITAM MERAH FR VARIASI | C81: HERMAN | D81: 1 | E81: SET | F81: 640000 | G81: =D81*F81 -> 640000
B82: SARUNG JOK G.AVANZA HITAM ABU FR VARIASI | C82: HERMAN | D82: 1 | E82: SET | F82: 740000 | G82: =D82*F82 -> 740000
A83: 44438 | B83: KARPET DASAR RUSH'18 HITAM | C83: HERMAN | D83: 10 | E83: SET | F83: 210000 | G83: =D83*F83 -> 2100000 | H83: =SUM(G83:G84) -> 4150000 | I83: FEBRUARI | J83: =SUM(H80:H86) -> 7955000
B84: KARPET DASAR BRIO HITAM | C84: HERMAN | D84: 10 | E84: SET | F84: 205000 | G84: =D84*F84 -> 2050000
A85: 44438 | B85: SARUNG JOK AVANZA AB CAPUCINO | C85: HERMAN | D85: 1 | E85: SET | F85: 735000 | G85: =D85*F85 -> 735000 | H85: =SUM(G85:G86) -> 1785000 | I85: FEBRUARI
B86: KARPET DASAR INNOVA HITAM | C86: HERMAN | D86: 5 | E86: SET | F86: 210000 | G86: =D86*F86 -> 1050000

Sheet SEPTEMBER
A1: BARANG MASUK ARAW FILM | K1: BON JATUH TEMPO JANUARI 2022 ( JT)
A2: TGL MASUK | B2: NAMA BARANG | C2: SUPLIER | D2: QTY | E2: SAT | F2: HARGA/PCS/SET | G2: JUMLAH | H2: TOTAL FAKTUR | I2: KET | K2: NO | L2: TGL BARANG MASUK | M2: NAMA SALES/ SUPLIER | N2: JUMLAH BON | O2: KET
A3: 44441 | B3: SARUNG STIR JEWEL HITAM BENANG MERAH | C3: IRWAN | D3: 10 | E3: SET | F3: 120000 | G3: =F3*D3 -> 1200000 | H3: =SUM(G3:G6) -> 3600000 | I3: MARET | K3: 1 | L3: 44404 | M3: IRWAN | N3: 9900000 | O3: GIRO TGL 20/1/22
B4: SARUNG STIR JEWEL HITAM MERAH HITAM | C4: IRWAN | D4: 10 | E4: SET | F4: 120000 | G4: =F4*D4 -> 1200000 | K4: 2 | L4: 44410 | M4: HERMAN | N4: 3000000 | O4: GIRO TGL 30/01/2022
B5: SARUNG STIR JEWEL CREAM HITAM CREAM | C5: IRWAN | D5: 5 | E5: SET | F5: 120000 | G5: =F5*D5 -> 600000 | K5: 3 | L5: 44411 | M5: IRWAN | N5: 2900000 | O5: GIRO TGL 20/1/22
B6: SARUNG STIR JEWEL ABU HITAM ABU | C6: IRWAN | D6: 5 | E6: SET | F6: 120000 | G6: =F6*D6 -> 600000 | K6: 4 | L6: 44411 | M6: HERMAN | N6: 4500000 | O6: GIRO TGL 30/01/2022
A7: 44441 | B7: TOWING ARB RUSH'18/AVANZA | C7: IRWAN | D7: 5 | E7: SET | F7: 420000 | G7: =F7*D7 -> 2100000 | H7: =SUM(G7:G12) -> 4750000 | I7: GIRO 20/2/22 | K7: 5 | L7: 44414 | M7: HERMAN | N7: 9000000 | O7: GIRO TGL 30/01/2022
B8: BEMPER MINI +BRAKET CALYA | C8: IRWAN | D8: 2 | E8: SET | F8: 650000 | G8: =F8*D8 -> 1300000 | K8: 6 | L8: 44415 | M8: IRWAN | N8: 4950000 | O8: GIRO TGL 20/1/22
B9: OUTHER XPANDER CHROME | C9: IRWAN | D9: 5 | E9: SET | F9: 95000 | G9: =F9*D9 -> 475000 | K9: 7 | L9: 44415 | M9: HERMAN | N9: 2225000 | O9: GIRO TGL 30/01/2022
B10: HANDLE BRIO CHROME | C10: IRWAN | D10: 5 | E10: SET | F10: 85000 | G10: =F10*D10 -> 425000 | K10: 8 | L10: 44417 | M10: GREAT | N10: 12000000 | O10: LUNAS TF TGL 10/1/22
B11: TANK COVER CHROME PAJERO'16 | C11: IRWAN | D11: 5 | E11: SET | F11: 45000 | G11: =F11*D11 -> 225000 | K11: 9 | L11: 44420 | M11: GREAT | N11: 9000000
B12: TANK COVER AGYA HITAM | C12: IRWAN | D12: 5 | E12: SET | F12: 45000 | G12: =F12*D12 -> 225000 | K12: 10 | L12: 44426 | M12: GREAT | N12: 3600000
A13: 44442 | B13: KARPET DASAR RUSH'18 HITAM | C13: HERMAN | D13: 10 | E13: SET | F13: 210000 | G13: =F13*D13 -> 2100000 | H13: =SUM(G13) -> 2100000 | I13: FEBRUARI | J13: =SUM(H13:H16) -> 4945000 | K13: 11 | L13: 44424 | M13: IRWAN | N13: 10550000 | O13: GIRO TGL 20/1/22
A14: 44442 | B14: SARUNG JOK XPANDER CAPUCINO BD FR | C14: HERMAN | D14: 2 | E14: SET | F14: 735000 | G14: =F14*D14 -> 1470000 | H14: =SUM(G14:G16) -> 2845000 | I14: FEBRUARI | K14: 12 | L14: 44424 | M14: HERMAN | N14: 3065000 | O14: GIRO TGL 30/01/2022
B15: SARUNG JOK AVANZA CAPUCINO BD FR | C15: HERMAN | D15: 1 | E15: SET | F15: 735000 | G15: =F15*D15 -> 735000 | K15: 13 | L15: 44426 | M15: HERMAN | N15: 12930000 | O15: GIRO TGL 30/01/2022
B16: SARUNG JOK BRIO SATYA HITAM KUNING VARIASI | C16: HERMAN | D16: 1 | E16: SET | F16: 640000 | G16: =F16*D16 -> 640000 | K16: 14 | L16: 44427 | M16: IRWAN | N16: 6025000 | O16: GIRO TGL 20/1/22
A17: 44442 | B17: KACA FILM 3 M 40% | C17: ERIK | D17: 1 | E17: ROL | F17: 2500000 | G17: =F17*D17 -> 2500000 | H17: =SUM(G17) -> 2500000 | I17: LUNAS TF. 01/9/21 | K17: 15 | L17: 44432 | M17: HERMAN | N17: 6055000 | O17: GIRO TGL 30/01/2022
A18: 44442 | B18: KACA FILM WINCOS HCD 30G UK 1.52X30M | C18: WINCOS | D18: 1 | E18: ROL | F18: 19800000 | G18: =F18*D18 -> 19800000 | H18: =SUM(G18) -> 19800000 | I18: LUNAS TF. 29/9/21 | K18: 16 | L18: 44448 | M18: TJM | N18: 4690000 | O18: GIRO TGL 25/1/22
A19: 44443 | B19: LOGO HONDA CHROME BRIO | C19: HERMAN | D19: 50 | E19: SET | F19: 35000 | G19: =F19*D19 -> 1750000 | H19: =SUM(G19) -> 1750000 | I19: FEBRUARI | K19: 17 | L19: 44452 | M19: TJM | N19: 5055000 | O19: GIRO TGL 25/1/22
A20: 44445 | B20: SARUNG JOK BRIO SATYA'18 HITAM KUNING | C20: HERMAN | D20: 1 | E20: SET | F20: 640000 | G20: =F20*D20 -> 640000 | H20: =SUM(G20:G22) -> 4020000 | I20: FEBRUARI | J20: =SUM(H20:H24) -> 6095000 | K20: 18 | L20: 44453 | M20: TJM | N20: 6300000 | O20: GIRO TGL 25/1/22
B21: SARUNG JOK BRIO SATYA'18 HITAM CAPUCINO | C21: HERMAN | D21: 2 | E21: SET | F21: 640000 | G21: =F21*D21 -> 1280000 | K21: 19 | L21: 44466 | M21: TJM | N21: 2880000 | O21: GIRO TGL 25/1/22
B22: KDP ALL NEW XENIA | C22: HERMAN | D22: 10 | E22: SET | F22: 210000 | G22: =F22*D22 -> 2100000 | K22: 20 | L22: 44491 | M22: TJM | N22: 3600000 | O22: GIRO TGL 25/1/22
A23: 44445 | B23: KDP HILUX DC HITAM | C23: HERMAN | D23: 5 | E23: SET | F23: 205000 | G23: =F23*D23 -> 1025000 | H23: =SUM(G23:G24) -> 2075000 | I23: FEBRUARI | K23: 21 | L23: 44522 | M23: TJM | N23: 12500000 | O23: LUNAS TF. 31/1/22
B24: KDP ALL NEW INNOVA HITAM | C24: HERMAN | D24: 5 | E24: SET | F24: 210000 | G24: =F24*D24 -> 1050000
A25: 44445 | B25: FORTUNER'21 BUMPER RHINO GUARD II | C25: PEGASUS | D25: 2 | E25: SET | F25: 1900000 | G25: =F25*D25 -> 3800000 | H25: =SUM(G25:G28) -> 9900000 | I25: lunas tf 2/9/ | M25: TOTAL | N25: =SUM(N3:N24) -> 134725000
B26: PAJERO'21 BUMPER RHINO GUARD II | C26: PEGASUS | D26: 2 | E26: SET | F26: 1900000 | G26: =F26*D26 -> 3800000
B27: PAJERO'21 BUMPER RHINO GUARD II + LED PJG 120 W | C27: PEGASUS | D27: 1 | E27: SET | F27: 2300000 | G27: =F27*D27 -> 2300000 | M27: GIRO | N27: =N22+N21+N20+N19+N18+N17+N16+N15+N14+N13+N9+N8+N7+N6+N5+N4+N3 -> 97625000
B28: LAMPU LED | C28: PEGASUS | D28: 1 | E28: SET | F28: 0 | G28: =F28*D28 -> 0
A29: 44445 | B29: KACA FILM WINTERBLAST HCD 10G C 70 (2105060085K2AG) | C29: WINCOS | D29: 1 | E29: SET | F29: 0 | G29: =F29*D29 -> 0 | H29: 0 | I29: BRIO
B30: KACA FILM WINTERBLAST HCD 10G C 70 (2105060073K2AD) | C30: WINCOS | D30: 1 | E30: SET | F30: 0 | G30: =F30*D30 -> 0
B31: KACA FILM WINTERBLAST HCD 30G C 70 (2106030079EGAP) | C31: WINCOS | D31: 1 | E31: SET | F31: 0 | G31: =F31*D31 -> 0
A32: 44446 | B32: TANKI COVER FIT AN AVANZA CHROME | C32: IRWAN | D32: 10 | E32: SET | F32: 45000 | G32: =F32*D32 -> 450000 | H32: =SUM(G32:G41) -> 15300000 | I32: FEBRUARI
B33: OUTER TERIOS '18 HITAM | C33: IRWAN | D33: 5 | E33: SET | F33: 95000 | G33: =F33*D33 -> 475000
B34: HANDLE BRIO CHROME | C34: IRWAN | D34: 5 | E34: SET | F34: 85000 | G34: =F34*D34 -> 425000
B35: EMBLEM CUP MESIN XPANDER CHROME | C35: IRWAN | D35: 10 | E35: SET | F35: 110000 | G35: =F35*D35 -> 1100000
B36: HANDLE CARBON AN RUSH'18 | C36: IRWAN | D36: 1 | E36: SET | F36: 130000 | G36: =F36*D36 -> 130000
B37: TALANG AIR FLAT ALL NEW BRIO | C37: IRWAN | D37: 22 | E37: SET | F37: 120000 | G37: =F37*D37 -> 2640000
B38: TALANG AIR FLAT ALL NEW PAJERO | C38: IRWAN | D38: 20 | E38: SET | F38: 120000 | G38: =F38*D38 -> 2400000
B39: TALANG AIR FLAT MOBILIO | C39: IRWAN | D39: 14 | E39: SET | F39: 120000 | G39: =F39*D39 -> 1680000
B40: BALANCE ARM PAJERO | C40: IRWAN | D40: 2 | E40: SET | F40: 1500000 | G40: =F40*D40 -> 3000000
B41: BALANCE ARM FORTUNER | C41: IRWAN | D41: 2 | E41: SET | F41: 1500000 | G41: =F41*D41 -> 3000000
A42: 44446 | B42: ADR-9988 ECO 9 INCH 2G+16G (PART NO:EA 168-99) | C42: ORCA | D42: 3 | E42: SET | F42: 1300000 | G42: =F42*D42 -> 3900000 | H42: =SUM(G42:G52) -> 6910000 | I42: FEBRUARI | J42: =SUM(H42:H64) -> 23891000
B43: WIPER HYBRID RWB T 170 UK.14" | C43: ORCA | D43: 10 | E43: SET | F43: 36000 | G43: =F43*D43 -> 360000
B44: WIPER HYBRID RWB T 170 UK.16" | C44: ORCA | D44: 10 | E44: SET | F44: 36000 | G44: =F44*D44 -> 360000
B45: WIPER HYBRID RWB T 170 UK.18" | C45: ORCA | D45: 10 | E45: SET | F45: 36000 | G45: =F45*D45 -> 360000
B46: WIPER HYBRID RWB T 170 UK.20" | C46: ORCA | D46: 10 | E46: SET | F46: 36000 | G46: =F46*D46 -> 360000
B47: WIPER HYBRID RWB T 170 UK.22" | C47: ORCA | D47: 10 | E47: SET | F47: 36000 | G47: =F47*D47 -> 360000 | L47: =H42+H53+H57 -> 23891000
B48: WIPER HYBRID RWB T 170 UK.17" | C48: ORCA | D48: 10 | E48: SET | F48: 36000 | G48: =F48*D48 -> 360000
B49: SM-018 H RING SPEAKER 6" HONDA | C49: ORCA | D49: 10 | E49: SET | F49: 35000 | G49: =F49*D49 -> 350000
B50: RCA CABLE 042-3M FROSTED BLACK/HYN | C50: ORCA | D50: 5 | E50: SET | F50: 23000 | G50: =F50*D50 -> 115000
B51: RCA CABLE 042-5M FROSTED BLACK/HYN | C51: ORCA | D51: 5 | E51: SET | F51: 28000 | G51: =F51*D51 -> 140000
B52: POWER CABLE PC-8AWG RED (30 MTR)/HYN | C52: ORCA | D52: 1 | E52: ROLL | F52: 245000 | G52: =F52*D52 -> 245000
B53: ADR-9988 ECO 10.1 INCH 2G+16G (PART NO:EA 168-1087) | C53: ORCA | D53: 3 | E53: SET | F53: 1400000 | G53: =F53*D53 -> 4200000 | H53: =SUM(G53:G56) -> 5800000 | I53: FEBRUARI
B54: IIL-7700 (PART NO : EA168-6005) | C54: ORCA | D54: 3 | E54: SET | F54: 160000 | G54: =F54*D54 -> 480000
B55: IIL-7700 (PART NO : EA168-6002) | C55: ORCA | D55: 3 | E55: SET | F55: 160000 | G55: =F55*D55 -> 480000
B56: IIL-7700 (PART NO : EA168-6005) | C56: ORCA | D56: 4 | E56: SET | F56: 160000 | G56: =F56*D56 -> 640000
B57: BODY COVER RWB ALL NEW BRIO | C57: ORCA | D57: 10 | E57: SET | F57: 126125 | G57: =F57*D57 -> 1261250 | H57: =SUM(G57:G64) -> 11181000 | I57: FEBRUARI
B58: BODY COVER RWB ALL NEW AGYA | C58: ORCA | D58: 20 | E58: SET | F58: 126125 | G58: =F58*D58 -> 2522500
B59: BODY COVER RWB ALL NEW YARRIS | C59: ORCA | D59: 10 | E59: SET | F59: 126125 | G59: =F59*D59 -> 1261250
B60: BODY COVER RWB CALYA | C60: ORCA | D60: 10 | E60: SET | F60: 131875 | G60: =F60*D60 -> 1318750
B61: BODY COVER RWB GRAND AVANZA | C61: ORCA | D61: 7 | E61: SET | F61: 131875 | G61: =F61*D61 -> 923125
B62: BODY COVER RWB GRAND INNOVA | C62: ORCA | D62: 10 | E62: SET | F62: 140500 | G62: =F62*D62 -> 1405000
B63: BODY COVER RWB XPANDER | C63: ORCA | D63: 10 | E63: SET | F63: 140500 | G63: =F63*D63 -> 1405000
B64: BODY COVER RWB GRAND FORTUNER | C64: ORCA | D64: 7 | E64: SET | F64: 154875 | G64: =F64*D64 -> 1084125
A65: 44446 | B65: SARUNG JOK GRAND AVANZA HITAM MOCCA FR VARIASI | C65: HERMAN | D65: 1 | E65: SET | F65: 740000 | G65: =F65*D65 -> 740000 | H65: =SUM(G65:G66) -> 9740000 | I65: FEBRUARI
B66: KDP ALL NEW BRIO HITAM TIPIS | C66: HERMAN | D66: 60 | E66: SET | F66: 150000 | G66: =F66*D66 -> 9000000
A67: 44446 | B67: LIVINA'19 OUTER HANDLE COVER ELEGANT BLACKTIVO | C67: JSL | D67: 1 | E67: SET | F67: 85000 | G67: =F67*D67 -> 85000 | H67: =SUM(G67:G80) -> 7200000 | I67: FEBRUARI
B68: AVANZA TANK COVER CROSSTIVO | C68: JSL | D68: 3 | E68: SET | F68: 30000 | G68: =F68*D68 -> 90000
B69: AN BRIO'18 REAR SCUFF PLATE BLACK W/REFLEKTOR | C69: JSL | D69: 10 | E69: SET | F69: 175000 | G69: =F69*D69 -> 1750000
B70: AN RUSH/TERIOS'18 SIDE SCUFF PLATE BLACK | C70: JSL | D70: 10 | E70: SET | F70: 75000 | G70: =F70*D70 -> 750000
B71: AN AVANZA TANK COVER CROSSTIVO | C71: JSL | D71: 10 | E71: SET | F71: 30000 | G71: =F71*D71 -> 300000
B72: AN PAJERO'16 SIDE SCUFF PLATE BLACK | C72: JSL | D72: 10 | E72: SET | F72: 85000 | G72: =F72*D72 -> 850000
B73: NEW YARIS'18 SIDE SCUFF PLATE ACTIVO | C73: JSL | D73: 5 | E73: SET | F73: 150000 | G73: =F73*D73 -> 750000
B74: SIGRA'16 TANK COVER CROSSTIVO BLACKTIVO | C74: JSL | D74: 10 | E74: SET | F74: 35000 | G74: =F74*D74 -> 350000
B75: AN BRIO'18 TANK COVER CADILLAC BLACKTIVO | C75: JSL | D75: 10 | E75: SET | F75: 35000 | G75: =F75*D75 -> 350000
B76: AN TERIOS'18 TANK COVER CADILLAC BLACKTIVO | C76: JSL | D76: 10 | E76: SET | F76: 35000 | G76: =F76*D76 -> 350000
B77: NEW YARIS'18 OUTER HANDLE COVER BLACKTIVO | C77: JSL | D77: 5 | E77: SET | F77: 125000 | G77: =F77*D77 -> 625000
B78: XPANDER'17 OUTER HANDLE COVER ELEGANT CHROME | C78: JSL | D78: 4 | E78: SET | F78: 80000 | G78: =F78*D78 -> 320000
B79: AN INNOVA'16 SIDE SCUFF PLATE BLACK | C79: JSL | D79: 10 | E79: SET | F79: 55000 | G79: =F79*D79 -> 550000
B80: XPANDER'17 OUTER HANDLE COVER ELEGANT CHROME | C80: JSL | D80: 1 | E80: SET | F80: 80000 | G80: =F80*D80 -> 80000
A81: 44448 | B81: KDP HD BRIO'18 BLACK | C81: TJM | D81: 4 | E81: SET | F81: 180000 | G81: =F81*D81 -> 720000 | H81: =SUM(G81:G82) -> 1090000 | I81: JANUARI | J81: =SUM(H81:H83) -> 4690000
B82: KDP TY RAIZE, BLACK | C82: TJM | D82: 2 | E82: SET | F82: 185000 | G82: =F82*D82 -> 370000
B83: TALANG AIR BRIO SLIM | C83: TJM | D83: 30 | E83: SET | F83: 120000 | G83: =F83*D83 -> 3600000 | H83: =SUM(G83) -> 3600000
A84: 44449 | B84: DIFFUSER ALL NEW BRIO '19 | C84: IRWAN | D84: 30 | E84: SET | F84: 320000 | G84: =F84*D84 -> 9600000 | H84: =SUM(G84:G91) -> 16880000 | I84: FEBRUARI
B85: TALANG AIR FLAT BRIO | C85: IRWAN | D85: 5 | E85: SET | F85: 120000 | G85: =F85*D85 -> 600000
B86: OUTER AVANZA HITAM | C86: IRWAN | D86: 20 | E86: SET | F86: 95000 | G86: =F86*D86 -> 1900000
B87: TANK COVER BRIO HITAM | C87: IRWAN | D87: 10 | E87: SET | F87: 45000 | G87: =F87*D87 -> 450000
B88: HANDLE RAIZE HITAM | C88: IRWAN | D88: 5 | E88: SET | F88: 100000 | G88: =F88*D88 -> 500000
B89: OUTER HITAM RAIZE | C89: IRWAN | D89: 3 | E89: SET | F89: 110000 | G89: =F89*D89 -> 330000 | J89: 3600
B90: TOWING ARB FULL KNOCK DOWN MERAH+LED PAJERO | C90: IRWAN | D90: 1 | E90: SET | F90: 1750000 | G90: =F90*D90 -> 1750000 | J90: 1090
B91: TOWING ARB FULL KNOCK DOWN MERAH+LED FORTUNER | C91: IRWAN | D91: 1 | E91: SET | F91: 1750000 | G91: =F91*D91 -> 1750000
A92: 44452 | B92: KDP CITY 2021 HITAM | C92: TJM | D92: 10 | E92: SET | F92: 180000 | G92: =F92*D92 -> 1800000 | H92: =SUM(G92:G95) -> 5055000 | I92: JANUARI | J92: =SUM(J89:J91) -> 4690
B93: KDP BRIO '18 HITAM | C93: TJM | D93: 10 | E93: SET | F93: 180000 | G93: =F93*D93 -> 1800000
B94: KDP RAIZE HITAM | C94: TJM | D94: 3 | E94: SET | F94: 185000 | G94: =F94*D94 -> 555000
B95: KDP YARIS 2021 HITAM | C95: TJM | D95: 5 | E95: SET | F95: 180000 | G95: =F95*D95 -> 900000
A96: 44452 | B96: KACA FILM 3M FXST 60 % | C96: LEO | D96: 1 | E96: ROL | F96: 1800000 | G96: =F96*D96 -> 1800000 | H96: =SUM(G96:G97) -> 3600000 | I96: LUNAS TF 23/12/21
B97: KACA FILM 3M FXST 40 % | C97: LEO | D97: 1 | E97: ROL | F97: 1800000 | G97: =F97*D97 -> 1800000
A98: 44452 | B98: SARUNG JOK AVANZA HITAM CAPUCINO FERARI VARIASI | C98: HERMAN | D98: 1 | E98: SET | F98: 740000 | G98: =F98*D98 -> 740000 | H98: =SUM(G98:G100) -> 2815000 | I98: FEBRUARI
B99: KDP HRV HITAM | C99: HERMAN | D99: 5 | E99: SET | F99: 205000 | G99: =F99*D99 -> 1025000
B100: KDP FORTUNER HITAM | C100: HERMAN | D100: 5 | E100: SET | F100: 210000 | G100: =F100*D100 -> 1050000
...

Sheet OKTOBER
A1: BARANG MASUK ARAW FILM | K1: BON JATUH TEMPO FEBRUARI 2022 ( JT)
A2: TGL MASUK | B2: NAMA BARANG | C2: SUPLIER | D2: QTY | E2: SAT | F2: HARGA/PCS/SET | G2: JUMLAH | H2: TOTAL FAKTUR | I2: KET | K2: NO | L2: TGL BARANG MASUK | M2: NAMA SALES/ SUPLIER | N2: JUMLAH BON | O2: KET
A3: 44473 | B3: SARUNG JOK MB TECK RUSH (9001 +9015) | C3: BUK IDA | D3: 1 | E3: SET | F3: 0 | G3: 0 | H3: 0 | K3: 1 | L3: 44438 | M3: HERMAN | N3: 7975000 | O3: GIRO TGL 25/2/22
A4: 44474 | B4: DIFFUSER AN.BRIO 2018 RS TYPE | C4: OTOPROJECT | D4: 50 | E4: SET | F4: 300000 | G4: =F4*D4 -> 15000000 | H4: =SUM(G4) -> 15000000 | I4: MARET | K4: 2 | L4: 44441 | M4: IRWAN | N4: 4750000 | O4: GIRO TGL 20/2/22
A5: 44474 | B5: WINTERBLAST HCD 30G C70 (2106030063EGAI) | C5: WINCOS | D5: 1 | E5: ROLL | F5: 0 | G5: =F5*D5 -> 0 | H5: 0 | I5: BRIO | K5: 3 | L5: 44442 | M5: HERMAN | N5: 4945000 | O5: GIRO TGL 25/2/22
A6: 44476 | B6: TALANG AIR AN.BRIO | C6: IRWAN | D6: 22 | E6: SET | F6: 120000 | G6: =F6*D6 -> 2640000 | H6: =SUM(G6:G9) -> 12490000 | I6: MARET | K6: 4 | L6: 44443 | M6: HERMAN | N6: 1750000 | O6: GIRO TGL 25/2/22 | Q6: =N8+N14 -> 32180000
B7: GRILLE M.LEXUS PAJERO 2021 | C7: IRWAN | D7: 1 | E7: SET | F7: 1450000 | G7: =F7*D7 -> 1450000 | K7: 5 | L7: 44445 | M7: HERMAN | N7: 6095000 | O7: GIRO TGL 25/2/22
B8: TOWING ARB RUSH'18/AVANZA | C8: IRWAN | D8: 10 | E8: SET | F8: 420000 | G8: =F8*D8 -> 4200000 | K8: 6 | L8: 44446 | M8: IRWAN | N8: 15300000 | O8: GIRO TGL 25/2/22
B9: TOWING ARB CALYA | C9: IRWAN | D9: 10 | E9: SET | F9: 420000 | G9: =F9*D9 -> 4200000 | K9: 7 | L9: 44446 | M9: JSL | N9: 7200000 | O9: GIRO TGL 5/2/22
B10: INJAKAN SAMPING OEM TRITON 2019 | C10: IRWAN | D10: 2 | E10: SET | F10: 1750000 | G10: =F10*D10 -> 3500000 | H10: =SUM(G10:G13) -> 10400000 | I10: APRIL | K10: 8 | L10: 44446 | M10: HERMAN | N10: 9740000 | O10: GIRO TGL 25/2/22
B11: OVERFENDER TRITON 2019 | C11: IRWAN | D11: 1 | E11: SET | F11: 1700000 | G11: =F11*D11 -> 1700000 | K11: 9 | L11: 44446 | M11: ORCA | N11: 11181000 | O11: GIRO TGL 26/2/22
B12: INJAKAN SAMPING THANOS XPANDER | C12: IRWAN | D12: 2 | E12: SET | F12: 1650000 | G12: =F12*D12 -> 3300000 | K12: 10 | L12: 44446 | M12: ORCA | N12: 5800000
B13: GRILLE M.TRD RUSH 2018 GLOSY | C13: IRWAN | D13: 2 | E13: SET | F13: 950000 | G13: =F13*D13 -> 1900000 | K13: 11 | L13: 44446 | M13: ORCA | N13: 6910000
B14: SPOILER BRIO HITAM | C14: IRWAN | D14: 10 | E14: SET | F14: 400000 | G14: =F14*D14 -> 4000000 | H14: =SUM(G14:G17) -> 16000000 | I14: MEI | K14: 12 | L14: 44449 | M14: IRWAN | N14: 16880000 | O14: GIRO TGL 25/2/22
B15: SPOILER BRIO MERAH | C15: IRWAN | D15: 10 | E15: SET | F15: 400000 | G15: =F15*D15 -> 4000000 | K15: 13 | L15: 44452 | M15: HERMAN | N15: 2815000 | O15: GIRO TGL 25/2/22
B16: SPOILER BRIO PUTIH | C16: IRWAN | D16: 10 | E16: SET | F16: 400000 | G16: =F16*D16 -> 4000000 | K16: 14 | L16: 44464 | M16: GREAT(KO AKHON) | N16: 4500000 | O16: LUNAS TF. TGL 07/02/22
B17: SPOILER BRIO SILVER | C17: IRWAN | D17: 10 | E17: SET | F17: 400000 | G17: =F17*D17 -> 4000000 | K17: 15 | L17: 44487 | M17: TJM | N17: 5400000 | O17: GIRO TGL 25/2/22
A18: 44476 | B18: SARUNG JOK MB TECK INNOVA G 2014 (9001 +9007) | C18: BUK IDA | D18: 1 | E18: SET | F18: 0 | G18: =F18*D18 -> 0 | H18: 0 | K18: 16 | L18: 44494 | M18: TJM | N18: 4830000 | O18: GIRO TGL 25/2/22
A19: 44477 | B19: AMPLIFIER ORCA 4 CHANNEL -7889A | C19: ORCA/YUSUF | D19: 3 | E19: SET | F19: 450000 | G19: =F19*D19 -> 1350000 | H19: =SUM(G19:G20) -> 2205000 | I19: MARET | K19: 17 | L19: 44480 | M19: GREAT | N19: 8500000 | O19: TRANSFER TGL 28/2/22
B20: SPEAKER SPLIT ORCA RC-652SPL 6.5'' | C20: ORCA/YUSUF | D20: 3 | E20: SET | F20: 285000 | G20: =F20*D20 -> 855000
A21: 44477 | B21: FRAME ORCA HO136H H. BRIO / MOBILIO 10.1 INCH TH. 2012 | C21: ORCA/YUSUF | D21: 6 | E21: SET | F21: 250000 | G21: =F21*D21 -> 1500000 | H21: 1500000 | I21: MATER
A22: 44477 | B22: TOWING DEPAN MINI RUSH 2018 | C22: IRWAN | D22: 2 | E22: SET | F22: 650000 | G22: =F22*D22 -> 1300000 | H22: =SUM(G22:G30) -> 9545000 | I22: APRIL | J22: =SUM(H22:H41) -> 15975000
B23: TALANG AIR BRIO ALL NEW | C23: IRWAN | D23: 11 | E23: SET | F23: 120000 | G23: =F23*D23 -> 1320000
B24: LIPT BAMPER BAWAH ALL NEW BRIO | C24: IRWAN | D24: 9 | E24: SET | F24: 500000 | G24: =F24*D24 -> 4500000
B25: SILIKON KUNCI ALL NEW BRIO | C25: IRWAN | D25: 15 | E25: SET | F25: 10000 | G25: =F25*D25 -> 150000 | N25: =SUM(N3:N24) -> 124571000 | Q25: tjm 4bln
B26: KLIP BAMPER KECIL | C26: IRWAN | D26: 10 | E26: SET | F26: 22500 | G26: =F26*D26 -> 225000
B27: KLIP BAMPER BESAR | C27: IRWAN | D27: 10 | E27: SET | F27: 25000 | G27: =F27*D27 -> 250000 | M27: ANGGARAN 70 JT
B28: DOORAUARD LUXURY DAIHATSU ( KARET PINTU) | C28: IRWAN | D28: 5 | E28: SET | F28: 45000 | G28: =F28*D28 -> 225000
B29: DOORAUARD LUXURY MITSUBHSHI ( KARET PINTU) | C29: IRWAN | D29: 15 | E29: SET | F29: 45000 | G29: =F29*D29 -> 675000
B30: DOORAUARD BRAVO TOYOTA ( KARET PINTU) | C30: IRWAN | D30: 20 | E30: SET | F30: 45000 | G30: =F30*D30 -> 900000
B31: DOORAUARD BRAVO DAIHATSU ( KARET PINTU) | C31: IRWAN | D31: 8 | E31: SET | F31: 45000 | G31: =F31*D31 -> 360000 | H31: =SUM(G31:G41) -> 6430000 | I31: MEI
B32: DOORAUARD BRAVO HONDA ( KARET PINTU) | C32: IRWAN | D32: 20 | E32: SET | F32: 45000 | G32: =F32*D32 -> 900000
B33: DOORAUARD BRAVO MITSUBDHI ( KARET PINTU) | C33: IRWAN | D33: 20 | E33: SET | F33: 45000 | G33: =F33*D33 -> 900000
B34: OUTHER ALL NEW BRIO CHROME | C34: IRWAN | D34: 5 | E34: SET | F34: 95000 | G34: =F34*D34 -> 475000
B35: TANK COVER PAJERO 2016 HITAM | C35: IRWAN | D35: 10 | E35: SET | F35: 45000 | G35: =F35*D35 -> 450000
B36: TANK COVER XPANDER HITAM | C36: IRWAN | D36: 10 | E36: SET | F36: 45000 | G36: =F36*D36 -> 450000
B37: TANK COVER AYLA HITAM | C37: IRWAN | D37: 10 | E37: SET | F37: 45000 | G37: =F37*D37 -> 450000
B38: GARNIS BELAKANG ALL NEW RUSH HITAM | C38: IRWAN | D38: 15 | E38: SET | F38: 145000 | G38: =F38*D38 -> 2175000
B39: ANTENA SIRIP HYBRID PUTIH | C39: IRWAN | D39: 7 | E39: SET | F39: 0 | G39: =F39*D39 -> 0
B40: ANTENA SIRIP HYBRID MERAH | C40: IRWAN | D40: 3 | E40: SET | F40: 45000 | G40: =F40*D40 -> 135000
B41: ANTENA SIRIP HYBRID KUNING | C41: IRWAN | D41: 3 | E41: SET | F41: 45000 | G41: =F41*D41 -> 135000
A42: 44477 | B42: ANTENA SIRIP HYBRID HITAM | C42: IRWAN | D42: 3 | E42: SET | F42: 45000 | G42: =F42*D42 -> 135000 | H42: =SUM(G42:G55) -> 19690000 | I42: JUNI
B43: SILT PLATE SAMPING XPANDER CROSS TANPA LAMPU | C43: IRWAN | D43: 4 | E43: SET | F43: 250000 | G43: =F43*D43 -> 1000000 | J43: =SUM(G42:G47) -> 11185000
B44: SILT PLATE SAMPING XPANDER TANPA LAMPU | C44: IRWAN | D44: 5 | E44: SET | F44: 250000 | G44: =F44*D44 -> 1250000
B45: SILT PLATE SAMPING XPANDER + LAMPU | C45: IRWAN | D45: 5 | E45: SET | F45: 300000 | G45: =F45*D45 -> 1500000
B46: SILT PLATE BELAKANG RAIZE | C46: IRWAN | D46: 5 | E46: PCS | F46: 200000 | G46: =F46*D46 -> 1000000
B47: TOA POLISI 200 WATT + 6 TOMBOL | C47: IRWAN | D47: 6 | E47: SET | F47: 1050000 | G47: =F47*D47 -> 6300000 | J47: =SUM(G48:G55) -> 8505000
B48: TOA POLISI WELLES 200 WATT | C48: IRWAN | D48: 2 | E48: SET | F48: 1050000 | G48: =F48*D48 -> 2100000
B49: CONSUL BOX ALL NEW BRIO | C49: IRWAN | D49: 5 | E49: SET | F49: 500000 | G49: =F49*D49 -> 2500000
B50: zxs | C50: IRWAN | D50: 10 | E50: SET | F50: 37500 | G50: =F50*D50 -> 375000
B51: CONSUL BOX CALYA | C51: IRWAN | D51: 2 | E51: SET | F51: 125000 | G51: =F51*D51 -> 250000
B52: SILT PLATE BELAKANG FORTUNER 2021 | C52: IRWAN | D52: 5 | E52: PCS | F52: 320000 | G52: =F52*D52 -> 1600000
B53: SPOLER CALYA HITAM | C53: IRWAN | D53: 2 | E53: SET | F53: 300000 | G53: =F53*D53 -> 600000
B54: SPOLER CALYA PUTIH | C54: IRWAN | D54: 2 | E54: SET | F54: 300000 | G54: =F54*D54 -> 600000
B55: EMBLEM CUP MESIN TERIOS CHROME | C55: IRWAN | D55: 4 | E55: SET | F55: 120000 | G55: =F55*D55 -> 480000
A56: 44480 | B56: KD BRIO HITAM TIPIS | C56: HERMAN | D56: 60 | E56: SET | F56: 150000 | G56: =F56*D56 -> 9000000 | H56: =SUM(G56) -> 9000000 | I56: MARET (PERTENGAHAN)
A57: 44480 | B57: SPOILER BRIO RED | C57: GREAT(KO AKHON) | D57: 5 | E57: SET | F57: 425000 | G57: =F57*D57 -> 2125000 | H57: =SUM(G57:G60) -> 8500000 | I57: MARET (PERTENGAHAN)
B58: SPOILER BRIO LUNAR SILVER | C58: GREAT(KO AKHON) | D58: 5 | E58: SET | F58: 425000 | G58: =F58*D58 -> 2125000
B59: SPOILER BRIO BLACK | C59: GREAT(KO AKHON) | D59: 5 | E59: SET | F59: 425000 | G59: =F59*D59 -> 2125000
B60: SPOILER BRIO WHITE | C60: GREAT(KO AKHON) | D60: 5 | E60: SET | F60: 425000 | G60: =F60*D60 -> 2125000
A61: 44481 | B61: CAR MAT 7D AN.FORTUNER'16 A/T SOLITAIRELINER BLACK (3 ROW) KARPET 3D | C61: OTOPROJECT | D61: 1 | E61: SET | F61: 1759200 | G61: =F61*D61 -> 1759200 | H61: =SUM(G61:G62) -> 3518400 | I61: DESEMBER
B62: CAR MAT 7D AN.PAJERO'16 A/T SOLITAIRELINER BLACK (3 ROW) KARPET 3D | C62: OTOPROJECT | D62: 1 | E62: SET | F62: 1759200 | G62: =F62*D62 -> 1759200
A63: 44483 | B63: KDP MS XPANDER BLACK | C63: TJM | D63: 10 | E63: SET | F63: 185000 | G63: =F63*D63 -> 1850000 | H63: =SUM(G63:G68) -> 11190000 | I63: DESEMBER
B64: KDP MS TRITON 2016 D/C BLACK | C64: TJM | D64: 10 | E64: SET | F64: 185000 | G64: =F64*D64 -> 1850000
B65: KDP HD HRV BLACK | C65: TJM | D65: 10 | E65: SET | F65: 180000 | G65: =F65*D65 -> 1800000
B66: KDP MS PAJERO 20-ON BLACK | C66: TJM | D66: 10 | E66: SET | F66: 185000 | G66: =F66*D66 -> 1850000
B67: KDP TY INNOVA 2016-ON BLACK | C67: TJM | D67: 12 | E67: SET | F67: 185000 | G67: =F67*D67 -> 2220000
B68: KDP HD BRIO 2018-ON BLACK | C68: TJM | D68: 9 | E68: SET | F68: 180000 | G68: =F68*D68 -> 1620000
A69: 44487 | B69: KDP CALYA BLACK | C69: TJM | D69: 10 | E69: SET | F69: 180000 | G69: =F69*D69 -> 1800000 | H69: =SUM(G69:G71) -> 5400000 | I69: FEBRUARI
B70: KDP CITY HB BLACK | C70: TJM | D70: 10 | E70: SET | F70: 180000 | G70: =F70*D70 -> 1800000
B71: KDP BRIO '18 BLACK | C71: TJM | D71: 10 | E71: SET | F71: 180000 | G71: =F71*D71 -> 1800000
A72: 44487 | B72: KD CITY HITAM TIPIS | C72: HERMAN | D72: 20 | E72: SET | F72: 150000 | G72: =F72*D72 -> 3000000 | H72: =SUM(G72:G73) -> 6000000 | I72: MARET
B73: KD HRV HITAM TIPIS | C73: HERMAN | D73: 20 | E73: SET | F73: 150000 | G73: =F73*D73 -> 3000000
A74: 44487 | B74: SARUNG JOK SIGRA MB TECK (9001+ 9004) | C74: BUK IDA | D74: 1 | E74: SET | F74: 0 | G74: =F74*D74 -> 0 | H74: 0
A75: 44487 | B75: CAMERA ENIGMA JS-606(SERVICE) | C75: NVM | D75: 3 | E75: SET | F75: 0 | G75: =F75*D75 -> 0 | H75: 0 | I75: SERVICE
A76: 44490 | B76: WINTERBLAST HCD 03G C70 (2101120124K2A3) | C76: WINCOS | D76: 1 | E76: ROLL | F76: 0 | G76: =F76*D76 -> 0 | H76: 0 | I76: BRIO
A77: 44491 | B77: KDP BRIO '18 BLACK | C77: TJM | D77: 20 | E77: SET | F77: 180000 | G77: =F77*D77 -> 3600000 | H77: =SUM(G77) -> 3600000 | I77: JANUARI
A78: 44494 | B78: SARUNG JOK MB TECK HRV 2021 (8801 + 8805) | C78: BUK IDA | D78: 1 | E78: SET | F78: 0 | G78: =F78*D78 -> 0 | H78: 0
B79: SARUNG JOK MB TECK TERIOS (9013) | C79: BUK IDA | D79: 1 | E79: SET | F79: 0 | G79: =F79*D79 -> 0 | H79: 0
A80: 44494 | B80: KDP BRIO '18 BLACK | C80: TJM | D80: 11 | E80: SET | F80: 180000 | G80: =F80*D80 -> 1980000 | H80: =SUM(G80:G83) -> 4830000 | I80: FEBRUARI
B81: KDP CALYA BLACK | C81: TJM | D81: 5 | E81: SET | F81: 180000 | G81: =F81*D81 -> 900000
B82: KDP GRAND MAX BLACK | C82: TJM | D82: 5 | E82: SET | F82: 195000 | G82: =F82*D82 -> 975000
B83: KDP LUXIO BLACK | C83: TJM | D83: 5 | E83: SET | F83: 195000 | G83: =F83*D83 -> 975000
A84: 44494 | B84: TOWING ARB CALYA | C84: IRWAN | D84: 5 | E84: SET | F84: 420000 | G84: =F84*D84 -> 2100000 | H84: =SUM(G84:G98) -> 18275000 | I84: JUNI
B85: TOWING ARB RUSH'18/AVANZA | C85: IRWAN | D85: 5 | E85: SET | F85: 420000 | G85: =F85*D85 -> 2100000
B86: TALANG AIR FLAT HRV | C86: IRWAN | D86: 10 | E86: SET | F86: 120000 | G86: =F86*D86 -> 1200000
B87: TALANG AIR FLAT XPANDER | C87: IRWAN | D87: 8 | E87: SET | F87: 120000 | G87: =F87*D87 -> 960000
B88: TALANG AIR FLAT BRIO | C88: IRWAN | D88: 7 | E88: SET | F88: 120000 | G88: =F88*D88 -> 840000
B89: BANTALAN 3 IN 1 | C89: IRWAN | D89: 20 | E89: SET | F89: 47500 | G89: =F89*D89 -> 950000
B90: ANTENA SIRIP HIU HITAM | C90: IRWAN | D90: 5 | E90: SET | F90: 45000 | G90: =F90*D90 -> 225000
B91: SILL PLATE SAMPING BRIO TANPA LAMPU | C91: IRWAN | D91: 15 | E91: SET | F91: 250000 | G91: =F91*D91 -> 3750000
B92: SILL PLATE SAMPING XPANDER TANPA LAMPU | C92: IRWAN | D92: 1 | E92: SET | F92: 250000 | G92: =F92*D92 -> 250000
B93: LOGO HONDA HITAM D/B BRIO | C93: IRWAN | D93: 10 | E93: SET | F93: 245000 | G93: =F93*D93 -> 2450000
B94: GARNIS LAMPU DEPAN RUSH CHROME | C94: IRWAN | D94: 10 | E94: SET | F94: 135000 | G94: =F94*D94 -> 1350000
B95: SPOILER CALYA GREY | C95: IRWAN | D95: 2 | E95: SET | F95: 300000 | G95: =F95*D95 -> 600000
B96: SPOILER CALYA MERAH | C96: IRWAN | D96: 2 | E96: SET | F96: 300000 | G96: =F96*D96 -> 600000
... B98: BRAKET TOWING MCC | C98: IRWAN | D98: 1 | E98: SET | F98: 0 | G98: =F98*D98 -> 0
A99: 44494 | B99: NONE BOX OEM BIN ESL PORT HRV15 BLACK | C99: CELO AUDIO | D99: 1 | E99: SET | F99: 760000 | G99: =F99*D99 -> 760000 | H99: =SUM(G99:G102) -> 1950000 | I99: APRIL
B100: CELLO SUB3 WBE SV40HM | C100: CELO AUDIO | D100: 1 | E100: PCS | F100: 525000 | G100: =F100*D100 -> 525000
B101: NONE PARTS METAL GRILL SUBWOOFER W8E HEXAGONAL BLACK | C101: CELO AUDIO | D101: 1 | E101: PCS | F101: 0 | G101: =F101*D101 -> 0
...

Sheet NOVEMBER
A1: BARANG MASUK ARAW FILM | K1: BON JATUH TEMPO MARET 2022 ( JT)
A2: TGL MASUK | B2: NAMA BARANG | C2: SUPLIER | D2: QTY | E2: SAT | F2: HARGA/PCS/SET | G2: JUMLAH | H2: TOTAL FAKTUR | I2: KET | K2: NO | L2: TGL BARANG MASUK | M2: NAMA SALES/ SUPLIER | N2: JUMLAH BON | O2: KET
A3: 44501 | B3: BODY COVER ALL PAJERO (H/M) | C3: HERMAN | D3: 3 | E3: PCS | F3: 285000 | G3: =F3*D3 -> 855000 | H3: =SUM(G3:G7) -> 3700000 | I3: APRIL | K3: 1 | L3: 44459 | M3: JKI | N3: 2200000 | O3: GIRO TGL 26/3/22
B4: BODY COVER ALL NEW FORTUNER '18 (H/M) | C4: HERMAN | D4: 3 | E4: PCS | F4: 285000 | G4: =F4*D4 -> 855000 | K4: 2 | L4: 44441 | M4: IRWAN | N4: 3600000 | O4: GIRO TGL 25/3/22
B5: BODY COVER ALL NEW RUSH STD | C5: HERMAN | D5: 5 | E5: PCS | F5: 138000 | G5: =F5*D5 -> 690000 | K5: 3 | L5: 44415 | M5: IRWAN | N5: 960000
B6: BODY COVER CALYA STD | C6: HERMAN | D6: 5 | E6: PCS | F6: 130000 | G6: =F6*D6 -> 650000 | K6: 4 | L6: 44427 | M6: IRWAN | N6: 1400000 | Q6: =N4+N5+N6+N8+N9+N12 -> 39487200
B7: BODY COVER GRAND AVANZA STD | C7: HERMAN | D7: 5 | E7: PCS | F7: 130000 | G7: =F7*D7 -> 650000 | K7: 5 | L7: 44462 | M7: JKI | N7: 5368000 | O7: GIRO TGL 26/3/22
A8: 44501 | B8: BODY COVER BRIO NEW (H/M) | C8: HERMAN | D8: 3 | E8: PCS | F8: 250000 | G8: =F8*D8 -> 750000 | H8: =SUM(G8:G12) -> 3900000 | I8: APRIL | K8: 6 | L8: 44459 | M8: IRWAN | N8: 14365000 | O8: GIRO TGL 29/3/22
B9: BODY COVER ALL NEW RUSH (H/M) | C9: HERMAN | D9: 3 | E9: PCS | F9: 265000 | G9: =F9*D9 -> 795000 | K9: 7 | L9: 44464 | M9: IRWAN | N9: 6672200
B10: BODY COVER RAIZE (H/M) | C10: HERMAN | D10: 3 | E10: PCS | F10: 250000 | G10: =F10*D10 -> 750000 | K10: 8 | L10: 44466 | M10: MOBILINDO | N10: 9790000 | O10: giro tgl 15/3/22
B11: BODY COVER CITY '21 (H/M) | C11: HERMAN | D11: 3 | E11: PCS | F11: 270000 | G11: =F11*D11 -> 810000 | K11: 9 | L11: 44474 | M11: OTOPROJECT | N11: 15000000
B12: BODY COVER HRV (H/M) | C12: HERMAN | D12: 3 | E12: PCS | F12: 265000 | G12: =F12*D12 -> 795000 | K12: 10 | L12: 44476 | M12: IRWAN | N12: 12490000 | O12: GIRO TGL 29/3/22 | Q12: =N3+N4+N5+N7+N8+N9+N10+N12+N13+N14+N17 -> 69650200
A13: 44502 | B13: TALANG AIR SLIM CITY HB | C13: IRWAN | D13: 11 | E13: SET | F13: 120000 | G13: =F13*D13 -> 1320000 | H13: =SUM(G13) -> 1320000 | I13: JULI | K13: 11 | L13: 44477 | M13: ORCA | N13: 1500000 | O13: GIRO TGL30/3/21
A14: 44503 | B14: TUTUP BAN SERAP INJECTION PAJERO'16 | C14: IRWAN | D14: 5 | E14: SET | F14: 500000 | G14: =F14*D14 -> 2500000 | H14: =SUM(G14:G20) -> 10275000 | I14: JULI | K14: 12 | L14: 44477 | M14: ORCA | N14: 2205000
B15: TUTUP BAN SERAP INJECTION FORTUNER'16 | C15: IRWAN | D15: 5 | E15: SET | F15: TDK DI PESAN | G15: 0 | K15: 13 | L15: 44480 | M15: HERMAN | N15: 9000000 | O15: GIRO TGL 30/3/22
B16: TUTUP BAN SERAP INJECTION INNOVA REBRON | C16: IRWAN | D16: 5 | E16: SET | F16: 450000 | G16: =F16*D16 -> 2250000 | K16: 14 | L16: 44487 | M16: HERMAN | N16: 6400000 | O16: GIRO TGL 30/3/22
B17: OUTHER PAJERO '16 CHROME | C17: IRWAN | D17: 5 | E17: SET | F17: 95000 | G17: =F17*D17 -> 475000 | K17: 15 | L17: 44861 | M17: JOVANINDO | N17: 10500000 | O17: GIRO TGL 30/3/22
B18: OUTHER PAJERO '16 HITAM | C18: IRWAN | D18: 10 | E18: SET | F18: 95000 | G18: =F18*D18 -> 950000 | K18: 16 | L18: 44505 | M18: TJM | N18: 4155000 | O18: TRANSRFER TGL 25/3/22
B19: TRUNKLID PAJERO HITAM | C19: IRWAN | D19: 2 | E19: SET | F19: 1000000 | G19: =F19*D19 -> 2000000 | K19: 17 | L19: 44509 | M19: GREAT/KO AKHON | N19: 18000000 | O19: TRANSRFER TGL 26/3/22
B20: SILL PLATE SAMPING HRV +LAMPU | C20: IRWAN | D20: 7 | E20: SET | F20: 300000 | G20: =F20*D20 -> 2100000 | K20: 18
A21: 44505 | B21: KDP CITY HB,BLACK | C21: TJM | D21: 20 | E21: SET | F21: 180000 | G21: =F21*D21 -> 3600000 | H21: =SUM(G21:G22) -> 4155000 | I21: MARET
B22: KDP INNOVA'16, BLACK | C22: TJM | D22: 3 | E22: SET | F22: 185000 | G22: =F22*D22 -> 555000
A23: 44508 | B23: TALANG AIR L300 | C23: IRWAN | D23: 12 | E23: SET | F23: 62500 | G23: =F23*D23 -> 750000 | H23: =SUM(G23:G24) -> 8250000 | I23: MEI
B24: FOOT STEP THANOS ALL NEW RUSH '18 | C24: IRWAN | D24: 5 | E24: SET | F24: 1500000 | G24: =F24*D24 -> 7500000 | N24: =SUM(N3:N23) -> 123605200
A25: 44508 | B25: SARUNG JOK TERIOS 2021 MB (90001+9014) | C25: BUK IDA | D25: 1 | E25: SET | F25: 0 | G25: =F25*D25 -> 0 | H25: 0
B26: SARUNG JOK GRAND INNOVA MB (90001+9016) | C26: BUK IDA | D26: 1 | E26: SET | F26: 0 | G26: =F26*D26 -> 0
A27: 44508 | B27: SARUNG JOK AVANZA AB (HITAM+CAPUCINO) FRR | C27: HERMAN | D27: 2 | E27: SET | F27: 735000 | G27: =F27*D27 -> 1470000 | H27: =SUM(G27) -> 1470000 | I27: APRIL (PERTENGAHAN)
A28: 44509 | B28: TOWING MCC PAJERO | C28: GREAT | D28: 15 | E28: SET | F28: 1200000 | G28: =F28*D28 -> 18000000 | H28: =SUM(G28) -> 18000000 | I28: MARET
A29: 44510 | B29: CITY HATCHBACK DOOR HANDLE COVER (8 PCS) BLACK | C29: HENDRIK | D29: 3 | E29: SET | F29: 110000 | G29: =F29*D29 -> 330000 | H29: =SUM(G29:G37) -> 3000000 | I29: LUNAS CASH 9/11
B30: CITY HATCHBACK OUTER HANDLE COVER (4 PCS) BLACK | C30: HENDRIK | D30: 3 | E30: SET | F30: 125000 | G30: =F30*D30 -> 375000
B31: CITY HATCHBACK TANK COVER (1 PCS) BLACK | C31: HENDRIK | D31: 3 | E31: SET | F31: 40000 | G31: =F31*D31 -> 120000
B32: CITY HATCHBACK DOOR HANDLE COVER (8 PCS) CHROME | C32: HENDRIK | D32: 2 | E32: SET | F32: 110000 | G32: =F32*D32 -> 220000
B33: CITY HATCHBACK OUTER HANDLE COVER (8 PCS) CHROME | C33: HENDRIK | D33: 2 | E33: SET | F33: 125000 | G33: =F33*D33 -> 250000
B34: CITY HATCHBACK TANK COVER (1 PCS) CHROME | C34: HENDRIK | D34: 2 | E34: SET | F34: 40000 | G34: =F34*D34 -> 80000
B35: RAIZE / ROCKY HEAD LIGHT COVER (2 PCS) BLACK | C35: HENDRIK | D35: 5 | E35: SET | F35: 135000 | G35: =F35*D35 -> 675000
B36: RAIZE / ROCKY TAIL LIGHT COVER (2 PCS) BLACK | C36: HENDRIK | D36: 5 | E36: SET | F36: 150000 | G36: =F36*D36 -> 750000
B37: RAIZE TANK COVER (1 PCS) BLACK | C37: HENDRIK | D37: 5 | E37: SET | F37: 40000 | G37: =F37*D37 -> 200000
A38: 44511 | B38: EMBLEM RS ORI | C38: HERMAN | D38: 50 | E38: SET | F38: 30000 | G38: =F38*D38 -> 1500000 | H38: =SUM(G38) -> 1500000 | I38: APRIL
A39: 44512 | B39: LAMPU POLISI LED MERAH | C39: IRWAN | D39: 2 | E39: SET | F39: 3000000 | G39: =F39*D39 -> 6000000 | H39: =SUM(G39:G42) -> 7725000 | I39: JULI
B40: PLAT NO 46CM MIKA TANPA LAMPU | C40: IRWAN | D40: 30 | E40: SET | F40: 0 | G40: =F40*D40 -> 0
B41: PLAT NO 46CM MIKA + LAMPU | C41: IRWAN | D41: 17 | E41: SET | F41: 75000 | G41: =F41*D41 -> 1275000
B42: PLAT NO 46CM ASTRA/BIASA | C42: IRWAN | D42: 30 | E42: SET | F42: 15000 | G42: =F42*D42 -> 450000
A43: 44512 | B43: SARUNG JOK BRIO SATYA'18 LEXUS HITAM KUNING | C43: HERMAN | D43: 2 | E43: SET | F43: 640000 | G43: =F43*D43 -> 1280000 | H43: =SUM(G43:G51) -> 12815000 | I43: MEI
B44: SARUNG JOK AVANZA'16 LEXUS HITAM ABU | C44: HERMAN | D44: 2 | E44: SET | F44: 740000 | G44: =F44*D44 -> 1480000
B45: SARUNG JOK RUSH'18 LEXUS HITAM ABU | C45: HERMAN | D45: 2 | E45: SET | F45: 740000 | G45: =F45*D45 -> 1480000
B46: SARUNG JOK BRIO SATYA'18 LEXUS HITAM ABU | C46: HERMAN | D46: 2 | E46: SET | F46: 640000 | G46: =F46*D46 -> 1280000
B47: SARUNG JOK INNOVA V'21 LEXUS HITAM COFFE | C47: HERMAN | D47: 1 | E47: SET | F47: 740000 | G47: =F47*D47 -> 740000
B48: SARUNG JOK HILUX'12 G LEXUS HITAM HITAM | C48: HERMAN | D48: 1 | E48: SET | F48: 635000 | G48: =F48*D48 -> 635000
B49: SARUNG JOK AVANZA'16 LEXUS HITAM CAPPUCINO | C49: HERMAN | D49: 2 | E49: SET | F49: 740000 | G49: =F49*D49 -> 1480000
B50: SARUNG JOK INNOVA G '21 LEXUS HITAM CAPPUCINO | C50: HERMAN | D50: 4 | E50: SET | F50: 740000 | G50: =F50*D50 -> 2960000
B51: SARUNG JOK RUSH '18 LEXUS HITAM CAPPUCINO | C51: HERMAN | D51: 2 | E51: SET | F51: 740000 | G51: =F51*D51 -> 1480000
A52: 44512 | B52: KERANDA | C52: JAYA MADANI | D52: 2 | E52: SET | F52: 3500000 | G52: =F52*D52 -> 7000000 | H52: =SUM(G52:G53) -> 7200000 | I52: NOVEMBER (AKHIR)
B53: PACKING BARANG | C53: JAYA MADANI | D53: 1 | E53: SET | F53: 200000 | G53: =F53*D53 -> 200000
A54: 44513 | B54: SARUNG JOK INNOVA G MB (9001+9010) | C54: BUK IDA | D54: 1 | E54: SET | F54: 0 | G54: =F54*D54 -> 0 | H54: 0
A55: 44515 | B55: SARUNG JOK TERIOS '21 HITAM ABU FR | C55: HERMAN | D55: 1 | E55: SET | F55: 735000 | G55: =F55*D55 -> 735000 | H55: =SUM(G55:G56) -> 2005000 | I55: APRIL | J55: =SUM(H55:H59) -> 5480000
B56: SARUNG JOK BRIO SATYA'18 HITAM FR | C56: HERMAN | D56: 2 | E56: SET | F56: 635000 | G56: =F56*D56 -> 1270000
B57: SARUNG JOK BRIO SATYA'18 HITAM BD MERAH FR | C57: HERMAN | D57: 2 | E57: SET | F57: 635000 | G57: =F57*D57 -> 1270000 | H57: =SUM(G57:G59) -> 3475000
B58: SARUNG JOK RUSH'18 HITAM MOCCA BD MERAH FR | C58: HERMAN | D58: 1 | E58: SET | F58: 735000 | G58: =F58*D58 -> 735000
B59: SARUNG JOK BRIO SATYA'18 HITAM FR | C59: HERMAN | D59: 2 | E59: SET | F59: 735000 | G59: =F59*D59 -> 1470000
A60: 44515 | B60: KACA FILM SRC 40 - BLACK (ANTI GORES 40% SLR) | C60: JKI | D60: 1 | E60: SET | F60: 1100000 | G60: =F60*D60 -> 1100000 | H60: =SUM(G60:G61) -> 2200000 | I60: MEI
B61: KACA FILM SRC 60 - BLACK (ANTI GORES 60% SLR) | C61: JKI | D61: 1 | E61: SET | F61: 1100000 | G61: =F61*D61 -> 1100000
A62: 44515 | B62: SARUNG JOK/TERIOS'19 VARIASI HITAM CREAM | C62: V-CENT | D62: 1 | E62: SET | F62: 750000 | G62: =F62*D62 -> 750000 | H62: =SUM(G62:G68) -> 3200000 | I62: DESEMBER
B63: SARUNG JOK/TERIOS'19 VARIASI HITAM MERAH | C63: V-CENT | D63: 1 | E63: SET | F63: 750000 | G63: =F63*D63 -> 750000
B64: SARUNG JOK INNOVA REBRON G VARIASI HITAM TERACOTTA | C64: V-CENT | D64: 1 | E64: SET | F64: 750000 | G64: =F64*D64 -> 750000
B65: SARUNG JOK INNOVA REBRON V VARIASI HITAM TERACOTTA | C65: V-CENT | D65: 1 | E65: SET | F65: 750000 | G65: =F65*D65 -> 750000
B66: BANTALAN JOK MOBIL HITAM MERAH | C66: V-CENT | D66: 1 | E66: SET | F66: 50000 | G66: =F66*D66 -> 50000
B67: BANTALAN JOK MOBIL HITAM CAPPUCINO | C67: V-CENT | D67: 1 | E67: SET | F67: 50000 | G67: =F67*D67 -> 50000
B68: BANTALAN JOK MOBIL HITAM TERACOTTA | C68: V-CENT | D68: 2 | E68: SET | F68: 50000 | G68: =F68*D68 -> 100000
A69: 44516 | B69: SARUNG JOK RUSH'18 HITAM BD MERAH FR | C69: HERMAN | D69: 1 | E69: SET | F69: 735000 | G69: =F69*D69 -> 735000 | H69: =SUM(G69:G74) -> 5045000 | I69: MEI | J69: =SUM(H69:H76) -> 7250000
B70: SARUNG JOK TERIOS'18 HITAM BD ABU FR | C70: HERMAN | D70: 1 | E70: SET | F70: 735000 | G70: =F70*D70 -> 735000
B71: SARUNG JOK TERIOS'18 HITAM BD FR | C71: HERMAN | D71: 1 | E71: SET | F71: 735000 | G71: =F71*D71 -> 735000
B72: SARUNG JOK TERIOS'18 HITAM BD MOCCA FR | C72: HERMAN | D72: 1 | E72: SET | F72: 735000 | G72: =F72*D72 -> 735000
B73: SARUNG JOK RUSH'18 HITAM BD FR | C73: HERMAN | D73: 2 | E73: SET | F73: 735000 | G73: =F73*D73 -> 1470000
B74: SARUNG JOK BRIO SATYA'18 HITAM BD FR | C74: HERMAN | D74: 1 | E74: SET | F74: 635000 | G74: =F74*D74 -> 635000
B75: SARUNG JOK INNOVA G'18 HITAM BD FR | C75: HERMAN | D75: 1 | E75: SET | F75: 735000 | G75: =F75*D75 -> 735000 | H75: =SUM(G75:G76) -> 2205000
B76: SARUNG JOK RUSH'18 HITAM BD ABU FR | C76: HERMAN | D76: 2 | E76: SET | F76: 735000 | G76: =F76*D76 -> 1470000
A77: 44517 | B77: CITY HB HEAD LIGHT COVER (2PCS) BLACK | C77: HENDRIK | D77: 3 | E77: SET | F77: 140000 | G77: =F77*D77 -> 420000 | H77: =SUM(G77:G81) -> 2100000 | I77: LUNAS CASH 9/11
B78: CITY HB TAIL LIGHT COVER (4 PCS) BLACK | C78: HENDRIK | D78: 3 | E78: SET | F78: 160000 | G78: =F78*D78 -> 480000
B79: CITY HB HEAD LIGHT COVER (2PCS) CHROME | C79: HENDRIK | D79: 2 | E79: SET | F79: 140000 | G79: =F79*D79 -> 280000
B80: CITY HB TAIL LIGHT COVER (4 PCS) CHROME | C80: HENDRIK | D80: 2 | E80: SET | F80: 160000 | G80: =F80*D80 -> 320000
B81: CITY HB DOOR SILT PLATE (4PCS) WITH LED | C81: HENDRIK | D81: 2 | E81: SET | F81: 300000 | G81: =F81*D81 -> 600000
A82: 44519 | B82: SARUNG JOK RUSH '18 FERARI HITAM + BD | C82: HERMAN | D82: 2 | E82: SET | F82: 735000 | G82: =F82*D82 -> 1470000 | H82: =SUM(G82:G87) -> 6515000 | I82: MEI
B83: SARUNG JOK AVANZA VVTI FERARI CAPUCHINO +BD | C83: HERMAN | D83: 2 | E83: SET | F83: 735000 | G83: =F83*D83 -> 1470000
B84: SARUNG JOK INNOVA G FERARI HITAM + COKLAT | C84: HERMAN | D84: 2 | E84: SET | F84: 735000 | G84: =F84*D84 -> 1470000
B85: SARUNG JOK BRIO SATYA '18 FERARI HITAM+ BD | C85: HERMAN | D85: 1 | E85: SET | F85: 635000 | G85: =F85*D85 -> 635000
B86: SARUNG JOK TERIOS '18 FERARI HITAM + MOCCA | C86: HERMAN | D86: 1 | E86: SET | F86: 735000 | G86: =F86*D86 -> 735000
B87: SARUNG JOK TERIOS '18 FERARI HITAM + BD | C87: HERMAN | D87: 1 | E87: SET | F87: 735000 | G87: =F87*D87 -> 735000
A88: 44519 | B88: PHILIP H4 (12V 60/55) | C88: PELITA HARAPAN | D88: 10 | E88: PCS | G88: =F88*D88 -> 0 | H88: =SUM(G88:G95) -> 345000 | I88: DI ANGSUR
B89: PHILIP P (P21/5W 23V/21) | C89: PELITA HARAPAN | D89: 10 | E89: PCS | F89: 6000 | G89: =F89*D89 -> 60000
B90: PHILIP (W21/5W 12V/21)TUSUK | C90: PELITA HARAPAN | D90: 10 | E90: PCS | F90: RETUR | G90: 0
B91: PHILIP (P21W/12V/21) | C91: PELITA HARAPAN | D91: 20 | E91: PCS | F91: 5625 | G91: =F91*D91 -> 112500
B92: PHILIP (W21W/12V/21W) TUSUK | C92: PELITA HARAPAN | D92: 10 | E92: PCS | F92: RETUR | G92: 0
B93: PHILIP (LU5W/12V 5W) JAGUNG | C93: PELITA HARAPAN | D93: 20 | E93: PCS | F93: 8625 | G93: =F93*D93 -> 172500
B94: LAMPU REM (12V/21.5W (K1) | C94: PELITA HARAPAN | D94: 50 | E94: PCS | F94: RETUR | G94: 0
B95: LAMPU REM (12V/20.5W (K2) | C95: PELITA HARAPAN | D95: 50 | E95: PCS | F95: RETUR | G95: 0
A96: 44522 | B96: TANDUK DEPAN MINI RUSH'18 | C96: IRWAN | D96: 4 | E96: SET | F96: 650000 | G96: =F96*D96 -> 2600000 | H96: =SUM(G96:G97) -> 4850000 | I96: JULI
B97: PLAT NO 46 CM MICA+LAMPU | C97: IRWAN | D97: 30 | E97: SET | F97: 75000 | G97: =F97*D97 -> 2250000
A98: 44522 | B98: SARUNG JOK BRIO SATYA'18 HITAM CAPUCINO FR | C98: HERMAN | D98: 1 | E98: SET | F98: 635000 | G98: =F98*D98 -> 635000 | H98: =SUM(G98:G100) -> 3375000 | I98: MEI
B99: SARUNG JOK BRIO SATYA'18 HITAM ABU FR | C99: HERMAN | D99: 2 | E99: SET | F99: 635000 | G99: =F99*D99 -> 1270000
B100: SARUNG JOK RUSH'18 HITAM MOCCA FR | C100: HERMAN | D100: 2 | E100: SET | F100: 735000 | G100: =F100*D100 -> 1470000
...

Sheet DESEMBER
A1: BARANG MASUK ARAW FILM | K1: BON JATUH TEMPO APRIL 2022 ( JT)
A2: TGL MASUK | B2: NAMA BARANG | C2: SUPLIER | D2: QTY | E2: SAT | F2: HARGA/PCS/SET | G2: JUMLAH | H2: TOTAL FAKTUR | I2: KET | K2: NO | L2: TGL BARANG MASUK | M2: NAMA SALES/ SUPLIER | N2: JUMLAH BON | O2: KET
A3: 44532 | B3: BODY COVER ALL NEW BRIO | C3: HERMAN | D3: 13 | E3: SET | F3: 130000 | G3: =F3*D3 -> 1690000 | H3: =SUM(G3:G6) -> 4707000 | I3: JUNI | J3: =SUM(H3:H10) -> 8921000 | K3: 1 | L3: 44459 | M3: MR.BOSS | N3: 1521500 | O3: GIRO TGL 28/4/22
B4: BODY COVER INNOVA REBORN | C4: HERMAN | D4: 6 | E4: SET | F4: 151500 | G4: =F4*D4 -> 909000 | K4: 2 | L4: 44424 | M4: IRWAN | N4: 10000000 | O4: GIRO TGL 25/04/22
B5: BODY COVER ALL NEW PAJERO | C5: HERMAN | D5: 9 | E5: SET | F5: 162000 | G5: =F5*D5 -> 1458000 | K5: 3 | L5: 44389 | M5: IRWAN | N5: 910000
B6: BODY COVER RAIZE | C6: HERMAN | D6: 5 | E6: SET | F6: 130000 | G6: =F6*D6 -> 650000 | K6: 4 | L6: 44476 | M6: IRWAN | N6: 10400000 | O6: GIRO TGL 29/4/22
B7: BODY COVER CITY HB | C7: HERMAN | D7: 8 | E7: SET | F7: 130000 | G7: =F7*D7 -> 1040000 | H7: =SUM(G7:G10) -> 4214000 | K7: 5 | L7: 44477 | M7: IRWAN | N7: 9545000
B8: BODY COVER HRV | C8: HERMAN | D8: 5 | E8: SET | F8: 138000 | G8: =F8*D8 -> 690000 | K8: 6 | L8: 44494 | M8: CELLO AUDIO | N8: 1950000 | O8: GIRO TGL 10/4/22
B9: BODY COVER ALL NEW RUSH | C9: HERMAN | D9: 16 | E9: SET | F9: 138000 | G9: =F9*D9 -> 2208000 | K9: 7 | L9: 44495 | M9: HERMAN | N9: 16467500 | O9: GIRO TGL 30/4/22
B10: BODY COVER ALL NEW LIVINA | C10: HERMAN | D10: 2 | E10: SET | F10: 138000 | G10: =F10*D10 -> 276000 | K10: 8 | L10: 44501 | M10: HERMAN | N10: 7600000 | O10: GIRO TGL 30/4/22
A11: 44532 | B11: SPOILER BRIO MERAH | C11: GREAT | D11: 1 | E11: SET | F11: 0 | G11: =F11*D11 -> 0 | H11: GANTI RETURAN | K11: 9 | L11: 44508 | M11: HERMAN | N11: 1470000 | O11: GIRO TGL 30/4/22
B12: SPOILER BRIO SILVER | C12: GREAT | D12: 1 | E12: SET | F12: 0 | G12: =F12*D12 -> 0 | K12: 10 | L12: 44515 | M12: HERMAN | N12: 5480000 | O12: GIRO TGL 30/4/22
A13: 44532 | B13: KACA FILM 3M CRYSTALLINE (20%) | C13: DHARMESTA | D13: 1 | E13: M | F13: 1100000 | G13: =F13*D13 -> 1100000 | H13: =SUM(G13) -> 1100000 | I13: LUNAS TF 25/11 | K13: 11 | L13: 44502 | M13: IRWAN | N13: 1320000 | O13: GIRO TGL 29/4/22
A14: 44534 | B14: SARUNG JOK BRIO SATYA'18 LEXUS HITAM CAPPUCINO | C14: HERMAN | D14: 4 | E14: SET | F14: 640000 | G14: =F14*D14 -> 2560000 | H14: =SUM(G14:G17) -> 6800000 | I14: JUNI | K14: 12 | L14: 44503 | M14: IRWAN | N14: 10275000
B15: SARUNG JOK RUSH'18 LEXUS CAPPUCINO HITAM | C15: HERMAN | D15: 2 | E15: SET | F15: 740000 | G15: =F15*D15 -> 1480000 | K15: 13 | L15: 44512 | M15: IRWAN | N15: 7725000
B16: SARUNG JOK RUSH'18 LEXUS HITAM MERAH | C16: HERMAN | D16: 2 | E16: SET | F16: 640000 | G16: =F16*D16 -> 1280000 | K16: 14 | L16: 44522 | M16: IRWAN | N16: 4850000
B17: SARUNG JOK AVANZA'16 LEXUS MERAH HITAM | C17: HERMAN | D17: 2 | E17: SET | F17: 740000 | G17: =F17*D17 -> 1480000 | K17: 15 | L17: 44565 | M17: TJM | N17: 7880000 | O17: GIRO TGL 25/4/22
A18: 44534 | B18: KDP GRANMAX BLACK | C18: TJM | D18: 5 | E18: SET | F18: 195000 | G18: =F18*D18 -> 975000 | H18: =SUM(G18) -> 975000 | I18: BARANG PENGGANTI 25/12 | K18: 16 | L18: 44897 | M18: HERMAN | N18: 4707000 | O18: GIRO TGL 30/4/22
A19: 44536 | B19: SARUNG JOK ALL NEW BRIO SATYA'18 HITAM MERAH FR | C19: HERMAN | D19: 2 | E19: SET | F19: 640000 | G19: =F19*D19 -> 1280000 | H19: =SUM(G19:G21) -> 4680000 | I19: JULI | K19: 17 | L19: 44919 | M19: MR BOSS | N19: 900000 | O19: GIRO TGL 30/4/22
B20: SARUNG JOK ALL NEW BRIO SATYA'18 HITAM BEIGE FR | C20: HERMAN | D20: 3 | E20: SET | F20: 640000 | G20: =F20*D20 -> 1920000 | K20: 19 | L20: 44919 | M20: MR BOSS | N20: 1230000 | O20: GIRO TGL 30/4/22
B21: SARUNG JOK AVANZA'16 HITAM MERAH FR | C21: HERMAN | D21: 2 | E21: SET | F21: 740000 | G21: =F21*D21 -> 1480000 | K21: 20 | L21: 44614 | M21: OTOPROJEC | N21: 2067000
A22: 44536 | B22: SARUNG JOK TERIOS'13 MB 9001+9015 | C22: BUK IDA | D22: 1 | E22: SET | F22: 0 | G22: =F22*D22 -> 0 | H22: 0 | N22: =SUM(N3:N21) -> 106298000
A23: 44536 | B23: HANDLE ALL NEW FORTUNER HITAM | C23: IRWAN | D23: 10 | E23: SET | F23: 85000 | G23: =F23*D23 -> 850000 | H23: =SUM(G23:G36) -> 31030000 | I23: AGUSTUS | J23: =SUM(H23:H44) -> 40295000
B24: KABEL RELLAY SET | C24: IRWAN | D24: 10 | E24: SET | F24: 130000 | G24: =F24*D24 -> 1300000
B25: CHARGER HP LOG ON 3 USB | C25: IRWAN | D25: 20 | E25: SET | F25: 100000 | G25: =F25*D25 -> 2000000
B26: GRILL INNOVA REBRON | C26: IRWAN | D26: 10 | E26: SET | F26: 110000 | G26: =F26*D26 -> 1100000
B27: BAMPER BELAKANG ALL NEW TRITON | C27: IRWAN | D27: 3 | E27: SET | F27: 2300000 | G27: =F27*D27 -> 6900000
B28: INJAKAN SAMPINGRUSH+LED | C28: IRWAN | D28: 3 | E28: SET | F28: 1750000 | G28: =F28*D28 -> 5250000
B29: TOWING ARB FORTUNER TRD | C29: IRWAN | D29: 5 | E29: SET | F29: 420000 | G29: =F29*D29 -> 2100000
B30: TOWING ARB FULL PLATE KNOCKDOWN MERAH +LED FORTUNER | C30: IRWAN | D30: 2 | E30: SET | F30: 1800000 | G30: =F30*D30 -> 3600000
B31: GARNISH BELAKANG RUSH CHROME | C31: IRWAN | D31: 10 | E31: SET | F31: 145000 | G31: =F31*D31 -> 1450000
B32: HANDLE RUSH HITAM | C32: IRWAN | D32: 16 | E32: SET | F32: 85000 | G32: =F32*D32 -> 1360000
B33: GARNISH LAMPU DEPAN INNOVA'16 HITAM | C33: IRWAN | D33: 9 | E33: SET | F33: 135000 | G33: =F33*D33 -> 1215000
B34: GARNISH LAMPU BELAKANG INNOVA'16 HITAM | C34: IRWAN | D34: 9 | E34: SET | F34: 145000 | G34: =F34*D34 -> 1305000
B35: TANK COVER INNOVA'16 HITAM | C35: IRWAN | D35: 20 | E35: SET | F35: 45000 | G35: =F35*D35 -> 900000
B36: HANDLE INNOVA'16 HITAM | C36: IRWAN | D36: 20 | E36: SET | F36: 85000 | G36: =F36*D36 -> 1700000
B37: OUTHER INNOVA'16 HITAM | C37: IRWAN | D37: 20 | E37: SET | F37: 95000 | G37: =F37*D37 -> 1900000 | H37: =SUM(G37:G44) -> 9265000 | I37: JULI
B38: ANTENA SIRIP HYBIRD PUTIH (RETUR) | C38: IRWAN | D38: 10 | E38: SET | F38: 0 | G38: =F38*D38 -> 0
B39: TURBO TIMER INNOVA'16 | C39: IRWAN | D39: 5 | E39: SET | F39: 840000 | G39: =F39*D39 -> 4200000
B40: OUTHER RUSH HITAM | C40: IRWAN | D40: 19 | E40: SET | F40: 95000 | G40: =F40*D40 -> 1805000
B41: OUTHER RAIZE HITAM | C41: IRWAN | D41: 5 | E41: SET | F41: 95000 | G41: =F41*D41 -> 475000
B42: TANK COVER RAIZE HITAM | C42: IRWAN | D42: 5 | E42: SET | F42: 45000 | G42: =F42*D42 -> 225000
B43: HANDLE RAIZE HITAM | C43: IRWAN | D43: 3 | E43: SET | F43: 85000 | G43: =F43*D43 -> 255000
B44: TANK COVER RUSH HITAM | C44: IRWAN | D44: 9 | E44: SET | F44: 45000 | G44: =F44*D44 -> 405000
A45: 44537 | B45: EA -168-9990 ADR PRO PLUS / APPLE CAR PLAY 9 INCHI 4 GB + 64GB+CM DVR (TVI ORCA ANDROID 9'') | C45: ORCA | D45: 2 | E45: SET | F45: 4200000 | G45: =F45*D45 -> 8400000 | H45: =SUM(G45) -> 8400000 | I45: MEI
A46: 44537 | B46: VACUM UDARA MOBIL | C46: AUTO2000 | D46: 8 | E46: SET | G46: =F46*D46 -> 0
B47: PENJEPIT PELINDUNG DEPAN | C47: AUTO2000 | D47: 11 | E47: SET | G47: =F47*D47 -> 0
A48: 44538 | B48: KACA FILM WINTERBLAST HCD 10G C 70 (2107150297K2AN) | C48: WINCOS | D48: 1 | E48: ROL | F48: 0 | G48: =F48*D48 -> 0 | H48: 0 | I48: BRIO
B49: KACA FILM WINTERBLAST HCD 30G C 70 (2108150189K2AP) | C49: WINCOS | D49: 1 | E49: ROL | F49: 0 | G49: =F49*D49 -> 0 | H49: 0
A50: 44539 | B50: KACA FILM PREMIUM HCD 20 G(50%) | C50: WINCOS | D50: 1 | E50: ROL | F50: 19800000 | G50: =F50*D50 -> 19800000 | H50: =SUM(G50:G51) -> 29800000 | I50: DESEMBER
B51: KACA FILM PREMIUM HCD 30 G (40%) | C51: WINCOS | D51: 1 | E51: ROL | F51: 10000000 | G51: =F51*D51 -> 10000000
A52: 44540 | B52: FORTUNER '21 BUMPER AVENGER EVO | C52: PEGASUS | D52: 1 | E52: SET | F52: 3200000 | G52: =F52*D52 -> 3200000 | H52: =SUM(G52) -> 3200000 | I52: LUNAS TF 06/12/21
A53: 44540 | B53: KACA FILM CPF1 STANDARD (60%) | C53: JKI | D53: 1 | E53: ROL | F53: 1650000 | G53: =F53*D53 -> 1650000 | H53: =SUM(G53) -> 1650000 | I53: MEI
A54: 44544 | B54: GARNISH LAMPU DEPAN RUSH'18 HITAM | C54: IRWAN | D54: 15 | E54: SET | F54: 135000 | G54: =F54*D54 -> 2025000 | H54: =SUM(G54:G65) -> 8315000 | I54: AGUSTUS
B55: HANDLE HITAM RUSH '18 KEYLESS | C55: IRWAN | D55: 20 | E55: SET | F55: 85000 | G55: =F55*D55 -> 1700000
B56: CASING KUNCI CARBON BRV/BRIO | C56: IRWAN | D56: 3 | E56: SET | F56: 125000 | G56: =F56*D56 -> 375000
B57: CASING KUNCI CARBON PAJERO'16 | C57: IRWAN | D57: 3 | E57: SET | F57: 125000 | G57: =F57*D57 -> 375000 | J57: SELEBIHNYA DI RETUR
B58: CASING KUNCI CARBON XPANDER | C58: IRWAN | D58: 3 | E58: SET | F58: 125000 | G58: =F58*D58 -> 375000
B59: SILICON KUNCI BRIO | C59: IRWAN | D59: 10 | E59: SET | F59: 12000 | G59: =F59*D59 -> 120000
B60: ALARM K-ONE INNOVA REBRON | C60: IRWAN | D60: 5 | E60: SET | F60: 165000 | G60: =F60*D60 -> 825000
B61: TALANG AIR FLAT FORTUNER'16 | C61: IRWAN | D61: 9 | E61: SET | F61: 120000 | G61: =F61*D61 -> 1080000
B62: TALANG AIR FLAT PAJERO'16 | C62: IRWAN | D62: 8 | E62: SET | F62: 120000 | G62: =F62*D62 -> 960000
B63: TALANG AIR FLAT INNOVA REBRON | C63: IRWAN | D63: 4 | E63: SET | F63: 120000 | G63: =F63*D63 -> 480000
B64: TALANG AIR FLAT MOBILIO | C64: IRWAN | D64: 0 | E64: SET | F64: 120000 | G64: =F64*D64 -> 0
B65: TALANG AIR FLAT XPANDER | C65: IRWAN | D65: 0 | E65: SET | F65: 120000 | G65: =F65*D65 -> 0
A66: 44546 | B66: FRAME ORCA FR-268T T. NEW RUSH 9'' TH. 2018 ON | C66: ORCA | D66: 1 | E66: PCS | F66: 325000 | G66: =F66*D66 -> 325000 | H66: =SUM(G66) -> 325000 | I66: MEI
A67: 44551 | B67: SARUNG JOK MB TECK TERIOS'13 (9001+9015) | C67: BUK IDA | D67: 1 | E67: SET | F67: 0 | G67: =F67*D67 -> 0
A68: 44551 | B68: HANDEL COVER CITY HB BLACK | C68: HENDRIK | D68: 8 | E68: SET | F68: 110000 | G68: =F68*D68 -> 880000 | H68: =SUM(G68:G77) -> 5150000 | I68: AKHIR BULAN DESEMBER BLM DISC (5%)
B69: OUTER COVER CITY HB BLACK | C69: HENDRIK | D69: 8 | E69: SET | F69: 125000 | G69: =F69*D69 -> 1000000
B70: TANK COVER CITY HB BLACK | C70: HENDRIK | D70: 8 | E70: SET | F70: 40000 | G70: =F70*D70 -> 320000
B71: GARNIS LAMPU DEPAN CITY HB BLACK | C71: HENDRIK | D71: 6 | E71: SET | F71: 140000 | G71: =F71*D71 -> 840000
B72: GARNIS LAMPU BELAKANG CITY HB BLACK | C72: HENDRIK | D72: 6 | E72: SET | F72: 160000 | G72: =F72*D72 -> 960000
B73: HANDEL COVER CITY HB CHROME | C73: HENDRIK | D73: 2 | E73: SET | F73: 110000 | G73: =F73*D73 -> 220000
B74: OUTER COVER CITY HB CHROME | C74: HENDRIK | D74: 2 | E74: SET | F74: 125000 | G74: =F74*D74 -> 250000
B75: TANK COVER CITY HB CHROME | C75: HENDRIK | D75: 2 | E75: SET | F75: 40000 | G75: =F75*D75 -> 80000
B76: GARNIS LAMPU DEPAN CITY HB CHROME | C76: HENDRIK | D76: 2 | E76: SET | F76: 140000 | G76: =F76*D76 -> 280000
B77: GARNIS LAMPU BELAKANG CITY HB CHROME | C77: HENDRIK | D77: 2 | E77: SET | F77: 160000 | G77: =F77*D77 -> 320000
A78: 44551 | B78: FRAME ORCA FR-112H MOBILIO/BRIO G TH.2017 | C78: ORCA | D78: 9 | E78: PCS | F78: 180000 | G78: =F78*D78 -> 1620000 | H78: =SUM(G78) -> 1620000 | I78: MEI
A79: 44554 | B79: TALANG AIR H- TECH HITAM ALL NEW PAJERO '16 (D/T) | C79: MR.BOSS | D79: 10 | E79: SET | F79: 123000 | G79: =F79*D79 -> 1230000 | H79: =SUM(G79) -> 1230000 | I79: APRIL | J79: =SUM(H79:H80) -> 2130000
A80: 44554 | B80: SIDE BODY MOULDING (HITAM) ALL NEW RUSH/TERIOS '18 | C80: MR.BOSS | D80: 3 | E80: SET | F80: 300000 | G80: =F80*D80 -> 900000 | H80: =SUM(G80) -> 900000
A81: 44555 | B81: SARUNG JOK MB TECK INNOVA'12 LUXURY (9001+9010) | C81: BUK IDA | D81: 1 | E81: SET | F81: 0 | G81: =F81*D81 -> 0 | H81: =SUM(G81:G82) -> 0
B82: SARUNG JOK MB TECK BRIO SATYA (9001+9005) | C82: BUK IDA | D82: 1 | E82: SET | F82: 0 | G82: =F82*D82 -> 0
A83: 44560 | B83: TUTUP BAN SERAP RUSH | C83: TOYOTA | D83: 1 | E83: PCS | H83: 2000000 | I83: LUNAS TF TGL 30/12/21
B84: TUTUP BAN SERAP FORTUNER | C84: TOYOTA | D84: 2 | E84: PCS
B85: SKITE PLATE BAMPER BELAKANG FORTUNER | C85: TOYOTA | D85: 1 | E85: SET
B86: SKITE PLATE BAMPER BELAKANG INNOVA | C86: TOYOTA | D86: 1 | E86: SET
B87: LIST KACA BELAKANG INNOVA CHROME | C87: TOYOTA | D87: 1 | E87: SET
B88: LIST BODY FORTUNER CHROME | C88: TOYOTA | D88: 1 | E88: SET
B89: LIST BODY INNOVA CHROME | C89: TOYOTA | D89: 1 | E89: SET
B90: REAR LICENSE ORNAMENT FORTUNER CHROME | C90: TOYOTA | D90: 1 | E90: PCS
B91: REAR LICENSE ORNAMENT INNOVA CHROME | C91: TOYOTA | D91: 1 | E91: PCS
B92: TRANK LED FORTUNER CHROME | C92: TOYOTA | D92: 1 | E92: PCS
B93: LITER U INNOVA CHROME | C93: TOYOTA | D93: 1 | E93: PCS
B94: HOOD MOLDING INNOVA CHROME | C94: TOYOTA | D94: 1 | E94: PCS
B95: HOOD MOLDING AVANZA '20CHROME | C95: TOYOTA | D95: 1 | E95: PCS
... B98: KARPET ORIGINAL (BLUDRU) INNOVA '18 '17 | C98: TOYOTA | D98: 1 | E98: SET
A110: 0

Sheet Sheet1
A1: BON JATUH TEMPO JANUARI 2022 ( JT)
A2: NO | B2: TGL BARANG MASUK | C2: NAMA SALES/ SUPLIER | D2: JUMLAH BON | E2: KET
A3: 1 | B3: 44404 | C3: IRWAN | D3: 9900000 | E3: GIRO TGL 20/1/22
A4: 2 | B4: 44410 | C4: HERMAN | D4: 3000000 | E4: GIRO TGL 30/01/2022
A5: 3 | B5: 44411 | C5: IRWAN | D5: 2900000 | E5: GIRO TGL 20/1/22
A6: 4 | B6: 44411 | C6: HERMAN | D6: 4500000 | E6: GIRO TGL 30/01/2022
A7: 5 | B7: 44414 | C7: HERMAN | D7: 9000000 | E7: GIRO TGL 30/01/2022
A8: 6 | B8: 44415 | C8: IRWAN | D8: 4950000 | E8: GIRO TGL 20/1/22
A9: 7 | B9: 44415 | C9: HERMAN | D9: 2225000 | E9: GIRO TGL 30/01/2022
A10: 8 | B10: 44417 | C10: GREAT | D10: 12000000 | E10: LUNAS TF TGL 10/1/22
A11: 9 | B11: 44420 | C11: GREAT | D11: 9000000
A12: 10 | B12: 44426 | C12: GREAT | D12: 3600000
A13: 11 | B13: 44424 | C13: IRWAN | D13: 10550000 | E13: GIRO TGL 20/1/22
A14: 12 | B14: 44424 | C14: HERMAN | D14: 3065000 | E14: GIRO TGL 30/01/2022
A15: 13 | B15: 44426 | C15: HERMAN | D15: 12930000 | E15: GIRO TGL 30/01/2022
A16: 14 | B16: 44427 | C16: IRWAN | D16: 6025000 | E16: GIRO TGL 20/1/22
A17: 15 | B17: 44432 | C17: HERMAN | D17: 6055000 | E17: GIRO TGL 30/01/2022
A18: 16 | B18: 44448 | C18: TJM | D18: 4690000 | E18: GIRO TGL 25/1/22
A19: 17 | B19: 44452 | C19: TJM | D19: 5055000 | E19: GIRO TGL 25/1/22
A20: 18 | B20: 44453 | C20: TJM | D20: 6300000 | E20: GIRO TGL 25/1/22
A21: 19 | B21: 44466 | C21: TJM | D21: 2880000 | E21: GIRO TGL 25/1/22
A22: 20 | B22: 44491 | C22: TJM | D22: 3600000 | E22: GIRO TGL 25/1/22
A23: 21 | B23: 44522 | C23: TJM | D23: 12500000 | E23: LUNAS TF. 31/1/22
C25: TOTAL | D25: =SUM(D3:D24) -> 134725000
C27: GIRO | D27: =D22+D21+D20+D19+D18+D17+D16+D15+D14+D13+D9+D8+D7+D6+D5+D4+D3 -> 97625000

Sheet Sheet2
A1: BON JATUH TEMPO DESEMBER 2021 ( JT)
A2: NO | B2: TGL BARANG MASUK | C2: NAMA SALES/ SUPLIER | D2: JUMLAH BON | E2: KET
A3: 1 | B3: 44354 | C3: IRWAN | D3: 10000000 | E3: GIRO TGL 15/12/21
A4: 2 | B4: 44361 | C4: IRWAN | D4: 7070000
A5: 3 | B5: 44368 | C5: IRWAN | D5: 1320000
A6: 4 | B6: 44375 | C6: IRWAN | D6: 2400000
A7: 5 | B7: 44378 | C7: AM77 | D7: 4400000 | E7: GIRO TGL 15/12/21
A8: 6 | B8: 44383 | C8: AM77 | D8: 5720000 | E8: GIRO TGL 15/12/21
A9: 7 | B9: 44385 | C9: IRWAN | D9: 14425000 | E9: GIRO TGL 15/12/21
A10: 8 | B10: 44387 | C10: ORCA | D10: 2000000 | E10: GIRO TGL 30/12/21
A11: 9 | B11: 44389 | C11: IRWAN | D11: 5825000 | E11: GIRO TGL 15/12/21
A12: 10 | B12: 44398 | C12: AM77 | D12: 2960000 | E12: GIRO TGL 15/12/21
A13: 11 | B13: 44404 | C13: IRWAN | D13: 3670000 | E13: GIRO TGL 15/12/21
A14: 12 | B14: 44421 | C14: MR BOSS | D14: 750000 | E14: GIRO TGL 30/12/21
A15: 13 | B15: 44400 | C15: ORCA | D15: 150000 | E15: GIRO . TGL 30/12/21
A16: 14 | B16: 44464 | C16: MR BOSS | D16: 14645000 | E16: GIRO TGL 30/12/21
A17: 15 | B17: 44481 | C17: OTOPROJECT | D17: 3518400 | E17: LUNAS TF. TGL 2/12/21
A18: 16 | B18: 44483 | C18: TJM | D18: 11190000 | E18: GIRO TGL 25/12/21
... A20: 18 | B20: 44487 | C20: HERMAN (PINJAMAN) | D20: 15000000 | E20: GIRO TGL 12/12/21
A21: 19 | B21: 44498 | C21: V-CENT | D21: 2100000
A22: 20 | B22: 44515 | C22: V-CENT | D22: 3200000
A23: 21 | B23: 44512 | C23: JAYA MADANI | D23: 7200000 | E23: LUNAS TF
A24: 22 | B24: 44539 | C24: WINCOS | D24: 29800000 | E24: LUNAS TF. TGL 29/12/21
A25: 23 | B25: 44551 | C25: HENDRIK | D25: 4892500 | E25: BLM DISC 5%
C27: TOTAL | D27: =SUM(D3:D26) -> 153015900
C29: BELUM DIBAYAR | D29: =D21+D22+D25 -> 10192500
C31: GIRO | D31: =D3+D4+D5+D6+D7+D8+D9+D10+D11+D12+D13+D14+D15+D16+D18+D19+D20 -> 102305000

Sheet Sheet3
A1: BON JATUH TEMPO JANUARI 2022 ( JT)
A2: NO | B2: TGL BARANG MASUK | C2: NAMA SALES/ SUPLIER | D2: JUMLAH BON | E2: KET
A3: 1 | B3: 44404 | C3: IRWAN | D3: 9900000 | E3: GIRO TGL 20/1/22
A4: 2 | B4: 44410 | C4: HERMAN | D4: 3000000 | E4: GIRO TGL 30/01/2022
A5: 3 | B5: 44411 | C5: IRWAN | D5: 2900000 | E5: GIRO TGL 20/1/22
A6: 4 | B6: 44411 | C6: HERMAN | D6: 4500000 | E6: GIRO TGL 30/01/2022
A7: 5 | B7: 44414 | C7: HERMAN | D7: 9000000 | E7: GIRO TGL 30/01/2022
A8: 6 | B8: 44415 | C8: IRWAN | D8: 4950000 | E8: GIRO TGL 20/1/22
A9: 7 | B9: 44415 | C9: HERMAN | D9: 2225000 | E9: GIRO TGL 30/01/2022
A10: 8 | B10: 44417 | C10: GREAT | D10: 12000000 | E10: AWAL
A11: 9 | B11: 44420 | C11: GREAT | D11: 9000000 | E11: pertengahan
A12: 10 | B12: 44426 | C12: GREAT | D12: 3600000
A13: 11 | B13: 44424 | C13: IRWAN | D13: 10550000 | E13: GIRO TGL 20/1/22
A14: 12 | B14: 44424 | C14: HERMAN | D14: 3065000 | E14: GIRO TGL 30/01/2022
A15: 13 | B15: 44426 | C15: HERMAN | D15: 12930000 | E15: GIRO TGL 30/01/2022
A16: 14 | B16: 44427 | C16: IRWAN | D16: 6025000 | E16: GIRO TGL 20/1/22
A17: 15 | B17: 44432 | C17: HERMAN | D17: 6055000 | E17: GIRO TGL 30/01/2022
A18: 16 | B18: 44448 | C18: TJM | D18: 4690000 | E18: GIRO TGL 25/1/22
A19: 17 | B19: 44452 | C19: TJM | D19: 5055000 | E19: GIRO TGL 25/1/22
A20: 18 | B20: 44453 | C20: TJM | D20: 6300000 | E20: GIRO TGL 25/1/22
A21: 19 | B21: 44466 | C21: TJM | D21: 2880000 | E21: GIRO TGL 25/1/22
A22: 20 | B22: 44491 | C22: TJM | D22: 3600000 | E22: GIRO TGL 25/1/22
A23: 21 | B23: 44522 | C23: TJM | D23: 12500000
C25: TOTAL | D25: =SUM(D3:D24) -> 134725000
C27: YG BELUM BYR | D27: =D23+D12+D11+D10 -> 37100000
C29: YG SUDAH GIRO | D29: =D3+D4+D5+D6+D7+D8+D9+D13+D14+D15+D16+D17+D18+D19+D20+D21+D22 -> 97625000
